Workbook
Name cfg_arm1: Settings!$B$7
Name cfg_arm2: Settings!$B$8
Name cfg_arm3: Settings!$B$9
Name cfg_base: Settings!$B$16
Name cfg_concurrent: Settings!$B$6
Name cfg_days: Settings!$B$25
Name cfg_exp: Settings!$B$18
Name cfg_hoursday: Settings!$B$26
Name cfg_mend: Settings!$B$20
Name cfg_mkey: Settings!$B$19
Name cfg_mskip: Settings!$B$21
Name cfg_overhead: Settings!$B$11
Name cfg_pct: Settings!$B$12
Name cfg_ratemult: Settings!$B$10
Name cfg_roster: Settings!$B$5
Name cfg_slope: Settings!$B$17
Name cfg_window: Settings!$B$27
Name list_agility_lap: agility_lap!$A$5:$A$53
Name list_clue_completion: clue_completion!$A$5:$A$40
Name list_gp_value: gp_value!$A$5:$A$92
Name list_item_drop: item_drop!$A$5:$A$329
Name list_minigame_completion: minigame_completion!$A$5:$A$47
Name list_npc_damage: npc_damage!$A$5:$A$109
Name list_npc_kill: npc_kill!$A$5:$A$109
Name list_xp_gain: xp_gain!$A$5:$A$58

Sheet README
A1: MazeRaceBingo - tile balancing workbook
A2: Built against github.com/TiboDeclercq98/mazeracebingo. Estimates expected time to completion (ETC) per tile so you can tune requirements.
B5: 1. How to use it
B6: Step 1 | C6: Open Settings and set your team size, how many players are realistically online at once, how you split them across the three arms, and the event window.
B7: Step 2 | C7: Still on Settings, shape the difficulty curve in section B. That curve is the 'target hours' each tile is scored against - it is what balanced means for your event.
B8: Step 3 | C8: Go to Planner. One row per tile, already sorted START -> Arm 1 -> Arm 2 -> Arm 3 in fog-of-war reveal order, so reading top to bottom is the order players meet them.
B9: Step 4 | C9: Per tile pick a Task type, a Mode, a Target, then up to 24 items from the dropdowns. The dropdowns change to match the task type you picked.
B10: Step 5 | C10: Watch the 'vs target' column. Green = within range, orange = too slow, blue = too easy. Adjust the Target number until it lands where you want.
B11: Step 6 | C11: Check the race forecast on Settings (section D). Slack should be a small positive number - that is a race that finishes with drama rather than one nobody completes.
B12: Step 7 | C12: Copy the JSON column into the taskDefinitions array of your save file.
B15: 2. Colour legend
B16: Blue text on yellow | C16: Input. Type over it. Every rate in this workbook is an editable estimate.
B17: Black text | C17: Formula. Leave alone.
B18: Green text | C18: A link pulling a value from another tab.
B19: Gold row | C19: Key tile (16, 57, 60). All three must be completed before END can be finished.
B20: Orange row | C20: END tile (5).
B21: Pale green row | C21: Skippable tile - a dead end no team is forced to clear.
B24: 3. What the ETC model actually does
B25: The atomic number | C25: Every catalogue entry reduces to r = units of progress per PLAYER-hour. r = (progress per action) x (actions per hour) / (group size). Group size folds raid and mass content in correctly: a 4-man raid at 2 raids/hr costs 2 player-hours per raid, not 0.5.
B26: Mode 'any' | C26: The target is the pooled total. Entries that share a catalogue source are farmed simultaneously, so their rates add. The model takes the FASTEST source group: ETC = target / max(group rate). Seven Zulrah uniques pool into one fat rate; Vorkath and Zulrah do not pool, so the team just farms whichever is quicker.
B27: Mode 'each', random drops | C27: Every listed item must independently reach the target. Items from one source arrive in parallel, so this is a coupon-collector problem. The model uses ETC = sum over items of (solo time / rank), ranking by descending solo time within each source group. For n equally-rare items that reproduces the exact answer H(n)/p; for mixed rarities it is within a few percent of the truth.
B28: Mode 'each', deterministic | C28: Kills, laps, XP and clues are not random, so parallel entries finish together: the model takes the slowest (max). Sequential entries add up (sum). Parallel = Auto means group by source, so different NPCs are sequential by default. Set Parallel = Yes when one activity feeds every entry at once, e.g. Attack, Strength and Defence XP from the same combat method.
B29: Wall-clock | C29: Player-hours / players assigned to that tile + the fixed overhead from Settings. Progress is team-wide, so more players is a straight linear speed-up.
B30: Unlucky column | C30: The 90th-percentile time (change the percentile on Settings). Modelled as a gamma with shape = number of random events needed, so a 1-in-500 single drop has a huge spread and a 200-kill task barely any. Approximate for 'each' mode - treat it as 'this is roughly how bad the tail is', not a precise number.
B31: Race forecast | C31: Fog of war means an arm can only be cleared in order, so an arm's time is the SUM of its forced tiles, and the race is the SLOWEST arm - the team needs all 3 keys and the END path. One bloated tile stalls an entire arm; that is what the 'Longest single tile' line is watching for.
B34: 4. Tab guide
B35: Settings | C35: Global assumptions, the difficulty curve, and the race forecast.
B36: Planner | C36: The working sheet. One row per tile.
B37: Maze | C37: The tile tree read off your maze diagram: parent, arm, depth, role, dead-ends.
B38: npc_kill | C38: Bosses and endgame PvM with kills/hr. Names must match in-game NPC names exactly.
B39: npc_damage | C39: Damage/hr = kills/hr x effective HP, both pulled from npc_kill so you edit once.
B40: xp_gain | C40: One row per skill with an assumed method and XP/hr.
B41: item_drop | C41: The big one. Item, source, drop rate, actions/hr. Source doubles as the pooling key.
B42: agility_lap | C42: The 19 courses the plugin can actually detect. Nothing else will ever fire.
B43: minigame_completion | C43: Minigame plus the chat-message substring the plugin listens for.
B44: clue_completion | C44: The 6 tiers, with acquisition time built into clues/hr.
B45: gp_value | C45: GP/hr by farming method. Only used for ETC - gp_value takes no item list.
B46: Lookup / Calc | C46: Machinery. Do not edit; they rebuild from the tabs above.
B49: 5. Read this before you trust a number
B50: Rates are estimates | C50: Every kills/hr, XP/hr and drop rate here is my best estimate for a competent main account, not gospel. The Confidence column flags how sure I am; anything marked Low, or with VERIFY in the notes, should be checked against the wiki before you build a tile on it. The model is the valuable part - the numbers are a starting point.
B51: Verify every minigame message | C51: minigame_completion fires on a chat substring. A typo means the tile can never be completed, and a string that is too short can fire on unrelated messages. Test each one in-game before the event.
B52: Item names must be exact | C52: item_drop matches the RuneLite item name, npc_kill matches the NPC name. 'Ahrim's hood' works, 'ahrims hood' does not. The Warnings column flags anything not found in the catalogue, but it cannot check names you typed manually.
B53: Stacked drops count quantity | C53: item_drop adds the stack size, not 1 per drop. A task for 100 of a stackable item can finish in a single kill.
B54: npc_kill needs your hitsplat | C54: The plugin only counts NPCs the player personally damaged. Leeching a mass does not count.
B55: gp_value only sees loot | C55: It sums GE value of items from NPC and chest loot events. Skilling profit, alching and merching are invisible to it.
B56: Keys are boobytraps | C56: In the current API, tiles flagged as boobytraps act as keys: /completetile on END is refused until every one of them is done. Your three are 16, 57 and 60.
B57: Traps and chests move the goalposts | C57: Completing a boobytrap raises a random revealed tile's requirement; completing a dead-end chest lowers one by 1. This workbook models the tile as designed, not those random adjustments.

Sheet Settings
A1: Settings - global assumptions
A2: Everything on this sheet drives the ETC model. Blue cells are yours to change.
A4: A. Team & schedule | E4: JSON field names (do not edit)
A5: Roster size (players on the team) | B5: 1 | C5: Reference only. | E5: Task type | F5: Singular field | G5: Plural field
A6: Players online & on-task at once | B6: 1 | C6: Realistic concurrent contributors across the whole team. | E6: npc_kill | F6: npc | G6: npcs
A7: Players working Arm 1 (blue) | B7: 1 | C7: Default players per tile on this arm. The three should add up to the line above. | E7: npc_damage | F7: npc | G7: npcs
A8: Players working Arm 2 (green) | B8: 1 | C8: One team of 5 clears arms one at a time. | E8: xp_gain | F8: skill | G8: skills
A9: Players working Arm 3 (orange) | B9: 1 | C9: Arm 3 holds the END tile. | E9: item_drop | F9: item | G9: items
A10: Rate multiplier (1.00 = catalogue rates) | B10: 1 | C10: 0.7 = casual / mid accounts, 1.0 = competent mains, 1.3 = efficient endgame team. | E10: agility_lap | F10: course | G10: courses
A11: Fixed overhead per tile (minutes) | B11: 12 | C11: Travel, banking, gearing, and working out what the tile even wants. | E11: minigame_completion | F11: minigame | G11: minigame
A12: 'Unlucky' percentile | B12: 0.9 | C12: 0.90 = the time 90% of runs come in under. Drives the Unlucky column. | E12: clue_completion | F12: tier | G12: tiers
E13: gp_value | F13: - | G13: -
A15: B. Difficulty target curve (what you are balancing TOWARD)
A16: Base target - WALL-CLOCK hours at depth 0 | B16: 0.42 | C16: Target time for a tile sitting right next to START.
A17: Target coefficient on depth^exponent | B17: 0.0104 | C17: Target = (base + slope * depth^exp) * role multiplier.
A18: Depth curve exponent | B18: 1.65 | C18: 1 = linear ramp. >1 = back-loaded.
A19: Role multiplier - KEY tile | B19: 1.7 | C19: Tiles 16, 57 and 60 - one in each arm.
A20: Role multiplier - END tile | B20: 2.2 | C20: Tile 5. Needs all 3 keys first.
A21: Role multiplier - Skippable tile | B21: 0.55 | C21: The 10 dead-end tiles nobody is forced to do. Keep them cheap and tempting.
A24: C. Event window
A25: Event length (days) | B25: 30
A26: Playable hours per day | B26: 5 | C26: Per player, realistically.
A27: Total event window (hours) | B27: =cfg_days*cfg_hoursday -> 150
A30: D. Race forecast - fog of war means each arm must be cleared IN ORDER
B31: Arm 1 (blue) | C31: Arm 2 (green) | D31: Arm 3 (orange) | E31: All arms
A32: Tiles on the arm | B32: =COUNTIF(Planner!$B$5:$B$85,"Arm 1") -> 22 | C32: =COUNTIF(Planner!$B$5:$B$85,"Arm 2") -> 27 | D32: =COUNTIF(Planner!$B$5:$B$85,"Arm 3") -> 31 | E32: =COUNTA(Planner!$A$5:$A$85) -> 81
A33: Tiles with a task set | B33: =COUNTIFS(Planner!$B$5:$B$85,"Arm 1",Planner!$F$5:$F$85,"<>") -> 22 | C33: =COUNTIFS(Planner!$B$5:$B$85,"Arm 2",Planner!$F$5:$F$85,"<>") -> 27 | D33: =COUNTIFS(Planner!$B$5:$B$85,"Arm 3",Planner!$F$5:$F$85,"<>") -> 31 | E33: =COUNTIF(Planner!$F$5:$F$85,"<>") -> 81
A34: Forced tiles (must be done) | B34: =COUNTIFS(Planner!$B$5:$B$85,"Arm 1",Planner!$D$5:$D$85,"<>Skippable") -> 19 | C34: =COUNTIFS(Planner!$B$5:$B$85,"Arm 2",Planner!$D$5:$D$85,"<>Skippable") -> 25 | D34: =COUNTIFS(Planner!$B$5:$B$85,"Arm 3",Planner!$D$5:$D$85,"<>Skippable") -> 26 | E34: =COUNTIF(Planner!$D$5:$D$85,"<>Skippable") -> 71
A35: Player-hours, forced tiles | B35: =SUMIFS(Planner!$AL$5:$AL$85,Planner!$B$5:$B$85,"Arm 1",Planner!$D$5:$D$85,"<>Skippable") -> 169.41486 | C35: =SUMIFS(Planner!$AL$5:$AL$85,Planner!$B$5:$B$85,"Arm 2",Planner!$D$5:$D$85,"<>Skippable") -> 214.16877 | D35: =SUMIFS(Planner!$AL$5:$AL$85,Planner!$B$5:$B$85,"Arm 3",Planner!$D$5:$D$85,"<>Skippable") -> 247.12755 | E35: =SUMIFS(Planner!$AL$5:$AL$85,Planner!$D$5:$D$85,"<>Skippable") -> 632.51841
A36: Wall-clock hours, forced tiles | B36: =SUMIFS(Planner!$AM$5:$AM$85,Planner!$B$5:$B$85,"Arm 1",Planner!$D$5:$D$85,"<>Skippable") -> 173.21486 | C36: =SUMIFS(Planner!$AM$5:$AM$85,Planner!$B$5:$B$85,"Arm 2",Planner!$D$5:$D$85,"<>Skippable") -> 219.16877 | D36: =SUMIFS(Planner!$AM$5:$AM$85,Planner!$B$5:$B$85,"Arm 3",Planner!$D$5:$D$85,"<>Skippable") -> 252.32755 | E36: =SUM(B36:D36) -> 644.71118
A37: Wall-clock, all tiles incl. skippable | B37: =SUMIFS(Planner!$AM$5:$AM$85,Planner!$B$5:$B$85,"Arm 1") -> 229.27996 | C37: =SUMIFS(Planner!$AM$5:$AM$85,Planner!$B$5:$B$85,"Arm 2") -> 330.15701 | D37: =SUMIFS(Planner!$AM$5:$AM$85,Planner!$B$5:$B$85,"Arm 3") -> 275.72788 | E37: =SUM(B37:D37) -> 835.16484
A39: PREDICTED RACE LENGTH - one team (hours) | B39: =E36 -> 644.71118 | C39: ONE team of 5 cannot be in three arms at once, and a key sits in EVERY arm (16 = Arm 2, 57 = Arm 3, 60 = Arm 1), so it is the SUM of all arms. If you run 3 teams racing in parallel instead, use the slowest arm: =MAX(B36:D36).
A40: Event window (hours) | B40: =cfg_window -> 150 | C40: From section C above.
A41: Slack (window - race length) | B41: =B40-B39 -> -494.71118 | C41: Negative = nobody finishes. A small positive number = a tight, exciting race.
A42: Longest single tile (wall-clock hrs) | B42: =MAX(Planner!$AM$5:$AM$85) -> 100.2 | C42: Watch for one tile that stalls the whole run.
A43: Tiles over 2x their target | B43: =COUNTIF(Planner!$AM$5:$AM$85,">2") -> 74 | C43: Rebalance these first.
A44: Tiles under 0.5x their target | B44: =COUNTIF(Planner!$AM$5:$AM$85,"<0.5") -> 0 | C44: Free tiles - consider making them meaner.
A45: (parallel variant) slowest arm only | B45: =MAX(B36,C36,D36) -> 252.32755 | C45: Only meaningful if you field one squad per arm.

Sheet Planner
A1: Planner - one row per maze tile
A2: Blue cells are inputs. Choose a task type first: the 24 item dropdowns then offer only entries from that type's tab. Everything right of the item slots is calculated.
A3: Mode 'any' = the target is the TOTAL across all listed entries. Mode 'each' = EVERY listed entry must independently reach the target (the tile requirement becomes items x target). Parallel: Auto = group by catalogue source | Yes = all entries progress at once (e.g. Atk/Str/Def from one combat method) | No = force one at a time.
A4: Tile | B4: Arm | C4: Depth | D4: Role | E4: Chest? | F4: Task type | G4: Mode | H4: Target | I4: Parallel | J4: Rate mult | K4: Players | L4: Item 1 | M4: Item 2 | N4: Item 3 | O4: Item 4 | P4: Item 5 | Q4: Item 6 | R4: Item 7 | S4: Item 8 | T4: Item 9 | U4: Item 10 | V4: Item 11 | W4: Item 12 | X4: Item 13 | Y4: Item 14 | Z4: Item 15 | AA4: Item 16 | AB4: Item 17 | AC4: Item 18 | AD4: Item 19 | AE4: Item 20 | AF4: Item 21 | AG4: Item 22 | AH4: Item 23 | AI4: Item 24 | AJ4: # items | AK4: Units req. | AL4: Player-hours | AM4: Wall-clock hrs | AN4: Wall-clock | AO4: Unlucky hrs | AP4: Target hrs | AQ4: vs target | AR4: Warnings | AS4: Description | AT4: JSON (paste into taskDefinitions)
A5: 77 | B5: =IFERROR(INDEX(Maze!$C$5:$C$85,MATCH($A5,Maze!$A$5:$A$85,0)),"") -> START | C5: =IFERROR(INDEX(Maze!$D$5:$D$85,MATCH($A5,Maze!$A$5:$A$85,0)),"") -> 0 | D5: =IFERROR(INDEX(Maze!$E$5:$E$85,MATCH($A5,Maze!$A$5:$A$85,0)),"") -> START | E5: =IFERROR(INDEX(Maze!$G$5:$G$85,MATCH($A5,Maze!$A$5:$A$85,0)),"") -> No | F5: agility_lap | H5: 150 | L5: Draynor | AJ5: {=SUMPRODUCT(($L5:$AI5<>"")*1)} -> 1 | AK5: =IF($F5="","",IF($G5="each",$AJ5*$H5,$H5)) -> 150 | AL5: =IF($F5="","",IFERROR((IF($G5="each",IF($I5="No",SUM(Calc!$BZ5:$CW5),IF($F5="item_drop",SUM(Calc!$DX5:$EU5),IF($I5="Yes",MAX(Calc!$BZ5:$CW5),SUM(Calc!$BZ5:$CW5)))),$H5/MAX(Calc!$BA5:$BX5)))/IF($J5="",cfg_ratemult,$J5),"")) -> 1.8072289 | AM5: =IF($AL5="","",$AL5/MAX(0.1,IF($K5="",IF($B5="Arm 1",cfg_arm1,IF($B5="Arm 2",cfg_arm2,IF($B5="Arm 3",cfg_arm3,cfg_concurrent))),$K5))+cfg_overhead/60) -> 2.0072289 | AN5: =IF($AM5="","",INT($AM5/24)&"d "&TEXT(MOD($AM5,24),"0.0")&"h") -> 0d 02h | AO5: =IF($AM5="","",$AL5*IFERROR(GAMMAINV(cfg_pct,MAX(1,IF($F5="item_drop",IF($G5="each",$AJ5*$H5,$H5),1000)),1/MAX(1,IF($F5="item_drop",IF($G5="each",$AJ5*$H5,$H5),1000))),1)/MAX(0.1,IF($K5="",IF($B5="Arm 1",cfg_arm1,IF($B5="Arm 2",cfg_arm2,IF($B5="Arm 3",cfg_arm3,cfg_concurrent))),$K5))+cfg_overhead/60) -> 2.0808451 | AP5: =(cfg_base+cfg_slope*$C5^cfg_exp)*IF($D5="KEY",cfg_mkey,IF($D5="END",cfg_mend,IF($D5="Skippable",cfg_mskip,1))) -> 0.42 | AQ5: =IF(OR($AM5="",$AP5=0),"",$AM5/$AP5) -> 4.7791165 | AR5: {=IF($F5="","- no task set -",_xlfn.TEXTJOIN(" | ",TRUE,IF(AND($F5<>"gp_value",$AJ5=0),"no items selected",""),IF(AND($F5="gp_value",$AJ5=0),"pick a farming method so the ETC can be estimated",""),IF(AND($F5="gp_value",$AJ5>1),"gp_value takes no item list - one method is enough",""),IF(AND($F5="minigame_completion",$AJ5>1),"only 1 minigame per tile",""),IF(OR($H5="",$H5<=0),"target missing",""),IF(SUMPRODUCT(($L5:$AE5<>"")*(Calc!$C5:$Z5=0))>0,"unknown entry - not in catalogue",""),IF(AND($G5="each",$AJ5=1),"each with 1 entry = same as any",""),IF($AL5="","ETC not computable","")))} -> #N/A | AS5: Wait this isn't Leagues? | AT5: =IF($F5="","","{"&CHAR(34)&"tileId"&CHAR(34)&":"&$A5&","&CHAR(34)&"taskType"&CHAR(34)&":"&CHAR(34)&$F5&CHAR(34)&","&CHAR(34)&"taskConfig"&CHAR(34)&":{"&IF($F5="gp_value","",IF($F5="minigame_completion",CHAR(34)&"minigame"&CHAR(34)&":"&CHAR(34)&$L5&CHAR(34)&","&CHAR(34)&"message"&CHAR(34)&":"&CHAR(34)&IFERROR(INDEX(minigame_completion!$J$5:$J$47,MATCH($L5,minigame_completion!$A$5:$A$47,0)),"")&CHAR(34)&",",IF($AJ5=1,CHAR(34)&INDEX(Settings!$F$6:$F$13,MATCH($F5,Settings!$E$6:$E$13,0))&CHAR(34)&":"&Calc!$EW5&",",CHAR(34)&INDEX(Settings!$G$6:$G$13,MATCH($F5,Settings!$E$6:$E$13,0))&CHAR(34)&":["&_xlfn.TEXTJOIN(",",TRUE,Calc!$EW5:$FT5)&"],")))&CHAR(34)&"target"&CHAR(34)&":"&$H5&IF($G5="each",","&CHAR(34)&"mode"&CHAR(34)&":"&CHAR(34)&"each"&CHAR(34),"")&"}}") -> {"tileId":77,"taskType":"agility_lap","taskConfig":{"course":"Draynor","target":150}}
A6: 78 | B6: =IFERROR(INDEX(Maze!$C$5:$C$85,MATCH($A6,Maze!$A$5:$A$85,0)),"") -> Arm 1 | C6: =IFERROR(INDEX(Maze!$D$5:$D$85,MATCH($A6,Maze!$A$5:$A$85,0)),"") -> 1 | D6: =IFERROR(INDEX(Maze!$E$5:$E$85,MATCH($A6,Maze!$A$5:$A$85,0)),"") -> Forced | E6: =IFERROR(INDEX(Maze!$G$5:$G$85,MATCH($A6,Maze!$A$5:$A$85,0)),"") -> No | F6: minigame_completion | H6: 100 | L6: Tempoross | AJ6: {=SUMPRODUCT(($L6:$AI6<>"")*1)} -> 1 | AK6: =IF($F6="","",IF($G6="each",$AJ6*$H6,$H6)) -> 100 | AL6: =IF($F6="","",IFERROR((IF($G6="each",IF($I6="No",SUM(Calc!$BZ6:$CW6),IF($F6="item_drop",SUM(Calc!$DX6:$EU6),IF($I6="Yes",MAX(Calc!$BZ6:$CW6),SUM(Calc!$BZ6:$CW6)))),$H6/MAX(Calc!$BA6:$BX6)))/IF($J6="",cfg_ratemult,$J6),"")) -> 11.111111 | AM6: =IF($AL6="","",$AL6/MAX(0.1,IF($K6="",IF($B6="Arm 1",cfg_arm1,IF($B6="Arm 2",cfg_arm2,IF($B6="Arm 3",cfg_arm3,cfg_concurrent))),$K6))+cfg_overhead/60) -> 11.311111 | AN6: =IF($AM6="","",INT($AM6/24)&"d "&TEXT(MOD($AM6,24),"0.0")&"h") -> 0d 11h | AO6: =IF($AM6="","",$AL6*IFERROR(GAMMAINV(cfg_pct,MAX(1,IF($F6="item_drop",IF($G6="each",$AJ6*$H6,$H6),1000)),1/MAX(1,IF($F6="item_drop",IF($G6="each",$AJ6*$H6,$H6),1000))),1)/MAX(0.1,IF($K6="",IF($B6="Arm 1",cfg_arm1,IF($B6="Arm 2",cfg_arm2,IF($B6="Arm 3",cfg_arm3,cfg_concurrent))),$K6))+cfg_overhead/60) -> 11.763715 | AP6: =(cfg_base+cfg_slope*$C6^cfg_exp)*IF($D6="KEY",cfg_mkey,IF($D6="END",cfg_mend,IF($D6="Skippable",cfg_mskip,1))) -> 0.4304 | AQ6: =IF(OR($AM6="",$AP6=0),"",$AM6/$AP6) -> 26.280463 | AR6: =IF($F6="","- no task set -",_xlfn.TEXTJOIN(" | ",TRUE,IF(AND($F6<>"gp_value",$AJ6=0),"no items selected",""),IF(AND($F6="gp_value",$AJ6=0),"pick a farming method so the ETC can be estimated",""),IF(AND($F6="gp_value",$AJ6>1),"gp_value takes no item list - one method is enough",""),IF(AND($F6="minigame_completion",$AJ6>1),"only 1 minigame per tile",""),IF(OR($H6="",$H6<=0),"target missing",""),IF(SUMPRODUCT(($L6:$AE6<>"")*(Calc!$C6:$Z6=0))>0,"unknown entry - not in catalogue",""),IF(AND($G6="each",$AJ6=1),"each with 1 entry = same as any",""),IF($AL6="","ETC not computable",""))) -> #N/A | AS6: Here fishy fishies! | AT6: =IF($F6="","","{"&CHAR(34)&"tileId"&CHAR(34)&":"&$A6&","&CHAR(34)&"taskType"&CHAR(34)&":"&CHAR(34)&$F6&CHAR(34)&","&CHAR(34)&"taskConfig"&CHAR(34)&":{"&IF($F6="gp_value","",IF($F6="minigame_completion",CHAR(34)&"minigame"&CHAR(34)&":"&CHAR(34)&$L6&CHAR(34)&","&CHAR(34)&"message"&CHAR(34)&":"&CHAR(34)&IFERROR(INDEX(minigame_completion!$J$5:$J$47,MATCH($L6,minigame_completion!$A$5:$A$47,0)),"")&CHAR(34)&",",IF($AJ6=1,CHAR(34)&INDEX(Settings!$F$6:$F$13,MATCH($F6,Settings!$E$6:$E$13,0))&CHAR(34)&":"&Calc!$EW6&",",CHAR(34)&INDEX(Settings!$G$6:$G$13,MATCH($F6,Settings!$E$6:$E$13,0))&CHAR(34)&":["&_xlfn.TEXTJOIN(",",TRUE,Calc!$EW6:$FT6)&"],")))&CHAR(34)&"target"&CHAR(34)&":"&$H6&IF($G6="each",","&CHAR(34)&"mode"&CHAR(34)&":"&CHAR(34)&"each"&CHAR(34),"")&"}}") -> {"tileId":78,"taskType":"minigame_completion","taskConfig":{"minigame":"Tempoross","message":"Tempoross kill count is","target":100}}
A7: 69 | B7: =IFERROR(INDEX(Maze!$C$5:$C$85,MATCH($A7,Maze!$A$5:$A$85,0)),"") -> Arm 1 | C7: =IFERROR(INDEX(Maze!$D$5:$D$85,MATCH($A7,Maze!$A$5:$A$85,0)),"") -> 2 | D7: =IFERROR(INDEX(Maze!$E$5:$E$85,MATCH($A7,Maze!$A$5:$A$85,0)),"") -> Forced | E7: =IFERROR(INDEX(Maze!$G$5:$G$85,MATCH($A7,Maze!$A$5:$A$85,0)),"") -> No | F7: clue_completion | H7: 50 | L7: beginner | AJ7: {=SUMPRODUCT(($L7:$AI7<>"")*1)} -> 1 | AK7: =IF($F7="","",IF($G7="each",$AJ7*$H7,$H7)) -> 50 | AL7: =IF($F7="","",IFERROR((IF($G7="each",IF($I7="No",SUM(Calc!$BZ7:$CW7),IF($F7="item_drop",SUM(Calc!$DX7:$EU7),IF($I7="Yes",MAX(Calc!$BZ7:$CW7),SUM(Calc!$BZ7:$CW7)))),$H7/MAX(Calc!$BA7:$BX7)))/IF($J7="",cfg_ratemult,$J7),"")) -> 2.5 | AM7: =IF($AL7="","",$AL7/MAX(0.1,IF($K7="",IF($B7="Arm 1",cfg_arm1,IF($B7="Arm 2",cfg_arm2,IF($B7="Arm 3",cfg_arm3,cfg_concurrent))),$K7))+cfg_overhead/60) -> 2.7 | AN7: =IF($AM7="","",INT($AM7/24)&"d "&TEXT(MOD($AM7,24),"0.0")&"h") -> 0d 03h | AO7: =IF($AM7="","",$AL7*IFERROR(GAMMAINV(cfg_pct,MAX(1,IF($F7="item_drop",IF($G7="each",$AJ7*$H7,$H7),1000)),1/MAX(1,IF($F7="item_drop",IF($G7="each",$AJ7*$H7,$H7),1000))),1)/MAX(0.1,IF($K7="",IF($B7="Arm 1",cfg_arm1,IF($B7="Arm 2",cfg_arm2,IF($B7="Arm 3",cfg_arm3,cfg_concurrent))),$K7))+cfg_overhead/60) -> 2.8018358 | AP7: =(cfg_base+cfg_slope*$C7^cfg_exp)*IF($D7="KEY",cfg_mkey,IF($D7="END",cfg_mend,IF($D7="Skippable",cfg_mskip,1))) -> 0.4526387 | AQ7: =IF(OR($AM7="",$AP7=0),"",$AM7/$AP7) -> 5.9650225 | AR7: =IF($F7="","- no task set -",_xlfn.TEXTJOIN(" | ",TRUE,IF(AND($F7<>"gp_value",$AJ7=0),"no items selected",""),IF(AND($F7="gp_value",$AJ7=0),"pick a farming method so the ETC can be estimated",""),IF(AND($F7="gp_value",$AJ7>1),"gp_value takes no item list - one method is enough",""),IF(AND($F7="minigame_completion",$AJ7>1),"only 1 minigame per tile",""),IF(OR($H7="",$H7<=0),"target missing",""),IF(SUMPRODUCT(($L7:$AE7<>"")*(Calc!$C7:$Z7=0))>0,"unknown entry - not in catalogue",""),IF(AND($G7="each",$AJ7=1),"each with 1 entry = same as any",""),IF($AL7="","ETC not computable",""))) -> #N/A | AS7: In the beninging | AT7: =IF($F7="","","{"&CHAR(34)&"tileId"&CHAR(34)&":"&$A7&","&CHAR(34)&"taskType"&CHAR(34)&":"&CHAR(34)&$F7&CHAR(34)&","&CHAR(34)&"taskConfig"&CHAR(34)&":{"&IF($F7="gp_value","",IF($F7="minigame_completion",CHAR(34)&"minigame"&CHAR(34)&":"&CHAR(34)&$L7&CHAR(34)&","&CHAR(34)&"message"&CHAR(34)&":"&CHAR(34)&IFERROR(INDEX(minigame_completion!$J$5:$J$47,MATCH($L7,minigame_completion!$A$5:$A$47,0)),"")&CHAR(34)&",",IF($AJ7=1,CHAR(34)&INDEX(Settings!$F$6:$F$13,MATCH($F7,Settings!$E$6:$E$13,0))&CHAR(34)&":"&Calc!$EW7&",",CHAR(34)&INDEX(Settings!$G$6:$G$13,MATCH($F7,Settings!$E$6:$E$13,0))&CHAR(34)&":["&_xlfn.TEXTJOIN(",",TRUE,Calc!$EW7:$FT7)&"],")))&CHAR(34)&"target"&CHAR(34)&":"&$H7&IF($G7="each",","&CHAR(34)&"mode"&CHAR(34)&":"&CHAR(34)&"each"&CHAR(34),"")&"}}") -> {"tileId":69,"taskType":"clue_completion","taskConfig":{"tier":"beginner","target":50}}
A8: 70 | B8: =IFERROR(INDEX(Maze!$C$5:$C$85,MATCH($A8,Maze!$A$5:$A$85,0)),"") -> Arm 1 | C8: =IFERROR(INDEX(Maze!$D$5:$D$85,MATCH($A8,Maze!$A$5:$A$85,0)),"") -> 3 | D8: =IFERROR(INDEX(Maze!$E$5:$E$85,MATCH($A8,Maze!$A$5:$A$85,0)),"") -> Forced | E8: =IFERROR(INDEX(Maze!$G$5:$G$85,MATCH($A8,Maze!$A$5:$A$85,0)),"") -> No | F8: npc_kill | H8: 50 | L8: Obor | AJ8: {=SUMPRODUCT(($L8:$AI8<>"")*1)} -> 1 | AK8: =IF($F8="","",IF($G8="each",$AJ8*$H8,$H8)) -> 50 | AL8: =IF($F8="","",IFERROR((IF($G8="each",IF($I8="No",SUM(Calc!$BZ8:$CW8),IF($F8="item_drop",SUM(Calc!$DX8:$EU8),IF($I8="Yes",MAX(Calc!$BZ8:$CW8),SUM(Calc!$BZ8:$CW8)))),$H8/MAX(Calc!$BA8:$BX8)))/IF($J8="",cfg_ratemult,$J8),"")) -> 1.6666667 | AM8: =IF($AL8="","",$AL8/MAX(0.1,IF($K8="",IF($B8="Arm 1",cfg_arm1,IF($B8="Arm 2",cfg_arm2,IF($B8="Arm 3",cfg_arm3,cfg_concurrent))),$K8))+cfg_overhead/60) -> 1.8666667 | AN8: =IF($AM8="","",INT($AM8/24)&"d "&TEXT(MOD($AM8,24),"0.0")&"h") -> 0d 02h | AO8: =IF($AM8="","",$AL8*IFERROR(GAMMAINV(cfg_pct,MAX(1,IF($F8="item_drop",IF($G8="each",$AJ8*$H8,$H8),1000)),1/MAX(1,IF($F8="item_drop",IF($G8="each",$AJ8*$H8,$H8),1000))),1)/MAX(0.1,IF($K8="",IF($B8="Arm 1",cfg_arm1,IF($B8="Arm 2",cfg_arm2,IF($B8="Arm 3",cfg_arm3,cfg_concurrent))),$K8))+cfg_overhead/60) -> 1.9345572 | AP8: =(cfg_base+cfg_slope*$C8^cfg_exp)*IF($D8="KEY",cfg_mkey,IF($D8="END",cfg_mend,IF($D8="Skippable",cfg_mskip,1))) -> 0.48372112 | AQ8: =IF(OR($AM8="",$AP8=0),"",$AM8/$AP8) -> 3.8589728 | AR8: =IF($F8="","- no task set -",_xlfn.TEXTJOIN(" | ",TRUE,IF(AND($F8<>"gp_value",$AJ8=0),"no items selected",""),IF(AND($F8="gp_value",$AJ8=0),"pick a farming method so the ETC can be estimated",""),IF(AND($F8="gp_value",$AJ8>1),"gp_value takes no item list - one method is enough",""),IF(AND($F8="minigame_completion",$AJ8>1),"only 1 minigame per tile",""),IF(OR($H8="",$H8<=0),"target missing",""),IF(SUMPRODUCT(($L8:$AE8<>"")*(Calc!$C8:$Z8=0))>0,"unknown entry - not in catalogue",""),IF(AND($G8="each",$AJ8=1),"each with 1 entry = same as any",""),IF($AL8="","ETC not computable",""))) -> #N/A | AS8: You're gonna need some keys | AT8: =IF($F8="","","{"&CHAR(34)&"tileId"&CHAR(34)&":"&$A8&","&CHAR(34)&"taskType"&CHAR(34)&":"&CHAR(34)&$F8&CHAR(34)&","&CHAR(34)&"taskConfig"&CHAR(34)&":{"&IF($F8="gp_value","",IF($F8="minigame_completion",CHAR(34)&"minigame"&CHAR(34)&":"&CHAR(34)&$L8&CHAR(34)&","&CHAR(34)&"message"&CHAR(34)&":"&CHAR(34)&IFERROR(INDEX(minigame_completion!$J$5:$J$47,MATCH($L8,minigame_completion!$A$5:$A$47,0)),"")&CHAR(34)&",",IF($AJ8=1,CHAR(34)&INDEX(Settings!$F$6:$F$13,MATCH($F8,Settings!$E$6:$E$13,0))&CHAR(34)&":"&Calc!$EW8&",",CHAR(34)&INDEX(Settings!$G$6:$G$13,MATCH($F8,Settings!$E$6:$E$13,0))&CHAR(34)&":["&_xlfn.TEXTJOIN(",",TRUE,Calc!$EW8:$FT8)&"],")))&CHAR(34)&"target"&CHAR(34)&":"&$H8&IF($G8="each",","&CHAR(34)&"mode"&CHAR(34)&":"&CHAR(34)&"each"&CHAR(34),"")&"}}") -> {"tileId":70,"taskType":"npc_kill","taskConfig":{"npc":"Obor","target":50}}
A9: 71 | B9: =IFERROR(INDEX(Maze!$C$5:$C$85,MATCH($A9,Maze!$A$5:$A$85,0)),"") -> Arm 1 | C9: =IFERROR(INDEX(Maze!$D$5:$D$85,MATCH($A9,Maze!$A$5:$A$85,0)),"") -> 4 | D9: =IFERROR(INDEX(Maze!$E$5:$E$85,MATCH($A9,Maze!$A$5:$A$85,0)),"") -> Forced | E9: =IFERROR(INDEX(Maze!$G$5:$G$85,MATCH($A9,Maze!$A$5:$A$85,0)),"") -> No | F9: npc_kill | H9: 50 | L9: Amoxliatl | AJ9: {=SUMPRODUCT(($L9:$AI9<>"")*1)} -> 1 | AK9: =IF($F9="","",IF($G9="each",$AJ9*$H9,$H9)) -> 50 | AL9: =IF($F9="","",IFERROR((IF($G9="each",IF($I9="No",SUM(Calc!$BZ9:$CW9),IF($F9="item_drop",SUM(Calc!$DX9:$EU9),IF($I9="Yes",MAX(Calc!$BZ9:$CW9),SUM(Calc!$BZ9:$CW9)))),$H9/MAX(Calc!$BA9:$BX9)))/IF($J9="",cfg_ratemult,$J9),"")) -> 0.71428571 | AM9: =IF($AL9="","",$AL9/MAX(0.1,IF($K9="",IF($B9="Arm 1",cfg_arm1,IF($B9="Arm 2",cfg_arm2,IF($B9="Arm 3",cfg_arm3,cfg_concurrent))),$K9))+cfg_overhead/60) -> 0.91428571 | AN9: =IF($AM9="","",INT($AM9/24)&"d "&TEXT(MOD($AM9,24),"0.0")&"h") -> 0d 01h | AO9: =IF($AM9="","",$AL9*IFERROR(GAMMAINV(cfg_pct,MAX(1,IF($F9="item_drop",IF($G9="each",$AJ9*$H9,$H9),1000)),1/MAX(1,IF($F9="item_drop",IF($G9="each",$AJ9*$H9,$H9),1000))),1)/MAX(0.1,IF($K9="",IF($B9="Arm 1",cfg_arm1,IF($B9="Arm 2",cfg_arm2,IF($B9="Arm 3",cfg_arm3,cfg_concurrent))),$K9))+cfg_overhead/60) -> 0.94338165 | AP9: =(cfg_base+cfg_slope*$C9^cfg_exp)*IF($D9="KEY",cfg_mkey,IF($D9="END",cfg_mend,IF($D9="Skippable",cfg_mskip,1))) -> 0.52243122 | AQ9: =IF(OR($AM9="",$AP9=0),"",$AM9/$AP9) -> 1.7500595 | AR9: =IF($F9="","- no task set -",_xlfn.TEXTJOIN(" | ",TRUE,IF(AND($F9<>"gp_value",$AJ9=0),"no items selected",""),IF(AND($F9="gp_value",$AJ9=0),"pick a farming method so the ETC can be estimated",""),IF(AND($F9="gp_value",$AJ9>1),"gp_value takes no item list - one method is enough",""),IF(AND($F9="minigame_completion",$AJ9>1),"only 1 minigame per tile",""),IF(OR($H9="",$H9<=0),"target missing",""),IF(SUMPRODUCT(($L9:$AE9<>"")*(Calc!$C9:$Z9=0))>0,"unknown entry - not in catalogue",""),IF(AND($G9="each",$AJ9=1),"each with 1 entry = same as any",""),IF($AL9="","ETC not computable",""))) -> #N/A | AS9: I think that's a Pokémon | AT9: =IF($F9="","","{"&CHAR(34)&"tileId"&CHAR(34)&":"&$A9&","&CHAR(34)&"taskType"&CHAR(34)&":"&CHAR(34)&$F9&CHAR(34)&","&CHAR(34)&"taskConfig"&CHAR(34)&":{"&IF($F9="gp_value","",IF($F9="minigame_completion",CHAR(34)&"minigame"&CHAR(34)&":"&CHAR(34)&$L9&CHAR(34)&","&CHAR(34)&"message"&CHAR(34)&":"&CHAR(34)&IFERROR(INDEX(minigame_completion!$J$5:$J$47,MATCH($L9,minigame_completion!$A$5:$A$47,0)),"")&CHAR(34)&",",IF($AJ9=1,CHAR(34)&INDEX(Settings!$F$6:$F$13,MATCH($F9,Settings!$E$6:$E$13,0))&CHAR(34)&":"&Calc!$EW9&",",CHAR(34)&INDEX(Settings!$G$6:$G$13,MATCH($F9,Settings!$E$6:$E$13,0))&CHAR(34)&":["&_xlfn.TEXTJOIN(",",TRUE,Calc!$EW9:$FT9)&"],")))&CHAR(34)&"target"&CHAR(34)&":"&$H9&IF($G9="each",","&CHAR(34)&"mode"&CHAR(34)&":"&CHAR(34)&"each"&CHAR(34),"")&"}}") -> {"tileId":71,"taskType":"npc_kill","taskConfig":{"npc":"Amoxliatl","target":50}}
A10: 80 | B10: =IFERROR(INDEX(Maze!$C$5:$C$85,MATCH($A10,Maze!$A$5:$A$85,0)),"") -> Arm 1 | C10: =IFERROR(INDEX(Maze!$D$5:$D$85,MATCH($A10,Maze!$A$5:$A$85,0)),"") -> 5 | D10: =IFERROR(INDEX(Maze!$E$5:$E$85,MATCH($A10,Maze!$A$5:$A$85,0)),"") -> Forced | E10: =IFERROR(INDEX(Maze!$G$5:$G$85,MATCH($A10,Maze!$A$5:$A$85,0)),"") -> No | F10: item_drop | H10: 1 | L10: Sarachnis cudgel | AJ10: {=SUMPRODUCT(($L10:$AI10<>"")*1)} -> 1 | AK10: =IF($F10="","",IF($G10="each",$AJ10*$H10,$H10)) -> 1 | AL10: =IF($F10="","",IFERROR((IF($G10="each",IF($I10="No",SUM(Calc!$BZ10:$CW10),IF($F10="item_drop",SUM(Calc!$DX10:$EU10),IF($I10="Yes",MAX(Calc!$BZ10:$CW10),SUM(Calc!$BZ10:$CW10)))),$H10/MAX(Calc!$BA10:$BX10)))/IF($J10="",cfg_ratemult,$J10),"")) -> 6.4 | AM10: =IF($AL10="","",$AL10/MAX(0.1,IF($K10="",IF($B10="Arm 1",cfg_arm1,IF($B10="Arm 2",cfg_arm2,IF($B10="Arm 3",cfg_arm3,cfg_concurrent))),$K10))+cfg_overhead/60) -> 6.6 | AN10: =IF($AM10="","",INT($AM10/24)&"d "&TEXT(MOD($AM10,24),"0.0")&"h") -> 0d 07h | AO10: =IF($AM10="","",$AL10*IFERROR(GAMMAINV(cfg_pct,MAX(1,IF($F10="item_drop",IF($G10="each",$AJ10*$H10,$H10),1000)),1/MAX(1,IF($F10="item_drop",IF($G10="each",$AJ10*$H10,$H10),1000))),1)/MAX(0.1,IF($K10="",IF($B10="Arm 1",cfg_arm1,IF($B10="Arm 2",cfg_arm2,IF($B10="Arm 3",cfg_arm3,cfg_concurrent))),$K10))+cfg_overhead/60) -> 14.936545 | AP10: =(cfg_base+cfg_slope*$C10^cfg_exp)*IF($D10="KEY",cfg_mkey,IF($D10="END",cfg_mend,IF($D10="Skippable",cfg_mskip,1))) -> 0.56802458 | AQ10: =IF(OR($AM10="",$AP10=0),"",$AM10/$AP10) -> 11.619215 | AR10: =IF($F10="","- no task set -",_xlfn.TEXTJOIN(" | ",TRUE,IF(AND($F10<>"gp_value",$AJ10=0),"no items selected",""),IF(AND($F10="gp_value",$AJ10=0),"pick a farming method so the ETC can be estimated",""),IF(AND($F10="gp_value",$AJ10>1),"gp_value takes no item list - one method is enough",""),IF(AND($F10="minigame_completion",$AJ10>1),"only 1 minigame per tile",""),IF(OR($H10="",$H10<=0),"target missing",""),IF(SUMPRODUCT(($L10:$AE10<>"")*(Calc!$C10:$Z10=0))>0,"unknown entry - not in catalogue",""),IF(AND($G10="each",$AJ10=1),"each with 1 entry = same as any",""),IF($AL10="","ETC not computable",""))) -> #N/A | AS10: Bonk! | AT10: =IF($F10="","","{"&CHAR(34)&"tileId"&CHAR(34)&":"&$A10&","&CHAR(34)&"taskType"&CHAR(34)&":"&CHAR(34)&$F10&CHAR(34)&","&CHAR(34)&"taskConfig"&CHAR(34)&":{"&IF($F10="gp_value","",IF($F10="minigame_completion",CHAR(34)&"minigame"&CHAR(34)&":"&CHAR(34)&$L10&CHAR(34)&","&CHAR(34)&"message"&CHAR(34)&":"&CHAR(34)&IFERROR(INDEX(minigame_completion!$J$5:$J$47,MATCH($L10,minigame_completion!$A$5:$A$47,0)),"")&CHAR(34)&",",IF($AJ10=1,CHAR(34)&INDEX(Settings!$F$6:$F$13,MATCH($F10,Settings!$E$6:$E$13,0))&CHAR(34)&":"&Calc!$EW10&",",CHAR(34)&INDEX(Settings!$G$6:$G$13,MATCH($F10,Settings!$E$6:$E$13,0))&CHAR(34)&":["&_xlfn.TEXTJOIN(",",TRUE,Calc!$EW10:$FT10)&"],")))&CHAR(34)&"target"&CHAR(34)&":"&$H10&IF($G10="each",","&CHAR(34)&"mode"&CHAR(34)&":"&CHAR(34)&"each"&CHAR(34),"")&"}}") -> {"tileId":80,"taskType":"item_drop","taskConfig":{"item":"Sarachnis cudgel","target":1}}
A11: 79 | B11: =IFERROR(INDEX(Maze!$C$5:$C$85,MATCH($A11,Maze!$A$5:$A$85,0)),"") -> Arm 1 | C11: =IFERROR(INDEX(Maze!$D$5:$D$85,MATCH($A11,Maze!$A$5:$A$85,0)),"") -> 6 | D11: =IFERROR(INDEX(Maze!$E$5:$E$85,MATCH($A11,Maze!$A$5:$A$85,0)),"") -> Skippable | E11: =IFERROR(INDEX(Maze!$G$5:$G$85,MATCH($A11,Maze!$A$5:$A$85,0)),"") -> Yes | F11: npc_kill | H11: 1000 | L11: Giant Mole | AJ11: {=SUMPRODUCT(($L11:$AI11<>"")*1)} -> 1 | AK11: =IF($F11="","",IF($G11="each",$AJ11*$H11,$H11)) -> 1000 | AL11: =IF($F11="","",IFERROR((IF($G11="each",IF($I11="No",SUM(Calc!$BZ11:$CW11),IF($F11="item_drop",SUM(Calc!$DX11:$EU11),IF($I11="Yes",MAX(Calc!$BZ11:$CW11),SUM(Calc!$BZ11:$CW11)))),$H11/MAX(Calc!$BA11:$BX11)))/IF($J11="",cfg_ratemult,$J11),"")) -> 20 | AM11: =IF($AL11="","",$AL11/MAX(0.1,IF($K11="",IF($B11="Arm 1",cfg_arm1,IF($B11="Arm 2",cfg_arm2,IF($B11="Arm 3",cfg_arm3,cfg_concurrent))),$K11))+cfg_overhead/60) -> 20.2 | AN11: =IF($AM11="","",INT($AM11/24)&"d "&TEXT(MOD($AM11,24),"0.0")&"h") -> 0d 20h | AO11: =IF($AM11="","",$AL11*IFERROR(GAMMAINV(cfg_pct,MAX(1,IF($F11="item_drop",IF($G11="each",$AJ11*$H11,$H11),1000)),1/MAX(1,IF($F11="item_drop",IF($G11="each",$AJ11*$H11,$H11),1000))),1)/MAX(0.1,IF($K11="",IF($B11="Arm 1",cfg_arm1,IF($B11="Arm 2",cfg_arm2,IF($B11="Arm 3",cfg_arm3,cfg_concurrent))),$K11))+cfg_overhead/60) -> 21.014686 | AP11: =(cfg_base+cfg_slope*$C11^cfg_exp)*IF($D11="KEY",cfg_mkey,IF($D11="END",cfg_mend,IF($D11="Skippable",cfg_mskip,1))) -> 0.34098807 | AQ11: =IF(OR($AM11="",$AP11=0),"",$AM11/$AP11) -> 59.239609 | AR11: =IF($F11="","- no task set -",_xlfn.TEXTJOIN(" | ",TRUE,IF(AND($F11<>"gp_value",$AJ11=0),"no items selected",""),IF(AND($F11="gp_value",$AJ11=0),"pick a farming method so the ETC can be estimated",""),IF(AND($F11="gp_value",$AJ11>1),"gp_value takes no item list - one method is enough",""),IF(AND($F11="minigame_completion",$AJ11>1),"only 1 minigame per tile",""),IF(OR($H11="",$H11<=0),"target missing",""),IF(SUMPRODUCT(($L11:$AE11<>"")*(Calc!$C11:$Z11=0))>0,"unknown entry - not in catalogue",""),IF(AND($G11="each",$AJ11=1),"each with 1 entry = same as any",""),IF($AL11="","ETC not computable",""))) -> #N/A | AS11: Whack-A-Mole | AT11: =IF($F11="","","{"&CHAR(34)&"tileId"&CHAR(34)&":"&$A11&","&CHAR(34)&"taskType"&CHAR(34)&":"&CHAR(34)&$F11&CHAR(34)&","&CHAR(34)&"taskConfig"&CHAR(34)&":{"&IF($F11="gp_value","",IF($F11="minigame_completion",CHAR(34)&"minigame"&CHAR(34)&":"&CHAR(34)&$L11&CHAR(34)&","&CHAR(34)&"message"&CHAR(34)&":"&CHAR(34)&IFERROR(INDEX(minigame_completion!$J$5:$J$47,MATCH($L11,minigame_completion!$A$5:$A$47,0)),"")&CHAR(34)&",",IF($AJ11=1,CHAR(34)&INDEX(Settings!$F$6:$F$13,MATCH($F11,Settings!$E$6:$E$13,0))&CHAR(34)&":"&Calc!$EW11&",",CHAR(34)&INDEX(Settings!$G$6:$G$13,MATCH($F11,Settings!$E$6:$E$13,0))&CHAR(34)&":["&_xlfn.TEXTJOIN(",",TRUE,Calc!$EW11:$FT11)&"],")))&CHAR(34)&"target"&CHAR(34)&":"&$H11&IF($G11="each",","&CHAR(34)&"mode"&CHAR(34)&":"&CHAR(34)&"each"&CHAR(34),"")&"}}") -> {"tileId":79,"taskType":"npc_kill","taskConfig":{"npc":"Giant Mole","target":1000}}
A12: 81 | B12: =IFERROR(INDEX(Maze!$C$5:$C$85,MATCH($A12,Maze!$A$5:$A$85,0)),"") -> Arm 1 | C12: =IFERROR(INDEX(Maze!$D$5:$D$85,MATCH($A12,Maze!$A$5:$A$85,0)),"") -> 6 | D12: =IFERROR(INDEX(Maze!$E$5:$E$85,MATCH($A12,Maze!$A$5:$A$85,0)),"") -> Forced | E12: =IFERROR(INDEX(Maze!$G$5:$G$85,MATCH($A12,Maze!$A$5:$A$85,0)),"") -> No | F12: npc_kill | H12: 250 | L12: Kraken | AJ12: {=SUMPRODUCT(($L12:$AI12<>"")*1)} -> 1 | AK12: =IF($F12="","",IF($G12="each",$AJ12*$H12,$H12)) -> 250 | AL12: =IF($F12="","",IFERROR((IF($G12="each",IF($I12="No",SUM(Calc!$BZ12:$CW12),IF($F12="item_drop",SUM(Calc!$DX12:$EU12),IF($I12="Yes",MAX(Calc!$BZ12:$CW12),SUM(Calc!$BZ12:$CW12)))),$H12/MAX(Calc!$BA12:$BX12)))/IF($J12="",cfg_ratemult,$J12),"")) -> 4.1666667 | AM12: =IF($AL12="","",$AL12/MAX(0.1,IF($K12="",IF($B12="Arm 1",cfg_arm1,IF($B12="Arm 2",cfg_arm2,IF($B12="Arm 3",cfg_arm3,cfg_concurrent))),$K12))+cfg_overhead/60) -> 4.3666667 | AN12: =IF($AM12="","",INT($AM12/24)&"d "&TEXT(MOD($AM12,24),"0.0")&"h") -> 0d 04h | AO12: =IF($AM12="","",$AL12*IFERROR(GAMMAINV(cfg_pct,MAX(1,IF($F12="item_drop",IF($G12="each",$AJ12*$H12,$H12),1000)),1/MAX(1,IF($F12="item_drop",IF($G12="each",$AJ12*$H12,$H12),1000))),1)/MAX(0.1,IF($K12="",IF($B12="Arm 1",cfg_arm1,IF($B12="Arm 2",cfg_arm2,IF($B12="Arm 3",cfg_arm3,cfg_concurrent))),$K12))+cfg_overhead/60) -> 4.536393 | AP12: =(cfg_base+cfg_slope*$C12^cfg_exp)*IF($D12="KEY",cfg_mkey,IF($D12="END",cfg_mend,IF($D12="Skippable",cfg_mskip,1))) -> 0.61997831 | AQ12: =IF(OR($AM12="",$AP12=0),"",$AM12/$AP12) -> 7.0432571 | AR12: =IF($F12="","- no task set -",_xlfn.TEXTJOIN(" | ",TRUE,IF(AND($F12<>"gp_value",$AJ12=0),"no items selected",""),IF(AND($F12="gp_value",$AJ12=0),"pick a farming method so the ETC can be estimated",""),IF(AND($F12="gp_value",$AJ12>1),"gp_value takes no item list - one method is enough",""),IF(AND($F12="minigame_completion",$AJ12>1),"only 1 minigame per tile",""),IF(OR($H12="",$H12<=0),"target missing",""),IF(SUMPRODUCT(($L12:$AE12<>"")*(Calc!$C12:$Z12=0))>0,"unknown entry - not in catalogue",""),IF(AND($G12="each",$AJ12=1),"each with 1 entry = same as any",""),IF($AL12="","ETC not computable",""))) -> #N/A | AS12: The special kind of anime | AT12: =IF($F12="","","{"&CHAR(34)&"tileId"&CHAR(34)&":"&$A12&","&CHAR(34)&"taskType"&CHAR(34)&":"&CHAR(34)&$F12&CHAR(34)&","&CHAR(34)&"taskConfig"&CHAR(34)&":{"&IF($F12="gp_value","",IF($F12="minigame_completion",CHAR(34)&"minigame"&CHAR(34)&":"&CHAR(34)&$L12&CHAR(34)&","&CHAR(34)&"message"&CHAR(34)&":"&CHAR(34)&IFERROR(INDEX(minigame_completion!$J$5:$J$47,MATCH($L12,minigame_completion!$A$5:$A$47,0)),"")&CHAR(34)&",",IF($AJ12=1,CHAR(34)&INDEX(Settings!$F$6:$F$13,MATCH($F12,Settings!$E$6:$E$13,0))&CHAR(34)&":"&Calc!$EW12&",",CHAR(34)&INDEX(Settings!$G$6:$G$13,MATCH($F12,Settings!$E$6:$E$13,0))&CHAR(34)&":["&_xlfn.TEXTJOIN(",",TRUE,Calc!$EW12:$FT12)&"],")))&CHAR(34)&"target"&CHAR(34)&":"&$H12&IF($G12="each",","&CHAR(34)&"mode"&CHAR(34)&":"&CHAR(34)&"each"&CHAR(34),"")&"}}") -> {"tileId":81,"taskType":"npc_kill","taskConfig":{"npc":"Kraken","target":250}}
A13: 72 | B13: =IFERROR(INDEX(Maze!$C$5:$C$85,MATCH($A13,Maze!$A$5:$A$85,0)),"") -> Arm 1 | C13: =IFERROR(INDEX(Maze!$D$5:$D$85,MATCH($A13,Maze!$A$5:$A$85,0)),"") -> 7 | D13: =IFERROR(INDEX(Maze!$E$5:$E$85,MATCH($A13,Maze!$A$5:$A$85,0)),"") -> Forced | E13: =IFERROR(INDEX(Maze!$G$5:$G$85,MATCH($A13,Maze!$A$5:$A$85,0)),"") -> No | F13: item_drop | H13: 3 | L13: Kbd heads | AJ13: {=SUMPRODUCT(($L13:$AI13<>"")*1)} -> 1 | AK13: =IF($F13="","",IF($G13="each",$AJ13*$H13,$H13)) -> 3 | AL13: =IF($F13="","",IFERROR((IF($G13="each",IF($I13="No",SUM(Calc!$BZ13:$CW13),IF($F13="item_drop",SUM(Calc!$DX13:$EU13),IF($I13="Yes",MAX(Calc!$BZ13:$CW13),SUM(Calc!$BZ13:$CW13)))),$H13/MAX(Calc!$BA13:$BX13)))/IF($J13="",cfg_ratemult,$J13),"")) -> 12.8 | AM13: =IF($AL13="","",$AL13/MAX(0.1,IF($K13="",IF($B13="Arm 1",cfg_arm1,IF($B13="Arm 2",cfg_arm2,IF($B13="Arm 3",cfg_arm3,cfg_concurrent))),$K13))+cfg_overhead/60) -> 13 | AN13: =IF($AM13="","",INT($AM13/24)&"d "&TEXT(MOD($AM13,24),"0.0")&"h") -> 0d 13h | AO13: =IF($AM13="","",$AL13*IFERROR(GAMMAINV(cfg_pct,MAX(1,IF($F13="item_drop",IF($G13="each",$AJ13*$H13,$H13),1000)),1/MAX(1,IF($F13="item_drop",IF($G13="each",$AJ13*$H13,$H13),1000))),1)/MAX(0.1,IF($K13="",IF($B13="Arm 1",cfg_arm1,IF($B13="Arm 2",cfg_arm2,IF($B13="Arm 3",cfg_arm3,cfg_concurrent))),$K13))+cfg_overhead/60) -> 22.908567 | AP13: =(cfg_base+cfg_slope*$C13^cfg_exp)*IF($D13="KEY",cfg_mkey,IF($D13="END",cfg_mend,IF($D13="Skippable",cfg_mskip,1))) -> 0.6778963 | AQ13: =IF(OR($AM13="",$AP13=0),"",$AM13/$AP13) -> 19.176975 | AR13: =IF($F13="","- no task set -",_xlfn.TEXTJOIN(" | ",TRUE,IF(AND($F13<>"gp_value",$AJ13=0),"no items selected",""),IF(AND($F13="gp_value",$AJ13=0),"pick a farming method so the ETC can be estimated",""),IF(AND($F13="gp_value",$AJ13>1),"gp_value takes no item list - one method is enough",""),IF(AND($F13="minigame_completion",$AJ13>1),"only 1 minigame per tile",""),IF(OR($H13="",$H13<=0),"target missing",""),IF(SUMPRODUCT(($L13:$AE13<>"")*(Calc!$C13:$Z13=0))>0,"unknown entry - not in catalogue",""),IF(AND($G13="each",$AJ13=1),"each with 1 entry = same as any",""),IF($AL13="","ETC not computable",""))) -> #N/A | AS13: Gawk gawk 3000 | AT13: =IF($F13="","","{"&CHAR(34)&"tileId"&CHAR(34)&":"&$A13&","&CHAR(34)&"taskType"&CHAR(34)&":"&CHAR(34)&$F13&CHAR(34)&","&CHAR(34)&"taskConfig"&CHAR(34)&":{"&IF($F13="gp_value","",IF($F13="minigame_completion",CHAR(34)&"minigame"&CHAR(34)&":"&CHAR(34)&$L13&CHAR(34)&","&CHAR(34)&"message"&CHAR(34)&":"&CHAR(34)&IFERROR(INDEX(minigame_completion!$J$5:$J$47,MATCH($L13,minigame_completion!$A$5:$A$47,0)),"")&CHAR(34)&",",IF($AJ13=1,CHAR(34)&INDEX(Settings!$F$6:$F$13,MATCH($F13,Settings!$E$6:$E$13,0))&CHAR(34)&":"&Calc!$EW13&",",CHAR(34)&INDEX(Settings!$G$6:$G$13,MATCH($F13,Settings!$E$6:$E$13,0))&CHAR(34)&":["&_xlfn.TEXTJOIN(",",TRUE,Calc!$EW13:$FT13)&"],")))&CHAR(34)&"target"&CHAR(34)&":"&$H13&IF($G13="each",","&CHAR(34)&"mode"&CHAR(34)&":"&CHAR(34)&"each"&CHAR(34),"")&"}}") -> {"tileId":72,"taskType":"item_drop","taskConfig":{"item":"Kbd heads","target":3}}
A14: 63 | B14: =IFERROR(INDEX(Maze!$C$5:$C$85,MATCH($A14,Maze!$A$5:$A$85,0)),"") -> Arm 1 | C14: =IFERROR(INDEX(Maze!$D$5:$D$85,MATCH($A14,Maze!$A$5:$A$85,0)),"") -> 8 | D14: =IFERROR(INDEX(Maze!$E$5:$E$85,MATCH($A14,Maze!$A$5:$A$85,0)),"") -> Forced | E14: =IFERROR(INDEX(Maze!$G$5:$G$85,MATCH($A14,Maze!$A$5:$A$85,0)),"") -> No | F14: item_drop | H14: 1 | L14: Odium shard 1 | M14: Odium shard 2 | N14: Odium shard 3 | AJ14: {=SUMPRODUCT(($L14:$AI14<>"")*1)} -> 3 | AK14: =IF($F14="","",IF($G14="each",$AJ14*$H14,$H14)) -> 1 | AL14: =IF($F14="","",IFERROR((IF($G14="each",IF($I14="No",SUM(Calc!$BZ14:$CW14),IF($F14="item_drop",SUM(Calc!$DX14:$EU14),IF($I14="Yes",MAX(Calc!$BZ14:$CW14),SUM(Calc!$BZ14:$CW14)))),$H14/MAX(Calc!$BA14:$BX14)))/IF($J14="",cfg_ratemult,$J14),"")) -> 5.6888889 | AM14: =IF($AL14="","",$AL14/MAX(0.1,IF($K14="",IF($B14="Arm 1",cfg_arm1,IF($B14="Arm 2",cfg_arm2,IF($B14="Arm 3",cfg_arm3,cfg_concurrent))),$K14))+cfg_overhead/60) -> 5.8888889 | AN14: =IF($AM14="","",INT($AM14/24)&"d "&TEXT(MOD($AM14,24),"0.0")&"h") -> 0d 06h | AO14: =IF($AM14="","",$AL14*IFERROR(GAMMAINV(cfg_pct,MAX(1,IF($F14="item_drop",IF($G14="each",$AJ14*$H14,$H14),1000)),1/MAX(1,IF($F14="item_drop",IF($G14="each",$AJ14*$H14,$H14),1000))),1)/MAX(0.1,IF($K14="",IF($B14="Arm 1",cfg_arm1,IF($B14="Arm 2",cfg_arm2,IF($B14="Arm 3",cfg_arm3,cfg_concurrent))),$K14))+cfg_overhead/60) -> 13.299151 | AP14: =(cfg_base+cfg_slope*$C14^cfg_exp)*IF($D14="KEY",cfg_mkey,IF($D14="END",cfg_mend,IF($D14="Skippable",cfg_mskip,1))) -> 0.74146361 | AQ14: =IF(OR($AM14="",$AP14=0),"",$AM14/$AP14) -> 7.9422494 | AR14: =IF($F14="","- no task set -",_xlfn.TEXTJOIN(" | ",TRUE,IF(AND($F14<>"gp_value",$AJ14=0),"no items selected",""),IF(AND($F14="gp_value",$AJ14=0),"pick a farming method so the ETC can be estimated",""),IF(AND($F14="gp_value",$AJ14>1),"gp_value takes no item list - one method is enough",""),IF(AND($F14="minigame_completion",$AJ14>1),"only 1 minigame per tile",""),IF(OR($H14="",$H14<=0),"target missing",""),IF(SUMPRODUCT(($L14:$AE14<>"")*(Calc!$C14:$Z14=0))>0,"unknown entry - not in catalogue",""),IF(AND($G14="each",$AJ14=1),"each with 1 entry = same as any",""),IF($AL14="","ETC not computable",""))) -> #N/A | AS14: Shard tale | AT14: =IF($F14="","","{"&CHAR(34)&"tileId"&CHAR(34)&":"&$A14&","&CHAR(34)&"taskType"&CHAR(34)&":"&CHAR(34)&$F14&CHAR(34)&","&CHAR(34)&"taskConfig"&CHAR(34)&":{"&IF($F14="gp_value","",IF($F14="minigame_completion",CHAR(34)&"minigame"&CHAR(34)&":"&CHAR(34)&$L14&CHAR(34)&","&CHAR(34)&"message"&CHAR(34)&":"&CHAR(34)&IFERROR(INDEX(minigame_completion!$J$5:$J$47,MATCH($L14,minigame_completion!$A$5:$A$47,0)),"")&CHAR(34)&",",IF($AJ14=1,CHAR(34)&INDEX(Settings!$F$6:$F$13,MATCH($F14,Settings!$E$6:$E$13,0))&CHAR(34)&":"&Calc!$EW14&",",CHAR(34)&INDEX(Settings!$G$6:$G$13,MATCH($F14,Settings!$E$6:$E$13,0))&CHAR(34)&":["&_xlfn.TEXTJOIN(",",TRUE,Calc!$EW14:$FT14)&"],")))&CHAR(34)&"target"&CHAR(34)&":"&$H14&IF($G14="each",","&CHAR(34)&"mode"&CHAR(34)&":"&CHAR(34)&"each"&CHAR(34),"")&"}}") -> {"tileId":63,"taskType":"item_drop","taskConfig":{"items":["Odium shard 1","Odium shard 2","Odium shard 3"],"target":1}}
A15: 54 | B15: =IFERROR(INDEX(Maze!$C$5:$C$85,MATCH($A15,Maze!$A$5:$A$85,0)),"") -> Arm 1 | C15: =IFERROR(INDEX(Maze!$D$5:$D$85,MATCH($A15,Maze!$A$5:$A$85,0)),"") -> 9 | D15: =IFERROR(INDEX(Maze!$E$5:$E$85,MATCH($A15,Maze!$A$5:$A$85,0)),"") -> Forced | E15: =IFERROR(INDEX(Maze!$G$5:$G$85,MATCH($A15,Maze!$A$5:$A$85,0)),"") -> No | F15: item_drop | H15: 5 | L15: Ahrim's hood | M15: Ahrim's robetop | N15: Ahrim's robeskirt | O15: Ahrim's staff | P15: Dharok's helm | Q15: Dharok's platebody | R15: Dharok's platelegs | S15: Dharok's greataxe | T15: Guthan's helm | U15: Guthan's platebody | V15: Guthan's chainskirt | W15: Guthan's warspear | X15: Karil's coif | Y15: Karil's leathertop | Z15: Karil's leatherskirt | AA15: Karil's crossbow | AB15: Torag's helm | AC15: Torag's platebody | AD15: Torag's platelegs | AE15: Torag's hammers | AF15: Verac's helm | AG15: Verac's brassard | AH15: Verac's plateskirt | AI15: Verac's flail | AJ15: {=SUMPRODUCT(($L15:$AI15<>"")*1)} -> 24 | AK15: =IF($F15="","",IF($G15="each",$AJ15*$H15,$H15)) -> 5 | AL15: =IF($F15="","",IFERROR((IF($G15="each",IF($I15="No",SUM(Calc!$BZ15:$CW15),IF($F15="item_drop",SUM(Calc!$DX15:$EU15),IF($I15="Yes",MAX(Calc!$BZ15:$CW15),SUM(Calc!$BZ15:$CW15)))),$H15/MAX(Calc!$BA15:$BX15)))/IF($J15="",cfg_ratemult,$J15),"")) -> 6.0763889 | AM15: =IF($AL15="","",$AL15/MAX(0.1,IF($K15="",IF($B15="Arm 1",cfg_arm1,IF($B15="Arm 2",cfg_arm2,IF($B15="Arm 3",cfg_arm3,cfg_concurrent))),$K15))+cfg_overhead/60) -> 6.2763889 | AN15: =IF($AM15="","",INT($AM15/24)&"d "&TEXT(MOD($AM15,24),"0.0")&"h") -> 0d 06h | AO15: =IF($AM15="","",$AL15*IFERROR(GAMMAINV(cfg_pct,MAX(1,IF($F15="item_drop",IF($G15="each",$AJ15*$H15,$H15),1000)),1/MAX(1,IF($F15="item_drop",IF($G15="each",$AJ15*$H15,$H15),1000))),1)/MAX(0.1,IF($K15="",IF($B15="Arm 1",cfg_arm1,IF($B15="Arm 2",cfg_arm2,IF($B15="Arm 3",cfg_arm3,cfg_concurrent))),$K15))+cfg_overhead/60) -> 9.9144318 | AP15: =(cfg_base+cfg_slope*$C15^cfg_exp)*IF($D15="KEY",cfg_mkey,IF($D15="END",cfg_mend,IF($D15="Skippable",cfg_mskip,1))) -> 0.81042128 | AQ15: =IF(OR($AM15="",$AP15=0),"",$AM15/$AP15) -> 7.7446003 | AR15: =IF($F15="","- no task set -",_xlfn.TEXTJOIN(" | ",TRUE,IF(AND($F15<>"gp_value",$AJ15=0),"no items selected",""),IF(AND($F15="gp_value",$AJ15=0),"pick a farming method so the ETC can be estimated",""),IF(AND($F15="gp_value",$AJ15>1),"gp_value takes no item list - one method is enough",""),IF(AND($F15="minigame_completion",$AJ15>1),"only 1 minigame per tile",""),IF(OR($H15="",$H15<=0),"target missing",""),IF(SUMPRODUCT(($L15:$AE15<>"")*(Calc!$C15:$Z15=0))>0,"unknown entry - not in catalogue",""),IF(AND($G15="each",$AJ15=1),"each with 1 entry = same as any",""),IF($AL15="","ETC not computable",""))) -> #N/A | AS15: Six feet under | AT15: =IF($F15="","","{"&CHAR(34)&"tileId"&CHAR(34)&":"&$A15&","&CHAR(34)&"taskType"&CHAR(34)&":"&CHAR(34)&$F15&CHAR(34)&","&CHAR(34)&"taskConfig"&CHAR(34)&":{"&IF($F15="gp_value","",IF($F15="minigame_completion",CHAR(34)&"minigame"&CHAR(34)&":"&CHAR(34)&$L15&CHAR(34)&","&CHAR(34)&"message"&CHAR(34)&":"&CHAR(34)&IFERROR(INDEX(minigame_completion!$J$5:$J$47,MATCH($L15,minigame_completion!$A$5:$A$47,0)),"")&CHAR(34)&",",IF($AJ15=1,CHAR(34)&INDEX(Settings!$F$6:$F$13,MATCH($F15,Settings!$E$6:$E$13,0))&CHAR(34)&":"&Calc!$EW15&",",CHAR(34)&INDEX(Settings!$G$6:$G$13,MATCH($F15,Settings!$E$6:$E$13,0))&CHAR(34)&":["&_xlfn.TEXTJOIN(",",TRUE,Calc!$EW15:$FT15)&"],")))&CHAR(34)&"target"&CHAR(34)&":"&$H15&IF($G15="each",","&CHAR(34)&"mode"&CHAR(34)&":"&CHAR(34)&"each"&CHAR(34),"")&"}}") -> {"tileId":54,"taskType":"item_drop","taskConfig":{"items":["Ahrim's hood","Ahrim's robetop","Ahrim's robeskirt","Ahrim's staff","Dharok's helm","Dharok's platebody","Dharok's platelegs","Dharok's greataxe","Guthan's helm","Guthan's platebody","Guthan's chainskirt","Guthan's warspear","Karil's coif","Karil's leathertop","Karil's leatherskirt","Karil's crossbow","Torag's helm","Torag's platebody","Torag's platelegs","Torag's hammers","Verac's helm","Verac's brassard","Verac's plateskirt","Verac's flail"],"target":5}}
A16: 45 | B16: =IFERROR(INDEX(Maze!$C$5:$C$85,MATCH($A16,Maze!$A$5:$A$85,0)),"") -> Arm 1 | C16: =IFERROR(INDEX(Maze!$D$5:$D$85,MATCH($A16,Maze!$A$5:$A$85,0)),"") -> 10 | D16: =IFERROR(INDEX(Maze!$E$5:$E$85,MATCH($A16,Maze!$A$5:$A$85,0)),"") -> Forced | E16: =IFERROR(INDEX(Maze!$G$5:$G$85,MATCH($A16,Maze!$A$5:$A$85,0)),"") -> No | F16: npc_kill | G16: each | H16: 100 | L16: Green dragon | M16: Blue dragon | N16: Red dragon | O16: Black dragon | AJ16: {=SUMPRODUCT(($L16:$AI16<>"")*1)} -> 4 | AK16: =IF($F16="","",IF($G16="each",$AJ16*$H16,$H16)) -> 400 | AL16: =IF($F16="","",IFERROR((IF($G16="each",IF($I16="No",SUM(Calc!$BZ16:$CW16),IF($F16="item_drop",SUM(Calc!$DX16:$EU16),IF($I16="Yes",MAX(Calc!$BZ16:$CW16),SUM(Calc!$BZ16:$CW16)))),$H16/MAX(Calc!$BA16:$BX16)))/IF($J16="",cfg_ratemult,$J16),"")) -> 6.0555556 | AM16: =IF($AL16="","",$AL16/MAX(0.1,IF($K16="",IF($B16="Arm 1",cfg_arm1,IF($B16="Arm 2",cfg_arm2,IF($B16="Arm 3",cfg_arm3,cfg_concurrent))),$K16))+cfg_overhead/60) -> 6.2555556 | AN16: =IF($AM16="","",INT($AM16/24)&"d "&TEXT(MOD($AM16,24),"0.0")&"h") -> 0d 06h | AO16: =IF($AM16="","",$AL16*IFERROR(GAMMAINV(cfg_pct,MAX(1,IF($F16="item_drop",IF($G16="each",$AJ16*$H16,$H16),1000)),1/MAX(1,IF($F16="item_drop",IF($G16="each",$AJ16*$H16,$H16),1000))),1)/MAX(0.1,IF($K16="",IF($B16="Arm 1",cfg_arm1,IF($B16="Arm 2",cfg_arm2,IF($B16="Arm 3",cfg_arm3,cfg_concurrent))),$K16))+cfg_overhead/60) -> 6.5022244 | AP16: =(cfg_base+cfg_slope*$C16^cfg_exp)*IF($D16="KEY",cfg_mkey,IF($D16="END",cfg_mend,IF($D16="Skippable",cfg_mskip,1))) -> 0.88455094 | AQ16: =IF(OR($AM16="",$AP16=0),"",$AM16/$AP16) -> 7.0720128 | AR16: =IF($F16="","- no task set -",_xlfn.TEXTJOIN(" | ",TRUE,IF(AND($F16<>"gp_value",$AJ16=0),"no items selected",""),IF(AND($F16="gp_value",$AJ16=0),"pick a farming method so the ETC can be estimated",""),IF(AND($F16="gp_value",$AJ16>1),"gp_value takes no item list - one method is enough",""),IF(AND($F16="minigame_completion",$AJ16>1),"only 1 minigame per tile",""),IF(OR($H16="",$H16<=0),"target missing",""),IF(SUMPRODUCT(($L16:$AE16<>"")*(Calc!$C16:$Z16=0))>0,"unknown entry - not in catalogue",""),IF(AND($G16="each",$AJ16=1),"each with 1 entry = same as any",""),IF($AL16="","ETC not computable",""))) -> #N/A | AS16: Imagine Dragon deez nuts across your face | AT16: =IF($F16="","","{"&CHAR(34)&"tileId"&CHAR(34)&":"&$A16&","&CHAR(34)&"taskType"&CHAR(34)&":"&CHAR(34)&$F16&CHAR(34)&","&CHAR(34)&"taskConfig"&CHAR(34)&":{"&IF($F16="gp_value","",IF($F16="minigame_completion",CHAR(34)&"minigame"&CHAR(34)&":"&CHAR(34)&$L16&CHAR(34)&","&CHAR(34)&"message"&CHAR(34)&":"&CHAR(34)&IFERROR(INDEX(minigame_completion!$J$5:$J$47,MATCH($L16,minigame_completion!$A$5:$A$47,0)),"")&CHAR(34)&",",IF($AJ16=1,CHAR(34)&INDEX(Settings!$F$6:$F$13,MATCH($F16,Settings!$E$6:$E$13,0))&CHAR(34)&":"&Calc!$EW16&",",CHAR(34)&INDEX(Settings!$G$6:$G$13,MATCH($F16,Settings!$E$6:$E$13,0))&CHAR(34)&":["&_xlfn.TEXTJOIN(",",TRUE,Calc!$EW16:$FT16)&"],")))&CHAR(34)&"target"&CHAR(34)&":"&$H16&IF($G16="each",","&CHAR(34)&"mode"&CHAR(34)&":"&CHAR(34)&"each"&CHAR(34),"")&"}}") -> {"tileId":45,"taskType":"npc_kill","taskConfig":{"npcs":["Green dragon","Blue dragon","Red dragon","Black dragon"],"target":100,"mode":"each"}}
A17: 44 | B17: =IFERROR(INDEX(Maze!$C$5:$C$85,MATCH($A17,Maze!$A$5:$A$85,0)),"") -> Arm 1 | C17: =IFERROR(INDEX(Maze!$D$5:$D$85,MATCH($A17,Maze!$A$5:$A$85,0)),"") -> 11 | D17: =IFERROR(INDEX(Maze!$E$5:$E$85,MATCH($A17,Maze!$A$5:$A$85,0)),"") -> Forced | E17: =IFERROR(INDEX(Maze!$G$5:$G$85,MATCH($A17,Maze!$A$5:$A$85,0)),"") -> No | F17: item_drop | G17: each | H17: 1 | L17: Mithril 2h sword | M17: Mud battlestaff | N17: Seercull | AJ17: {=SUMPRODUCT(($L17:$AI17<>"")*1)} -> 3 | AK17: =IF($F17="","",IF($G17="each",$AJ17*$H17,$H17)) -> 3 | AL17: =IF($F17="","",IFERROR((IF($G17="each",IF($I17="No",SUM(Calc!$BZ17:$CW17),IF($F17="item_drop",SUM(Calc!$DX17:$EU17),IF($I17="Yes",MAX(Calc!$BZ17:$CW17),SUM(Calc!$BZ17:$CW17)))),$H17/MAX(Calc!$BA17:$BX17)))/IF($J17="",cfg_ratemult,$J17),"")) -> 3.2 | AM17: =IF($AL17="","",$AL17/MAX(0.1,IF($K17="",IF($B17="Arm 1",cfg_arm1,IF($B17="Arm 2",cfg_arm2,IF($B17="Arm 3",cfg_arm3,cfg_concurrent))),$K17))+cfg_overhead/60) -> 3.4 | AN17: =IF($AM17="","",INT($AM17/24)&"d "&TEXT(MOD($AM17,24),"0.0")&"h") -> 0d 03h | AO17: =IF($AM17="","",$AL17*IFERROR(GAMMAINV(cfg_pct,MAX(1,IF($F17="item_drop",IF($G17="each",$AJ17*$H17,$H17),1000)),1/MAX(1,IF($F17="item_drop",IF($G17="each",$AJ17*$H17,$H17),1000))),1)/MAX(0.1,IF($K17="",IF($B17="Arm 1",cfg_arm1,IF($B17="Arm 2",cfg_arm2,IF($B17="Arm 3",cfg_arm3,cfg_concurrent))),$K17))+cfg_overhead/60) -> 5.8771417 | AP17: =(cfg_base+cfg_slope*$C17^cfg_exp)*IF($D17="KEY",cfg_mkey,IF($D17="END",cfg_mend,IF($D17="Skippable",cfg_mskip,1))) -> 0.96366487 | AQ17: =IF(OR($AM17="",$AP17=0),"",$AM17/$AP17) -> 3.5281975 | AR17: =IF($F17="","- no task set -",_xlfn.TEXTJOIN(" | ",TRUE,IF(AND($F17<>"gp_value",$AJ17=0),"no items selected",""),IF(AND($F17="gp_value",$AJ17=0),"pick a farming method so the ETC can be estimated",""),IF(AND($F17="gp_value",$AJ17>1),"gp_value takes no item list - one method is enough",""),IF(AND($F17="minigame_completion",$AJ17>1),"only 1 minigame per tile",""),IF(OR($H17="",$H17<=0),"target missing",""),IF(SUMPRODUCT(($L17:$AE17<>"")*(Calc!$C17:$Z17=0))>0,"unknown entry - not in catalogue",""),IF(AND($G17="each",$AJ17=1),"each with 1 entry = same as any",""),IF($AL17="","ETC not computable",""))) -> #N/A | AS17: Lotr but different | AT17: =IF($F17="","","{"&CHAR(34)&"tileId"&CHAR(34)&":"&$A17&","&CHAR(34)&"taskType"&CHAR(34)&":"&CHAR(34)&$F17&CHAR(34)&","&CHAR(34)&"taskConfig"&CHAR(34)&":{"&IF($F17="gp_value","",IF($F17="minigame_completion",CHAR(34)&"minigame"&CHAR(34)&":"&CHAR(34)&$L17&CHAR(34)&","&CHAR(34)&"message"&CHAR(34)&":"&CHAR(34)&IFERROR(INDEX(minigame_completion!$J$5:$J$47,MATCH($L17,minigame_completion!$A$5:$A$47,0)),"")&CHAR(34)&",",IF($AJ17=1,CHAR(34)&INDEX(Settings!$F$6:$F$13,MATCH($F17,Settings!$E$6:$E$13,0))&CHAR(34)&":"&Calc!$EW17&",",CHAR(34)&INDEX(Settings!$G$6:$G$13,MATCH($F17,Settings!$E$6:$E$13,0))&CHAR(34)&":["&_xlfn.TEXTJOIN(",",TRUE,Calc!$EW17:$FT17)&"],")))&CHAR(34)&"target"&CHAR(34)&":"&$H17&IF($G17="each",","&CHAR(34)&"mode"&CHAR(34)&":"&CHAR(34)&"each"&CHAR(34),"")&"}}") -> {"tileId":44,"taskType":"item_drop","taskConfig":{"items":["Mithril 2h sword","Mud battlestaff","Seercull"],"target":1,"mode":"each"}}
A18: 43 | B18: =IFERROR(INDEX(Maze!$C$5:$C$85,MATCH($A18,Maze!$A$5:$A$85,0)),"") -> Arm 1 | C18: =IFERROR(INDEX(Maze!$D$5:$D$85,MATCH($A18,Maze!$A$5:$A$85,0)),"") -> 12 | D18: =IFERROR(INDEX(Maze!$E$5:$E$85,MATCH($A18,Maze!$A$5:$A$85,0)),"") -> Forced | E18: =IFERROR(INDEX(Maze!$G$5:$G$85,MATCH($A18,Maze!$A$5:$A$85,0)),"") -> No | F18: item_drop | H18: 3 | L18: Unsired | AJ18: {=SUMPRODUCT(($L18:$AI18<>"")*1)} -> 1 | AK18: =IF($F18="","",IF($G18="each",$AJ18*$H18,$H18)) -> 3 | AL18: =IF($F18="","",IFERROR((IF($G18="each",IF($I18="No",SUM(Calc!$BZ18:$CW18),IF($F18="item_drop",SUM(Calc!$DX18:$EU18),IF($I18="Yes",MAX(Calc!$BZ18:$CW18),SUM(Calc!$BZ18:$CW18)))),$H18/MAX(Calc!$BA18:$BX18)))/IF($J18="",cfg_ratemult,$J18),"")) -> 7.6923077 | AM18: =IF($AL18="","",$AL18/MAX(0.1,IF($K18="",IF($B18="Arm 1",cfg_arm1,IF($B18="Arm 2",cfg_arm2,IF($B18="Arm 3",cfg_arm3,cfg_concurrent))),$K18))+cfg_overhead/60) -> 7.8923077 | AN18: =IF($AM18="","",INT($AM18/24)&"d "&TEXT(MOD($AM18,24),"0.0")&"h") -> 0d 08h | AO18: =IF($AM18="","",$AL18*IFERROR(GAMMAINV(cfg_pct,MAX(1,IF($F18="item_drop",IF($G18="each",$AJ18*$H18,$H18),1000)),1/MAX(1,IF($F18="item_drop",IF($G18="each",$AJ18*$H18,$H18),1000))),1)/MAX(0.1,IF($K18="",IF($B18="Arm 1",cfg_arm1,IF($B18="Arm 2",cfg_arm2,IF($B18="Arm 3",cfg_arm3,cfg_concurrent))),$K18))+cfg_overhead/60) -> 13.846975 | AP18: =(cfg_base+cfg_slope*$C18^cfg_exp)*IF($D18="KEY",cfg_mkey,IF($D18="END",cfg_mend,IF($D18="Skippable",cfg_mskip,1))) -> 1.0475992 | AQ18: =IF(OR($AM18="",$AP18=0),"",$AM18/$AP18) -> 7.533709 | AR18: =IF($F18="","- no task set -",_xlfn.TEXTJOIN(" | ",TRUE,IF(AND($F18<>"gp_value",$AJ18=0),"no items selected",""),IF(AND($F18="gp_value",$AJ18=0),"pick a farming method so the ETC can be estimated",""),IF(AND($F18="gp_value",$AJ18>1),"gp_value takes no item list - one method is enough",""),IF(AND($F18="minigame_completion",$AJ18>1),"only 1 minigame per tile",""),IF(OR($H18="",$H18<=0),"target missing",""),IF(SUMPRODUCT(($L18:$AE18<>"")*(Calc!$C18:$Z18=0))>0,"unknown entry - not in catalogue",""),IF(AND($G18="each",$AJ18=1),"each with 1 entry = same as any",""),IF($AL18="","ETC not computable",""))) -> #N/A | AS18: They're stackable now | AT18: =IF($F18="","","{"&CHAR(34)&"tileId"&CHAR(34)&":"&$A18&","&CHAR(34)&"taskType"&CHAR(34)&":"&CHAR(34)&$F18&CHAR(34)&","&CHAR(34)&"taskConfig"&CHAR(34)&":{"&IF($F18="gp_value","",IF($F18="minigame_completion",CHAR(34)&"minigame"&CHAR(34)&":"&CHAR(34)&$L18&CHAR(34)&","&CHAR(34)&"message"&CHAR(34)&":"&CHAR(34)&IFERROR(INDEX(minigame_completion!$J$5:$J$47,MATCH($L18,minigame_completion!$A$5:$A$47,0)),"")&CHAR(34)&",",IF($AJ18=1,CHAR(34)&INDEX(Settings!$F$6:$F$13,MATCH($F18,Settings!$E$6:$E$13,0))&CHAR(34)&":"&Calc!$EW18&",",CHAR(34)&INDEX(Settings!$G$6:$G$13,MATCH($F18,Settings!$E$6:$E$13,0))&CHAR(34)&":["&_xlfn.TEXTJOIN(",",TRUE,Calc!$EW18:$FT18)&"],")))&CHAR(34)&"target"&CHAR(34)&":"&$H18&IF($G18="each",","&CHAR(34)&"mode"&CHAR(34)&":"&CHAR(34)&"each"&CHAR(34),"")&"}}") -> {"tileId":43,"taskType":"item_drop","taskConfig":{"item":"Unsired","target":3}}
A19: 42 | B19: =IFERROR(INDEX(Maze!$C$5:$C$85,MATCH($A19,Maze!$A$5:$A$85,0)),"") -> Arm 1 | C19: =IFERROR(INDEX(Maze!$D$5:$D$85,MATCH($A19,Maze!$A$5:$A$85,0)),"") -> 13 | D19: =IFERROR(INDEX(Maze!$E$5:$E$85,MATCH($A19,Maze!$A$5:$A$85,0)),"") -> Forced | E19: =IFERROR(INDEX(Maze!$G$5:$G$85,MATCH($A19,Maze!$A$5:$A$85,0)),"") -> No | F19: agility_lap | H19: 500 | L19: Draynor | M19: Al Kharid | N19: Varrock | O19: Canifis | P19: Falador | Q19: Seers' Village | R19: Pollnivneach | S19: Rellekka | T19: Ardougne | AJ19: {=SUMPRODUCT(($L19:$AI19<>"")*1)} -> 9 | AK19: =IF($F19="","",IF($G19="each",$AJ19*$H19,$H19)) -> 500 | AL19: =IF($F19="","",IFERROR((IF($G19="each",IF($I19="No",SUM(Calc!$BZ19:$CW19),IF($F19="item_drop",SUM(Calc!$DX19:$EU19),IF($I19="Yes",MAX(Calc!$BZ19:$CW19),SUM(Calc!$BZ19:$CW19)))),$H19/MAX(Calc!$BA19:$BX19)))/IF($J19="",cfg_ratemult,$J19),"")) -> 6.0240964 | AM19: =IF($AL19="","",$AL19/MAX(0.1,IF($K19="",IF($B19="Arm 1",cfg_arm1,IF($B19="Arm 2",cfg_arm2,IF($B19="Arm 3",cfg_arm3,cfg_concurrent))),$K19))+cfg_overhead/60) -> 6.2240964 | AN19: =IF($AM19="","",INT($AM19/24)&"d "&TEXT(MOD($AM19,24),"0.0")&"h") -> 0d 06h | AO19: =IF($AM19="","",$AL19*IFERROR(GAMMAINV(cfg_pct,MAX(1,IF($F19="item_drop",IF($G19="each",$AJ19*$H19,$H19),1000)),1/MAX(1,IF($F19="item_drop",IF($G19="each",$AJ19*$H19,$H19),1000))),1)/MAX(0.1,IF($K19="",IF($B19="Arm 1",cfg_arm1,IF($B19="Arm 2",cfg_arm2,IF($B19="Arm 3",cfg_arm3,cfg_concurrent))),$K19))+cfg_overhead/60) -> 6.4694838 | AP19: =(cfg_base+cfg_slope*$C19^cfg_exp)*IF($D19="KEY",cfg_mkey,IF($D19="END",cfg_mend,IF($D19="Skippable",cfg_mskip,1))) -> 1.1362092 | AQ19: =IF(OR($AM19="",$AP19=0),"",$AM19/$AP19) -> 5.4779495 | AR19: =IF($F19="","- no task set -",_xlfn.TEXTJOIN(" | ",TRUE,IF(AND($F19<>"gp_value",$AJ19=0),"no items selected",""),IF(AND($F19="gp_value",$AJ19=0),"pick a farming method so the ETC can be estimated",""),IF(AND($F19="gp_value",$AJ19>1),"gp_value takes no item list - one method is enough",""),IF(AND($F19="minigame_completion",$AJ19>1),"only 1 minigame per tile",""),IF(OR($H19="",$H19<=0),"target missing",""),IF(SUMPRODUCT(($L19:$AE19<>"")*(Calc!$C19:$Z19=0))>0,"unknown entry - not in catalogue",""),IF(AND($G19="each",$AJ19=1),"each with 1 entry = same as any",""),IF($AL19="","ETC not computable",""))) -> #N/A | AS19: Cardio? In this economy? | AT19: =IF($F19="","","{"&CHAR(34)&"tileId"&CHAR(34)&":"&$A19&","&CHAR(34)&"taskType"&CHAR(34)&":"&CHAR(34)&$F19&CHAR(34)&","&CHAR(34)&"taskConfig"&CHAR(34)&":{"&IF($F19="gp_value","",IF($F19="minigame_completion",CHAR(34)&"minigame"&CHAR(34)&":"&CHAR(34)&$L19&CHAR(34)&","&CHAR(34)&"message"&CHAR(34)&":"&CHAR(34)&IFERROR(INDEX(minigame_completion!$J$5:$J$47,MATCH($L19,minigame_completion!$A$5:$A$47,0)),"")&CHAR(34)&",",IF($AJ19=1,CHAR(34)&INDEX(Settings!$F$6:$F$13,MATCH($F19,Settings!$E$6:$E$13,0))&CHAR(34)&":"&Calc!$EW19&",",CHAR(34)&INDEX(Settings!$G$6:$G$13,MATCH($F19,Settings!$E$6:$E$13,0))&CHAR(34)&":["&_xlfn.TEXTJOIN(",",TRUE,Calc!$EW19:$FT19)&"],")))&CHAR(34)&"target"&CHAR(34)&":"&$H19&IF($G19="each",","&CHAR(34)&"mode"&CHAR(34)&":"&CHAR(34)&"each"&CHAR(34),"")&"}}") -> {"tileId":42,"taskType":"agility_lap","taskConfig":{"courses":["Draynor","Al Kharid","Varrock","Canifis","Falador","Seers' Village","Pollnivneach","Rellekka","Ardougne"],"target":500}}
A20: 33 | B20: =IFERROR(INDEX(Maze!$C$5:$C$85,MATCH($A20,Maze!$A$5:$A$85,0)),"") -> Arm 1 | C20: =IFERROR(INDEX(Maze!$D$5:$D$85,MATCH($A20,Maze!$A$5:$A$85,0)),"") -> 14 | D20: =IFERROR(INDEX(Maze!$E$5:$E$85,MATCH($A20,Maze!$A$5:$A$85,0)),"") -> Skippable | E20: =IFERROR(INDEX(Maze!$G$5:$G$85,MATCH($A20,Maze!$A$5:$A$85,0)),"") -> No | F20: item_drop | G20: each | H20: 1 | L20: Godsword shard 1 | M20: Godsword shard 2 | N20: Godsword shard 3 | AJ20: {=SUMPRODUCT(($L20:$AI20<>"")*1)} -> 3 | AK20: =IF($F20="","",IF($G20="each",$AJ20*$H20,$H20)) -> 3 | AL20: =IF($F20="","",IFERROR((IF($G20="each",IF($I20="No",SUM(Calc!$BZ20:$CW20),IF($F20="item_drop",SUM(Calc!$DX20:$EU20),IF($I20="Yes",MAX(Calc!$BZ20:$CW20),SUM(Calc!$BZ20:$CW20)))),$H20/MAX(Calc!$BA20:$BX20)))/IF($J20="",cfg_ratemult,$J20),"")) -> 17.246914 | AM20: =IF($AL20="","",$AL20/MAX(0.1,IF($K20="",IF($B20="Arm 1",cfg_arm1,IF($B20="Arm 2",cfg_arm2,IF($B20="Arm 3",cfg_arm3,cfg_concurrent))),$K20))+cfg_overhead/60) -> 17.446914 | AN20: =IF($AM20="","",INT($AM20/24)&"d "&TEXT(MOD($AM20,24),"0.0")&"h") -> 0d 17h | AO20: =IF($AM20="","",$AL20*IFERROR(GAMMAINV(cfg_pct,MAX(1,IF($F20="item_drop",IF($G20="each",$AJ20*$H20,$H20),1000)),1/MAX(1,IF($F20="item_drop",IF($G20="each",$AJ20*$H20,$H20),1000))),1)/MAX(0.1,IF($K20="",IF($B20="Arm 1",cfg_arm1,IF($B20="Arm 2",cfg_arm2,IF($B20="Arm 3",cfg_arm3,cfg_concurrent))),$K20))+cfg_overhead/60) -> 30.797866 | AP20: =(cfg_base+cfg_slope*$C20^cfg_exp)*IF($D20="KEY",cfg_mkey,IF($D20="END",cfg_mend,IF($D20="Skippable",cfg_mskip,1))) -> 0.67615093 | AQ20: =IF(OR($AM20="",$AP20=0),"",$AM20/$AP20) -> 25.803283 | AR20: =IF($F20="","- no task set -",_xlfn.TEXTJOIN(" | ",TRUE,IF(AND($F20<>"gp_value",$AJ20=0),"no items selected",""),IF(AND($F20="gp_value",$AJ20=0),"pick a farming method so the ETC can be estimated",""),IF(AND($F20="gp_value",$AJ20>1),"gp_value takes no item list - one method is enough",""),IF(AND($F20="minigame_completion",$AJ20>1),"only 1 minigame per tile",""),IF(OR($H20="",$H20<=0),"target missing",""),IF(SUMPRODUCT(($L20:$AE20<>"")*(Calc!$C20:$Z20=0))>0,"unknown entry - not in catalogue",""),IF(AND($G20="each",$AJ20=1),"each with 1 entry = same as any",""),IF($AL20="","ETC not computable",""))) -> #N/A | AS20: Feel free to put them together | AT20: =IF($F20="","","{"&CHAR(34)&"tileId"&CHAR(34)&":"&$A20&","&CHAR(34)&"taskType"&CHAR(34)&":"&CHAR(34)&$F20&CHAR(34)&","&CHAR(34)&"taskConfig"&CHAR(34)&":{"&IF($F20="gp_value","",IF($F20="minigame_completion",CHAR(34)&"minigame"&CHAR(34)&":"&CHAR(34)&$L20&CHAR(34)&","&CHAR(34)&"message"&CHAR(34)&":"&CHAR(34)&IFERROR(INDEX(minigame_completion!$J$5:$J$47,MATCH($L20,minigame_completion!$A$5:$A$47,0)),"")&CHAR(34)&",",IF($AJ20=1,CHAR(34)&INDEX(Settings!$F$6:$F$13,MATCH($F20,Settings!$E$6:$E$13,0))&CHAR(34)&":"&Calc!$EW20&",",CHAR(34)&INDEX(Settings!$G$6:$G$13,MATCH($F20,Settings!$E$6:$E$13,0))&CHAR(34)&":["&_xlfn.TEXTJOIN(",",TRUE,Calc!$EW20:$FT20)&"],")))&CHAR(34)&"target"&CHAR(34)&":"&$H20&IF($G20="each",","&CHAR(34)&"mode"&CHAR(34)&":"&CHAR(34)&"each"&CHAR(34),"")&"}}") -> {"tileId":33,"taskType":"item_drop","taskConfig":{"items":["Godsword shard 1","Godsword shard 2","Godsword shard 3"],"target":1,"mode":"each"}}
A21: 34 | B21: =IFERROR(INDEX(Maze!$C$5:$C$85,MATCH($A21,Maze!$A$5:$A$85,0)),"") -> Arm 1 | C21: =IFERROR(INDEX(Maze!$D$5:$D$85,MATCH($A21,Maze!$A$5:$A$85,0)),"") -> 15 | D21: =IFERROR(INDEX(Maze!$E$5:$E$85,MATCH($A21,Maze!$A$5:$A$85,0)),"") -> Skippable | E21: =IFERROR(INDEX(Maze!$G$5:$G$85,MATCH($A21,Maze!$A$5:$A$85,0)),"") -> Yes | F21: item_drop | H21: 2 | L21: Burning claw | AJ21: {=SUMPRODUCT(($L21:$AI21<>"")*1)} -> 1 | AK21: =IF($F21="","",IF($G21="each",$AJ21*$H21,$H21)) -> 2 | AL21: =IF($F21="","",IFERROR((IF($G21="each",IF($I21="No",SUM(Calc!$BZ21:$CW21),IF($F21="item_drop",SUM(Calc!$DX21:$EU21),IF($I21="Yes",MAX(Calc!$BZ21:$CW21),SUM(Calc!$BZ21:$CW21)))),$H21/MAX(Calc!$BA21:$BX21)))/IF($J21="",cfg_ratemult,$J21),"")) -> 18.218182 | AM21: =IF($AL21="","",$AL21/MAX(0.1,IF($K21="",IF($B21="Arm 1",cfg_arm1,IF($B21="Arm 2",cfg_arm2,IF($B21="Arm 3",cfg_arm3,cfg_concurrent))),$K21))+cfg_overhead/60) -> 18.418182 | AN21: =IF($AM21="","",INT($AM21/24)&"d "&TEXT(MOD($AM21,24),"0.0")&"h") -> 0d 18h | AO21: =IF($AM21="","",$AL21*IFERROR(GAMMAINV(cfg_pct,MAX(1,IF($F21="item_drop",IF($G21="each",$AJ21*$H21,$H21),1000)),1/MAX(1,IF($F21="item_drop",IF($G21="each",$AJ21*$H21,$H21),1000))),1)/MAX(0.1,IF($K21="",IF($B21="Arm 1",cfg_arm1,IF($B21="Arm 2",cfg_arm2,IF($B21="Arm 3",cfg_arm3,cfg_concurrent))),$K21))+cfg_overhead/60) -> 35.631815 | AP21: =(cfg_base+cfg_slope*$C21^cfg_exp)*IF($D21="KEY",cfg_mkey,IF($D21="END",cfg_mend,IF($D21="Skippable",cfg_mskip,1))) -> 0.72982316 | AQ21: =IF(OR($AM21="",$AP21=0),"",$AM21/$AP21) -> 25.2365 | AR21: =IF($F21="","- no task set -",_xlfn.TEXTJOIN(" | ",TRUE,IF(AND($F21<>"gp_value",$AJ21=0),"no items selected",""),IF(AND($F21="gp_value",$AJ21=0),"pick a farming method so the ETC can be estimated",""),IF(AND($F21="gp_value",$AJ21>1),"gp_value takes no item list - one method is enough",""),IF(AND($F21="minigame_completion",$AJ21>1),"only 1 minigame per tile",""),IF(OR($H21="",$H21<=0),"target missing",""),IF(SUMPRODUCT(($L21:$AE21<>"")*(Calc!$C21:$Z21=0))>0,"unknown entry - not in catalogue",""),IF(AND($G21="each",$AJ21=1),"each with 1 entry = same as any",""),IF($AL21="","ETC not computable",""))) -> #N/A | AS21: 1 would have been useless | AT21: =IF($F21="","","{"&CHAR(34)&"tileId"&CHAR(34)&":"&$A21&","&CHAR(34)&"taskType"&CHAR(34)&":"&CHAR(34)&$F21&CHAR(34)&","&CHAR(34)&"taskConfig"&CHAR(34)&":{"&IF($F21="gp_value","",IF($F21="minigame_completion",CHAR(34)&"minigame"&CHAR(34)&":"&CHAR(34)&$L21&CHAR(34)&","&CHAR(34)&"message"&CHAR(34)&":"&CHAR(34)&IFERROR(INDEX(minigame_completion!$J$5:$J$47,MATCH($L21,minigame_completion!$A$5:$A$47,0)),"")&CHAR(34)&",",IF($AJ21=1,CHAR(34)&INDEX(Settings!$F$6:$F$13,MATCH($F21,Settings!$E$6:$E$13,0))&CHAR(34)&":"&Calc!$EW21&",",CHAR(34)&INDEX(Settings!$G$6:$G$13,MATCH($F21,Settings!$E$6:$E$13,0))&CHAR(34)&":["&_xlfn.TEXTJOIN(",",TRUE,Calc!$EW21:$FT21)&"],")))&CHAR(34)&"target"&CHAR(34)&":"&$H21&IF($G21="each",","&CHAR(34)&"mode"&CHAR(34)&":"&CHAR(34)&"each"&CHAR(34),"")&"}}") -> {"tileId":34,"taskType":"item_drop","taskConfig":{"item":"Burning claw","target":2}}
A22: 51 | B22: =IFERROR(INDEX(Maze!$C$5:$C$85,MATCH($A22,Maze!$A$5:$A$85,0)),"") -> Arm 1 | C22: =IFERROR(INDEX(Maze!$D$5:$D$85,MATCH($A22,Maze!$A$5:$A$85,0)),"") -> 14 | D22: =IFERROR(INDEX(Maze!$E$5:$E$85,MATCH($A22,Maze!$A$5:$A$85,0)),"") -> Forced | E22: =IFERROR(INDEX(Maze!$G$5:$G$85,MATCH($A22,Maze!$A$5:$A$85,0)),"") -> No | F22: item_drop | H22: 5 | L22: Awakener's orb | AJ22: {=SUMPRODUCT(($L22:$AI22<>"")*1)} -> 1 | AK22: =IF($F22="","",IF($G22="each",$AJ22*$H22,$H22)) -> 5 | AL22: =IF($F22="","",IFERROR((IF($G22="each",IF($I22="No",SUM(Calc!$BZ22:$CW22),IF($F22="item_drop",SUM(Calc!$DX22:$EU22),IF($I22="Yes",MAX(Calc!$BZ22:$CW22),SUM(Calc!$BZ22:$CW22)))),$H22/MAX(Calc!$BA22:$BX22)))/IF($J22="",cfg_ratemult,$J22),"")) -> 7.0588235 | AM22: =IF($AL22="","",$AL22/MAX(0.1,IF($K22="",IF($B22="Arm 1",cfg_arm1,IF($B22="Arm 2",cfg_arm2,IF($B22="Arm 3",cfg_arm3,cfg_concurrent))),$K22))+cfg_overhead/60) -> 7.2588235 | AN22: =IF($AM22="","",INT($AM22/24)&"d "&TEXT(MOD($AM22,24),"0.0")&"h") -> 0d 07h | AO22: =IF($AM22="","",$AL22*IFERROR(GAMMAINV(cfg_pct,MAX(1,IF($F22="item_drop",IF($G22="each",$AJ22*$H22,$H22),1000)),1/MAX(1,IF($F22="item_drop",IF($G22="each",$AJ22*$H22,$H22),1000))),1)/MAX(0.1,IF($K22="",IF($B22="Arm 1",cfg_arm1,IF($B22="Arm 2",cfg_arm2,IF($B22="Arm 3",cfg_arm3,cfg_concurrent))),$K22))+cfg_overhead/60) -> 11.485068 | AP22: =(cfg_base+cfg_slope*$C22^cfg_exp)*IF($D22="KEY",cfg_mkey,IF($D22="END",cfg_mend,IF($D22="Skippable",cfg_mskip,1))) -> 1.2293653 | AQ22: =IF(OR($AM22="",$AP22=0),"",$AM22/$AP22) -> 5.9045292 | AR22: =IF($F22="","- no task set -",_xlfn.TEXTJOIN(" | ",TRUE,IF(AND($F22<>"gp_value",$AJ22=0),"no items selected",""),IF(AND($F22="gp_value",$AJ22=0),"pick a farming method so the ETC can be estimated",""),IF(AND($F22="gp_value",$AJ22>1),"gp_value takes no item list - one method is enough",""),IF(AND($F22="minigame_completion",$AJ22>1),"only 1 minigame per tile",""),IF(OR($H22="",$H22<=0),"target missing",""),IF(SUMPRODUCT(($L22:$AE22<>"")*(Calc!$C22:$Z22=0))>0,"unknown entry - not in catalogue",""),IF(AND($G22="each",$AJ22=1),"each with 1 entry = same as any",""),IF($AL22="","ETC not computable",""))) -> #N/A | AS22: O R B | AT22: =IF($F22="","","{"&CHAR(34)&"tileId"&CHAR(34)&":"&$A22&","&CHAR(34)&"taskType"&CHAR(34)&":"&CHAR(34)&$F22&CHAR(34)&","&CHAR(34)&"taskConfig"&CHAR(34)&":{"&IF($F22="gp_value","",IF($F22="minigame_completion",CHAR(34)&"minigame"&CHAR(34)&":"&CHAR(34)&$L22&CHAR(34)&","&CHAR(34)&"message"&CHAR(34)&":"&CHAR(34)&IFERROR(INDEX(minigame_completion!$J$5:$J$47,MATCH($L22,minigame_completion!$A$5:$A$47,0)),"")&CHAR(34)&",",IF($AJ22=1,CHAR(34)&INDEX(Settings!$F$6:$F$13,MATCH($F22,Settings!$E$6:$E$13,0))&CHAR(34)&":"&Calc!$EW22&",",CHAR(34)&INDEX(Settings!$G$6:$G$13,MATCH($F22,Settings!$E$6:$E$13,0))&CHAR(34)&":["&_xlfn.TEXTJOIN(",",TRUE,Calc!$EW22:$FT22)&"],")))&CHAR(34)&"target"&CHAR(34)&":"&$H22&IF($G22="each",","&CHAR(34)&"mode"&CHAR(34)&":"&CHAR(34)&"each"&CHAR(34),"")&"}}") -> {"tileId":51,"taskType":"item_drop","taskConfig":{"item":"Awakener's orb","target":5}}
A23: 52 | B23: =IFERROR(INDEX(Maze!$C$5:$C$85,MATCH($A23,Maze!$A$5:$A$85,0)),"") -> Arm 1 | C23: =IFERROR(INDEX(Maze!$D$5:$D$85,MATCH($A23,Maze!$A$5:$A$85,0)),"") -> 15 | D23: =IFERROR(INDEX(Maze!$E$5:$E$85,MATCH($A23,Maze!$A$5:$A$85,0)),"") -> Forced | E23: =IFERROR(INDEX(Maze!$G$5:$G$85,MATCH($A23,Maze!$A$5:$A$85,0)),"") -> No | F23: item_drop | H23: 1 | L23: Skull of vet'ion | M23: Claws of callisto | N23: Fangs of venenatis | AJ23: {=SUMPRODUCT(($L23:$AI23<>"")*1)} -> 3 | AK23: =IF($F23="","",IF($G23="each",$AJ23*$H23,$H23)) -> 1 | AL23: =IF($F23="","",IFERROR((IF($G23="each",IF($I23="No",SUM(Calc!$BZ23:$CW23),IF($F23="item_drop",SUM(Calc!$DX23:$EU23),IF($I23="Yes",MAX(Calc!$BZ23:$CW23),SUM(Calc!$BZ23:$CW23)))),$H23/MAX(Calc!$BA23:$BX23)))/IF($J23="",cfg_ratemult,$J23),"")) -> 7.5294118 | AM23: =IF($AL23="","",$AL23/MAX(0.1,IF($K23="",IF($B23="Arm 1",cfg_arm1,IF($B23="Arm 2",cfg_arm2,IF($B23="Arm 3",cfg_arm3,cfg_concurrent))),$K23))+cfg_overhead/60) -> 7.7294118 | AN23: =IF($AM23="","",INT($AM23/24)&"d "&TEXT(MOD($AM23,24),"0.0")&"h") -> 0d 08h | AO23: =IF($AM23="","",$AL23*IFERROR(GAMMAINV(cfg_pct,MAX(1,IF($F23="item_drop",IF($G23="each",$AJ23*$H23,$H23),1000)),1/MAX(1,IF($F23="item_drop",IF($G23="each",$AJ23*$H23,$H23),1000))),1)/MAX(0.1,IF($K23="",IF($B23="Arm 1",cfg_arm1,IF($B23="Arm 2",cfg_arm2,IF($B23="Arm 3",cfg_arm3,cfg_concurrent))),$K23))+cfg_overhead/60) -> 17.537111 | AP23: =(cfg_base+cfg_slope*$C23^cfg_exp)*IF($D23="KEY",cfg_mkey,IF($D23="END",cfg_mend,IF($D23="Skippable",cfg_mskip,1))) -> 1.3269512 | AQ23: =IF(OR($AM23="",$AP23=0),"",$AM23/$AP23) -> 5.8249405 | AR23: =IF($F23="","- no task set -",_xlfn.TEXTJOIN(" | ",TRUE,IF(AND($F23<>"gp_value",$AJ23=0),"no items selected",""),IF(AND($F23="gp_value",$AJ23=0),"pick a farming method so the ETC can be estimated",""),IF(AND($F23="gp_value",$AJ23>1),"gp_value takes no item list - one method is enough",""),IF(AND($F23="minigame_completion",$AJ23>1),"only 1 minigame per tile",""),IF(OR($H23="",$H23<=0),"target missing",""),IF(SUMPRODUCT(($L23:$AE23<>"")*(Calc!$C23:$Z23=0))>0,"unknown entry - not in catalogue",""),IF(AND($G23="each",$AJ23=1),"each with 1 entry = same as any",""),IF($AL23="","ETC not computable",""))) -> #N/A | AS23: Upgradescape is fun | AT23: =IF($F23="","","{"&CHAR(34)&"tileId"&CHAR(34)&":"&$A23&","&CHAR(34)&"taskType"&CHAR(34)&":"&CHAR(34)&$F23&CHAR(34)&","&CHAR(34)&"taskConfig"&CHAR(34)&":{"&IF($F23="gp_value","",IF($F23="minigame_completion",CHAR(34)&"minigame"&CHAR(34)&":"&CHAR(34)&$L23&CHAR(34)&","&CHAR(34)&"message"&CHAR(34)&":"&CHAR(34)&IFERROR(INDEX(minigame_completion!$J$5:$J$47,MATCH($L23,minigame_completion!$A$5:$A$47,0)),"")&CHAR(34)&",",IF($AJ23=1,CHAR(34)&INDEX(Settings!$F$6:$F$13,MATCH($F23,Settings!$E$6:$E$13,0))&CHAR(34)&":"&Calc!$EW23&",",CHAR(34)&INDEX(Settings!$G$6:$G$13,MATCH($F23,Settings!$E$6:$E$13,0))&CHAR(34)&":["&_xlfn.TEXTJOIN(",",TRUE,Calc!$EW23:$FT23)&"],")))&CHAR(34)&"target"&CHAR(34)&":"&$H23&IF($G23="each",","&CHAR(34)&"mode"&CHAR(34)&":"&CHAR(34)&"each"&CHAR(34),"")&"}}") -> {"tileId":52,"taskType":"item_drop","taskConfig":{"items":["Skull of vet'ion","Claws of callisto","Fangs of venenatis"],"target":1}}
A24: 53 | B24: =IFERROR(INDEX(Maze!$C$5:$C$85,MATCH($A24,Maze!$A$5:$A$85,0)),"") -> Arm 1 | C24: =IFERROR(INDEX(Maze!$D$5:$D$85,MATCH($A24,Maze!$A$5:$A$85,0)),"") -> 16 | D24: =IFERROR(INDEX(Maze!$E$5:$E$85,MATCH($A24,Maze!$A$5:$A$85,0)),"") -> Forced | E24: =IFERROR(INDEX(Maze!$G$5:$G$85,MATCH($A24,Maze!$A$5:$A$85,0)),"") -> No | F24: npc_kill | H24: 250 | L24: Alchemical Hydra | AJ24: {=SUMPRODUCT(($L24:$AI24<>"")*1)} -> 1 | AK24: =IF($F24="","",IF($G24="each",$AJ24*$H24,$H24)) -> 250 | AL24: =IF($F24="","",IFERROR((IF($G24="each",IF($I24="No",SUM(Calc!$BZ24:$CW24),IF($F24="item_drop",SUM(Calc!$DX24:$EU24),IF($I24="Yes",MAX(Calc!$BZ24:$CW24),SUM(Calc!$BZ24:$CW24)))),$H24/MAX(Calc!$BA24:$BX24)))/IF($J24="",cfg_ratemult,$J24),"")) -> 10 | AM24: =IF($AL24="","",$AL24/MAX(0.1,IF($K24="",IF($B24="Arm 1",cfg_arm1,IF($B24="Arm 2",cfg_arm2,IF($B24="Arm 3",cfg_arm3,cfg_concurrent))),$K24))+cfg_overhead/60) -> 10.2 | AN24: =IF($AM24="","",INT($AM24/24)&"d "&TEXT(MOD($AM24,24),"0.0")&"h") -> 0d 10h | AO24: =IF($AM24="","",$AL24*IFERROR(GAMMAINV(cfg_pct,MAX(1,IF($F24="item_drop",IF($G24="each",$AJ24*$H24,$H24),1000)),1/MAX(1,IF($F24="item_drop",IF($G24="each",$AJ24*$H24,$H24),1000))),1)/MAX(0.1,IF($K24="",IF($B24="Arm 1",cfg_arm1,IF($B24="Arm 2",cfg_arm2,IF($B24="Arm 3",cfg_arm3,cfg_concurrent))),$K24))+cfg_overhead/60) -> 10.607343 | AP24: =(cfg_base+cfg_slope*$C24^cfg_exp)*IF($D24="KEY",cfg_mkey,IF($D24="END",cfg_mend,IF($D24="Skippable",cfg_mskip,1))) -> 1.4288609 | AQ24: =IF(OR($AM24="",$AP24=0),"",$AM24/$AP24) -> 7.1385533 | AR24: =IF($F24="","- no task set -",_xlfn.TEXTJOIN(" | ",TRUE,IF(AND($F24<>"gp_value",$AJ24=0),"no items selected",""),IF(AND($F24="gp_value",$AJ24=0),"pick a farming method so the ETC can be estimated",""),IF(AND($F24="gp_value",$AJ24>1),"gp_value takes no item list - one method is enough",""),IF(AND($F24="minigame_completion",$AJ24>1),"only 1 minigame per tile",""),IF(OR($H24="",$H24<=0),"target missing",""),IF(SUMPRODUCT(($L24:$AE24<>"")*(Calc!$C24:$Z24=0))>0,"unknown entry - not in catalogue",""),IF(AND($G24="each",$AJ24=1),"each with 1 entry = same as any",""),IF($AL24="","ETC not computable",""))) -> #N/A | AS24: Steve Rogers would be proud | AT24: =IF($F24="","","{"&CHAR(34)&"tileId"&CHAR(34)&":"&$A24&","&CHAR(34)&"taskType"&CHAR(34)&":"&CHAR(34)&$F24&CHAR(34)&","&CHAR(34)&"taskConfig"&CHAR(34)&":{"&IF($F24="gp_value","",IF($F24="minigame_completion",CHAR(34)&"minigame"&CHAR(34)&":"&CHAR(34)&$L24&CHAR(34)&","&CHAR(34)&"message"&CHAR(34)&":"&CHAR(34)&IFERROR(INDEX(minigame_completion!$J$5:$J$47,MATCH($L24,minigame_completion!$A$5:$A$47,0)),"")&CHAR(34)&",",IF($AJ24=1,CHAR(34)&INDEX(Settings!$F$6:$F$13,MATCH($F24,Settings!$E$6:$E$13,0))&CHAR(34)&":"&Calc!$EW24&",",CHAR(34)&INDEX(Settings!$G$6:$G$13,MATCH($F24,Settings!$E$6:$E$13,0))&CHAR(34)&":["&_xlfn.TEXTJOIN(",",TRUE,Calc!$EW24:$FT24)&"],")))&CHAR(34)&"target"&CHAR(34)&":"&$H24&IF($G24="each",","&CHAR(34)&"mode"&CHAR(34)&":"&CHAR(34)&"each"&CHAR(34),"")&"}}") -> {"tileId":53,"taskType":"npc_kill","taskConfig":{"npc":"Alchemical Hydra","target":250}}
A25: 62 | B25: =IFERROR(INDEX(Maze!$C$5:$C$85,MATCH($A25,Maze!$A$5:$A$85,0)),"") -> Arm 1 | C25: =IFERROR(INDEX(Maze!$D$5:$D$85,MATCH($A25,Maze!$A$5:$A$85,0)),"") -> 17 | D25: =IFERROR(INDEX(Maze!$E$5:$E$85,MATCH($A25,Maze!$A$5:$A$85,0)),"") -> Forced | E25: =IFERROR(INDEX(Maze!$G$5:$G$85,MATCH($A25,Maze!$A$5:$A$85,0)),"") -> No | F25: item_drop | H25: 1 | L25: Armadyl helmet | M25: Armadyl chestplate | N25: Armadyl chainskirt | O25: Armadyl hilt | AJ25: {=SUMPRODUCT(($L25:$AI25<>"")*1)} -> 4 | AK25: =IF($F25="","",IF($G25="each",$AJ25*$H25,$H25)) -> 1 | AL25: =IF($F25="","",IFERROR((IF($G25="each",IF($I25="No",SUM(Calc!$BZ25:$CW25),IF($F25="item_drop",SUM(Calc!$DX25:$EU25),IF($I25="Yes",MAX(Calc!$BZ25:$CW25),SUM(Calc!$BZ25:$CW25)))),$H25/MAX(Calc!$BA25:$BX25)))/IF($J25="",cfg_ratemult,$J25),"")) -> 4.2333333 | AM25: =IF($AL25="","",$AL25/MAX(0.1,IF($K25="",IF($B25="Arm 1",cfg_arm1,IF($B25="Arm 2",cfg_arm2,IF($B25="Arm 3",cfg_arm3,cfg_concurrent))),$K25))+cfg_overhead/60) -> 4.4333333 | AN25: =IF($AM25="","",INT($AM25/24)&"d "&TEXT(MOD($AM25,24),"0.0")&"h") -> 0d 04h | AO25: =IF($AM25="","",$AL25*IFERROR(GAMMAINV(cfg_pct,MAX(1,IF($F25="item_drop",IF($G25="each",$AJ25*$H25,$H25),1000)),1/MAX(1,IF($F25="item_drop",IF($G25="each",$AJ25*$H25,$H25),1000))),1)/MAX(0.1,IF($K25="",IF($B25="Arm 1",cfg_arm1,IF($B25="Arm 2",cfg_arm2,IF($B25="Arm 3",cfg_arm3,cfg_concurrent))),$K25))+cfg_overhead/60) -> 9.9476102 | AP25: =(cfg_base+cfg_slope*$C25^cfg_exp)*IF($D25="KEY",cfg_mkey,IF($D25="END",cfg_mend,IF($D25="Skippable",cfg_mskip,1))) -> 1.5349979 | AQ25: =IF(OR($AM25="",$AP25=0),"",$AM25/$AP25) -> 2.8881689 | AR25: =IF($F25="","- no task set -",_xlfn.TEXTJOIN(" | ",TRUE,IF(AND($F25<>"gp_value",$AJ25=0),"no items selected",""),IF(AND($F25="gp_value",$AJ25=0),"pick a farming method so the ETC can be estimated",""),IF(AND($F25="gp_value",$AJ25>1),"gp_value takes no item list - one method is enough",""),IF(AND($F25="minigame_completion",$AJ25>1),"only 1 minigame per tile",""),IF(OR($H25="",$H25<=0),"target missing",""),IF(SUMPRODUCT(($L25:$AE25<>"")*(Calc!$C25:$Z25=0))>0,"unknown entry - not in catalogue",""),IF(AND($G25="each",$AJ25=1),"each with 1 entry = same as any",""),IF($AL25="","ETC not computable",""))) -> #N/A | AS25: Angry birds | AT25: =IF($F25="","","{"&CHAR(34)&"tileId"&CHAR(34)&":"&$A25&","&CHAR(34)&"taskType"&CHAR(34)&":"&CHAR(34)&$F25&CHAR(34)&","&CHAR(34)&"taskConfig"&CHAR(34)&":{"&IF($F25="gp_value","",IF($F25="minigame_completion",CHAR(34)&"minigame"&CHAR(34)&":"&CHAR(34)&$L25&CHAR(34)&","&CHAR(34)&"message"&CHAR(34)&":"&CHAR(34)&IFERROR(INDEX(minigame_completion!$J$5:$J$47,MATCH($L25,minigame_completion!$A$5:$A$47,0)),"")&CHAR(34)&",",IF($AJ25=1,CHAR(34)&INDEX(Settings!$F$6:$F$13,MATCH($F25,Settings!$E$6:$E$13,0))&CHAR(34)&":"&Calc!$EW25&",",CHAR(34)&INDEX(Settings!$G$6:$G$13,MATCH($F25,Settings!$E$6:$E$13,0))&CHAR(34)&":["&_xlfn.TEXTJOIN(",",TRUE,Calc!$EW25:$FT25)&"],")))&CHAR(34)&"target"&CHAR(34)&":"&$H25&IF($G25="each",","&CHAR(34)&"mode"&CHAR(34)&":"&CHAR(34)&"each"&CHAR(34),"")&"}}") -> {"tileId":62,"taskType":"item_drop","taskConfig":{"items":["Armadyl helmet","Armadyl chestplate","Armadyl chainskirt","Armadyl hilt"],"target":1}}
A26: 61 | B26: =IFERROR(INDEX(Maze!$C$5:$C$85,MATCH($A26,Maze!$A$5:$A$85,0)),"") -> Arm 1 | C26: =IFERROR(INDEX(Maze!$D$5:$D$85,MATCH($A26,Maze!$A$5:$A$85,0)),"") -> 18 | D26: =IFERROR(INDEX(Maze!$E$5:$E$85,MATCH($A26,Maze!$A$5:$A$85,0)),"") -> Forced | E26: =IFERROR(INDEX(Maze!$G$5:$G$85,MATCH($A26,Maze!$A$5:$A$85,0)),"") -> No | F26: item_drop | H26: 1 | L26: Infernal cape | AJ26: {=SUMPRODUCT(($L26:$AI26<>"")*1)} -> 1 | AK26: =IF($F26="","",IF($G26="each",$AJ26*$H26,$H26)) -> 1 | AL26: =IF($F26="","",IFERROR((IF($G26="each",IF($I26="No",SUM(Calc!$BZ26:$CW26),IF($F26="item_drop",SUM(Calc!$DX26:$EU26),IF($I26="Yes",MAX(Calc!$BZ26:$CW26),SUM(Calc!$BZ26:$CW26)))),$H26/MAX(Calc!$BA26:$BX26)))/IF($J26="",cfg_ratemult,$J26),"")) -> 5 | AM26: =IF($AL26="","",$AL26/MAX(0.1,IF($K26="",IF($B26="Arm 1",cfg_arm1,IF($B26="Arm 2",cfg_arm2,IF($B26="Arm 3",cfg_arm3,cfg_concurrent))),$K26))+cfg_overhead/60) -> 5.2 | AN26: =IF($AM26="","",INT($AM26/24)&"d "&TEXT(MOD($AM26,24),"0.0")&"h") -> 0d 05h | AO26: =IF($AM26="","",$AL26*IFERROR(GAMMAINV(cfg_pct,MAX(1,IF($F26="item_drop",IF($G26="each",$AJ26*$H26,$H26),1000)),1/MAX(1,IF($F26="item_drop",IF($G26="each",$AJ26*$H26,$H26),1000))),1)/MAX(0.1,IF($K26="",IF($B26="Arm 1",cfg_arm1,IF($B26="Arm 2",cfg_arm2,IF($B26="Arm 3",cfg_arm3,cfg_concurrent))),$K26))+cfg_overhead/60) -> 11.712925 | AP26: =(cfg_base+cfg_slope*$C26^cfg_exp)*IF($D26="KEY",cfg_mkey,IF($D26="END",cfg_mend,IF($D26="Skippable",cfg_mskip,1))) -> 1.6452733 | AQ26: =IF(OR($AM26="",$AP26=0),"",$AM26/$AP26) -> 3.1605691 | AR26: =IF($F26="","- no task set -",_xlfn.TEXTJOIN(" | ",TRUE,IF(AND($F26<>"gp_value",$AJ26=0),"no items selected",""),IF(AND($F26="gp_value",$AJ26=0),"pick a farming method so the ETC can be estimated",""),IF(AND($F26="gp_value",$AJ26>1),"gp_value takes no item list - one method is enough",""),IF(AND($F26="minigame_completion",$AJ26>1),"only 1 minigame per tile",""),IF(OR($H26="",$H26<=0),"target missing",""),IF(SUMPRODUCT(($L26:$AE26<>"")*(Calc!$C26:$Z26=0))>0,"unknown entry - not in catalogue",""),IF(AND($G26="each",$AJ26=1),"each with 1 entry = same as any",""),IF($AL26="","ETC not computable",""))) -> #N/A | AS26: Git gut | AT26: =IF($F26="","","{"&CHAR(34)&"tileId"&CHAR(34)&":"&$A26&","&CHAR(34)&"taskType"&CHAR(34)&":"&CHAR(34)&$F26&CHAR(34)&","&CHAR(34)&"taskConfig"&CHAR(34)&":{"&IF($F26="gp_value","",IF($F26="minigame_completion",CHAR(34)&"minigame"&CHAR(34)&":"&CHAR(34)&$L26&CHAR(34)&","&CHAR(34)&"message"&CHAR(34)&":"&CHAR(34)&IFERROR(INDEX(minigame_completion!$J$5:$J$47,MATCH($L26,minigame_completion!$A$5:$A$47,0)),"")&CHAR(34)&",",IF($AJ26=1,CHAR(34)&INDEX(Settings!$F$6:$F$13,MATCH($F26,Settings!$E$6:$E$13,0))&CHAR(34)&":"&Calc!$EW26&",",CHAR(34)&INDEX(Settings!$G$6:$G$13,MATCH($F26,Settings!$E$6:$E$13,0))&CHAR(34)&":["&_xlfn.TEXTJOIN(",",TRUE,Calc!$EW26:$FT26)&"],")))&CHAR(34)&"target"&CHAR(34)&":"&$H26&IF($G26="each",","&CHAR(34)&"mode"&CHAR(34)&":"&CHAR(34)&"each"&CHAR(34),"")&"}}") -> {"tileId":61,"taskType":"item_drop","taskConfig":{"item":"Infernal cape","target":1}}
A27: 60 | B27: =IFERROR(INDEX(Maze!$C$5:$C$85,MATCH($A27,Maze!$A$5:$A$85,0)),"") -> Arm 1 | C27: =IFERROR(INDEX(Maze!$D$5:$D$85,MATCH($A27,Maze!$A$5:$A$85,0)),"") -> 19 | D27: =IFERROR(INDEX(Maze!$E$5:$E$85,MATCH($A27,Maze!$A$5:$A$85,0)),"") -> KEY | E27: =IFERROR(INDEX(Maze!$G$5:$G$85,MATCH($A27,Maze!$A$5:$A$85,0)),"") -> Yes | F27: item_drop | H27: 1 | L27: Twisted bow | M27: Kodai insignia | N27: Elder maul | O27: Ancestral hat | P27: Ancestral robe top | Q27: Ancestral robe bottom | R27: Dragon claws | S27: Twisted buckler | T27: Dinh's bulwark | U27: Dragon hunter crossbow | AJ27: {=SUMPRODUCT(($L27:$AI27<>"")*1)} -> 10 | AK27: =IF($F27="","",IF($G27="each",$AJ27*$H27,$H27)) -> 1 | AL27: =IF($F27="","",IFERROR((IF($G27="each",IF($I27="No",SUM(Calc!$BZ27:$CW27),IF($F27="item_drop",SUM(Calc!$DX27:$EU27),IF($I27="Yes",MAX(Calc!$BZ27:$CW27),SUM(Calc!$BZ27:$CW27)))),$H27/MAX(Calc!$BA27:$BX27)))/IF($J27="",cfg_ratemult,$J27),"")) -> 61.497326 | AM27: =IF($AL27="","",$AL27/MAX(0.1,IF($K27="",IF($B27="Arm 1",cfg_arm1,IF($B27="Arm 2",cfg_arm2,IF($B27="Arm 3",cfg_arm3,cfg_concurrent))),$K27))+cfg_overhead/60) -> 61.697326 | AN27: =IF($AM27="","",INT($AM27/24)&"d "&TEXT(MOD($AM27,24),"0.0")&"h") -> 2d 14h | AO27: =IF($AM27="","",$AL27*IFERROR(GAMMAINV(cfg_pct,MAX(1,IF($F27="item_drop",IF($G27="each",$AJ27*$H27,$H27),1000)),1/MAX(1,IF($F27="item_drop",IF($G27="each",$AJ27*$H27,$H27),1000))),1)/MAX(0.1,IF($K27="",IF($B27="Arm 1",cfg_arm1,IF($B27="Arm 2",cfg_arm2,IF($B27="Arm 3",cfg_arm3,cfg_concurrent))),$K27))+cfg_overhead/60) -> 141.80283 | AP27: =(cfg_base+cfg_slope*$C27^cfg_exp)*IF($D27="KEY",cfg_mkey,IF($D27="END",cfg_mend,IF($D27="Skippable",cfg_mskip,1))) -> 2.9913286 | AQ27: =IF(OR($AM27="",$AP27=0),"",$AM27/$AP27) -> 20.625392 | AR27: =IF($F27="","- no task set -",_xlfn.TEXTJOIN(" | ",TRUE,IF(AND($F27<>"gp_value",$AJ27=0),"no items selected",""),IF(AND($F27="gp_value",$AJ27=0),"pick a farming method so the ETC can be estimated",""),IF(AND($F27="gp_value",$AJ27>1),"gp_value takes no item list - one method is enough",""),IF(AND($F27="minigame_completion",$AJ27>1),"only 1 minigame per tile",""),IF(OR($H27="",$H27<=0),"target missing",""),IF(SUMPRODUCT(($L27:$AE27<>"")*(Calc!$C27:$Z27=0))>0,"unknown entry - not in catalogue",""),IF(AND($G27="each",$AJ27=1),"each with 1 entry = same as any",""),IF($AL27="","ETC not computable",""))) -> #N/A | AS27: Olm's greatest hits | AT27: =IF($F27="","","{"&CHAR(34)&"tileId"&CHAR(34)&":"&$A27&","&CHAR(34)&"taskType"&CHAR(34)&":"&CHAR(34)&$F27&CHAR(34)&","&CHAR(34)&"taskConfig"&CHAR(34)&":{"&IF($F27="gp_value","",IF($F27="minigame_completion",CHAR(34)&"minigame"&CHAR(34)&":"&CHAR(34)&$L27&CHAR(34)&","&CHAR(34)&"message"&CHAR(34)&":"&CHAR(34)&IFERROR(INDEX(minigame_completion!$J$5:$J$47,MATCH($L27,minigame_completion!$A$5:$A$47,0)),"")&CHAR(34)&",",IF($AJ27=1,CHAR(34)&INDEX(Settings!$F$6:$F$13,MATCH($F27,Settings!$E$6:$E$13,0))&CHAR(34)&":"&Calc!$EW27&",",CHAR(34)&INDEX(Settings!$G$6:$G$13,MATCH($F27,Settings!$E$6:$E$13,0))&CHAR(34)&":["&_xlfn.TEXTJOIN(",",TRUE,Calc!$EW27:$FT27)&"],")))&CHAR(34)&"target"&CHAR(34)&":"&$H27&IF($G27="each",","&CHAR(34)&"mode"&CHAR(34)&":"&CHAR(34)&"each"&CHAR(34),"")&"}}") -> {"tileId":60,"taskType":"item_drop","taskConfig":{"items":["Twisted bow","Kodai insignia","Elder maul","Ancestral hat","Ancestral robe top","Ancestral robe bottom","Dragon claws","Twisted buckler","Dinh's bulwark","Dragon hunter crossbow"],"target":1}}
A28: 68 | B28: =IFERROR(INDEX(Maze!$C$5:$C$85,MATCH($A28,Maze!$A$5:$A$85,0)),"") -> Arm 2 | C28: =IFERROR(INDEX(Maze!$D$5:$D$85,MATCH($A28,Maze!$A$5:$A$85,0)),"") -> 1 | D28: =IFERROR(INDEX(Maze!$E$5:$E$85,MATCH($A28,Maze!$A$5:$A$85,0)),"") -> Forced | E28: =IFERROR(INDEX(Maze!$G$5:$G$85,MATCH($A28,Maze!$A$5:$A$85,0)),"") -> No | F28: npc_kill | G28: each | H28: 100 | L28: Crazy archaeologist | M28: Deranged archaeologist | AJ28: {=SUMPRODUCT(($L28:$AI28<>"")*1)} -> 2 | AK28: =IF($F28="","",IF($G28="each",$AJ28*$H28,$H28)) -> 200 | AL28: =IF($F28="","",IFERROR((IF($G28="each",IF($I28="No",SUM(Calc!$BZ28:$CW28),IF($F28="item_drop",SUM(Calc!$DX28:$EU28),IF($I28="Yes",MAX(Calc!$BZ28:$CW28),SUM(Calc!$BZ28:$CW28)))),$H28/MAX(Calc!$BA28:$BX28)))/IF($J28="",cfg_ratemult,$J28),"")) -> 4.4444444 | AM28: =IF($AL28="","",$AL28/MAX(0.1,IF($K28="",IF($B28="Arm 1",cfg_arm1,IF($B28="Arm 2",cfg_arm2,IF($B28="Arm 3",cfg_arm3,cfg_concurrent))),$K28))+cfg_overhead/60) -> 4.6444444 | AN28: =IF($AM28="","",INT($AM28/24)&"d "&TEXT(MOD($AM28,24),"0.0")&"h") -> 0d 05h | AO28: =IF($AM28="","",$AL28*IFERROR(GAMMAINV(cfg_pct,MAX(1,IF($F28="item_drop",IF($G28="each",$AJ28*$H28,$H28),1000)),1/MAX(1,IF($F28="item_drop",IF($G28="each",$AJ28*$H28,$H28),1000))),1)/MAX(0.1,IF($K28="",IF($B28="Arm 1",cfg_arm1,IF($B28="Arm 2",cfg_arm2,IF($B28="Arm 3",cfg_arm3,cfg_concurrent))),$K28))+cfg_overhead/60) -> 4.8254858 | AP28: =(cfg_base+cfg_slope*$C28^cfg_exp)*IF($D28="KEY",cfg_mkey,IF($D28="END",cfg_mend,IF($D28="Skippable",cfg_mskip,1))) -> 0.4304 | AQ28: =IF(OR($AM28="",$AP28=0),"",$AM28/$AP28) -> 10.790995 | AR28: =IF($F28="","- no task set -",_xlfn.TEXTJOIN(" | ",TRUE,IF(AND($F28<>"gp_value",$AJ28=0),"no items selected",""),IF(AND($F28="gp_value",$AJ28=0),"pick a farming method so the ETC can be estimated",""),IF(AND($F28="gp_value",$AJ28>1),"gp_value takes no item list - one method is enough",""),IF(AND($F28="minigame_completion",$AJ28>1),"only 1 minigame per tile",""),IF(OR($H28="",$H28<=0),"target missing",""),IF(SUMPRODUCT(($L28:$AE28<>"")*(Calc!$C28:$Z28=0))>0,"unknown entry - not in catalogue",""),IF(AND($G28="each",$AJ28=1),"each with 1 entry = same as any",""),IF($AL28="","ETC not computable",""))) -> #N/A | AS28: Crazy? I was crazy once | AT28: =IF($F28="","","{"&CHAR(34)&"tileId"&CHAR(34)&":"&$A28&","&CHAR(34)&"taskType"&CHAR(34)&":"&CHAR(34)&$F28&CHAR(34)&","&CHAR(34)&"taskConfig"&CHAR(34)&":{"&IF($F28="gp_value","",IF($F28="minigame_completion",CHAR(34)&"minigame"&CHAR(34)&":"&CHAR(34)&$L28&CHAR(34)&","&CHAR(34)&"message"&CHAR(34)&":"&CHAR(34)&IFERROR(INDEX(minigame_completion!$J$5:$J$47,MATCH($L28,minigame_completion!$A$5:$A$47,0)),"")&CHAR(34)&",",IF($AJ28=1,CHAR(34)&INDEX(Settings!$F$6:$F$13,MATCH($F28,Settings!$E$6:$E$13,0))&CHAR(34)&":"&Calc!$EW28&",",CHAR(34)&INDEX(Settings!$G$6:$G$13,MATCH($F28,Settings!$E$6:$E$13,0))&CHAR(34)&":["&_xlfn.TEXTJOIN(",",TRUE,Calc!$EW28:$FT28)&"],")))&CHAR(34)&"target"&CHAR(34)&":"&$H28&IF($G28="each",","&CHAR(34)&"mode"&CHAR(34)&":"&CHAR(34)&"each"&CHAR(34),"")&"}}") -> {"tileId":68,"taskType":"npc_kill","taskConfig":{"npcs":["Crazy archaeologist","Deranged archaeologist"],"target":100,"mode":"each"}}
A29: 59 | B29: =IFERROR(INDEX(Maze!$C$5:$C$85,MATCH($A29,Maze!$A$5:$A$85,0)),"") -> Arm 2 | C29: =IFERROR(INDEX(Maze!$D$5:$D$85,MATCH($A29,Maze!$A$5:$A$85,0)),"") -> 2 | D29: =IFERROR(INDEX(Maze!$E$5:$E$85,MATCH($A29,Maze!$A$5:$A$85,0)),"") -> Forced | E29: =IFERROR(INDEX(Maze!$G$5:$G$85,MATCH($A29,Maze!$A$5:$A$85,0)),"") -> No | F29: npc_damage | H29: 20000 | L29: Gemstone Crab | AJ29: {=SUMPRODUCT(($L29:$AI29<>"")*1)} -> 1 | AK29: =IF($F29="","",IF($G29="each",$AJ29*$H29,$H29)) -> 20000 | AL29: =IF($F29="","",IFERROR((IF($G29="each",IF($I29="No",SUM(Calc!$BZ29:$CW29),IF($F29="item_drop",SUM(Calc!$DX29:$EU29),IF($I29="Yes",MAX(Calc!$BZ29:$CW29),SUM(Calc!$BZ29:$CW29)))),$H29/MAX(Calc!$BA29:$BX29)))/IF($J29="",cfg_ratemult,$J29),"")) -> 1 | AM29: =IF($AL29="","",$AL29/MAX(0.1,IF($K29="",IF($B29="Arm 1",cfg_arm1,IF($B29="Arm 2",cfg_arm2,IF($B29="Arm 3",cfg_arm3,cfg_concurrent))),$K29))+cfg_overhead/60) -> 1.2 | AN29: =IF($AM29="","",INT($AM29/24)&"d "&TEXT(MOD($AM29,24),"0.0")&"h") -> 0d 01h | AO29: =IF($AM29="","",$AL29*IFERROR(GAMMAINV(cfg_pct,MAX(1,IF($F29="item_drop",IF($G29="each",$AJ29*$H29,$H29),1000)),1/MAX(1,IF($F29="item_drop",IF($G29="each",$AJ29*$H29,$H29),1000))),1)/MAX(0.1,IF($K29="",IF($B29="Arm 1",cfg_arm1,IF($B29="Arm 2",cfg_arm2,IF($B29="Arm 3",cfg_arm3,cfg_concurrent))),$K29))+cfg_overhead/60) -> 1.2407343 | AP29: =(cfg_base+cfg_slope*$C29^cfg_exp)*IF($D29="KEY",cfg_mkey,IF($D29="END",cfg_mend,IF($D29="Skippable",cfg_mskip,1))) -> 0.4526387 | AQ29: =IF(OR($AM29="",$AP29=0),"",$AM29/$AP29) -> 2.6511211 | AR29: =IF($F29="","- no task set -",_xlfn.TEXTJOIN(" | ",TRUE,IF(AND($F29<>"gp_value",$AJ29=0),"no items selected",""),IF(AND($F29="gp_value",$AJ29=0),"pick a farming method so the ETC can be estimated",""),IF(AND($F29="gp_value",$AJ29>1),"gp_value takes no item list - one method is enough",""),IF(AND($F29="minigame_completion",$AJ29>1),"only 1 minigame per tile",""),IF(OR($H29="",$H29<=0),"target missing",""),IF(SUMPRODUCT(($L29:$AE29<>"")*(Calc!$C29:$Z29=0))>0,"unknown entry - not in catalogue",""),IF(AND($G29="each",$AJ29=1),"each with 1 entry = same as any",""),IF($AL29="","ETC not computable",""))) -> #N/A | AS29: Poor crab keeps getting harassed | AT29: =IF($F29="","","{"&CHAR(34)&"tileId"&CHAR(34)&":"&$A29&","&CHAR(34)&"taskType"&CHAR(34)&":"&CHAR(34)&$F29&CHAR(34)&","&CHAR(34)&"taskConfig"&CHAR(34)&":{"&IF($F29="gp_value","",IF($F29="minigame_completion",CHAR(34)&"minigame"&CHAR(34)&":"&CHAR(34)&$L29&CHAR(34)&","&CHAR(34)&"message"&CHAR(34)&":"&CHAR(34)&IFERROR(INDEX(minigame_completion!$J$5:$J$47,MATCH($L29,minigame_completion!$A$5:$A$47,0)),"")&CHAR(34)&",",IF($AJ29=1,CHAR(34)&INDEX(Settings!$F$6:$F$13,MATCH($F29,Settings!$E$6:$E$13,0))&CHAR(34)&":"&Calc!$EW29&",",CHAR(34)&INDEX(Settings!$G$6:$G$13,MATCH($F29,Settings!$E$6:$E$13,0))&CHAR(34)&":["&_xlfn.TEXTJOIN(",",TRUE,Calc!$EW29:$FT29)&"],")))&CHAR(34)&"target"&CHAR(34)&":"&$H29&IF($G29="each",","&CHAR(34)&"mode"&CHAR(34)&":"&CHAR(34)&"each"&CHAR(34),"")&"}}") -> {"tileId":59,"taskType":"npc_damage","taskConfig":{"npc":"Gemstone Crab","target":20000}}
A30: 50 | B30: =IFERROR(INDEX(Maze!$C$5:$C$85,MATCH($A30,Maze!$A$5:$A$85,0)),"") -> Arm 2 | C30: =IFERROR(INDEX(Maze!$D$5:$D$85,MATCH($A30,Maze!$A$5:$A$85,0)),"") -> 3 | D30: =IFERROR(INDEX(Maze!$E$5:$E$85,MATCH($A30,Maze!$A$5:$A$85,0)),"") -> Forced | E30: =IFERROR(INDEX(Maze!$G$5:$G$85,MATCH($A30,Maze!$A$5:$A$85,0)),"") -> No | F30: clue_completion | H30: 40 | L30: easy | AJ30: {=SUMPRODUCT(($L30:$AI30<>"")*1)} -> 1 | AK30: =IF($F30="","",IF($G30="each",$AJ30*$H30,$H30)) -> 40 | AL30: =IF($F30="","",IFERROR((IF($G30="each",IF($I30="No",SUM(Calc!$BZ30:$CW30),IF($F30="item_drop",SUM(Calc!$DX30:$EU30),IF($I30="Yes",MAX(Calc!$BZ30:$CW30),SUM(Calc!$BZ30:$CW30)))),$H30/MAX(Calc!$BA30:$BX30)))/IF($J30="",cfg_ratemult,$J30),"")) -> 2.8571429 | AM30: =IF($AL30="","",$AL30/MAX(0.1,IF($K30="",IF($B30="Arm 1",cfg_arm1,IF($B30="Arm 2",cfg_arm2,IF($B30="Arm 3",cfg_arm3,cfg_concurrent))),$K30))+cfg_overhead/60) -> 3.0571429 | AN30: =IF($AM30="","",INT($AM30/24)&"d "&TEXT(MOD($AM30,24),"0.0")&"h") -> 0d 03h | AO30: =IF($AM30="","",$AL30*IFERROR(GAMMAINV(cfg_pct,MAX(1,IF($F30="item_drop",IF($G30="each",$AJ30*$H30,$H30),1000)),1/MAX(1,IF($F30="item_drop",IF($G30="each",$AJ30*$H30,$H30),1000))),1)/MAX(0.1,IF($K30="",IF($B30="Arm 1",cfg_arm1,IF($B30="Arm 2",cfg_arm2,IF($B30="Arm 3",cfg_arm3,cfg_concurrent))),$K30))+cfg_overhead/60) -> 3.1735266 | AP30: =(cfg_base+cfg_slope*$C30^cfg_exp)*IF($D30="KEY",cfg_mkey,IF($D30="END",cfg_mend,IF($D30="Skippable",cfg_mskip,1))) -> 0.48372112 | AQ30: =IF(OR($AM30="",$AP30=0),"",$AM30/$AP30) -> 6.3200524 | AR30: =IF($F30="","- no task set -",_xlfn.TEXTJOIN(" | ",TRUE,IF(AND($F30<>"gp_value",$AJ30=0),"no items selected",""),IF(AND($F30="gp_value",$AJ30=0),"pick a farming method so the ETC can be estimated",""),IF(AND($F30="gp_value",$AJ30>1),"gp_value takes no item list - one method is enough",""),IF(AND($F30="minigame_completion",$AJ30>1),"only 1 minigame per tile",""),IF(OR($H30="",$H30<=0),"target missing",""),IF(SUMPRODUCT(($L30:$AE30<>"")*(Calc!$C30:$Z30=0))>0,"unknown entry - not in catalogue",""),IF(AND($G30="each",$AJ30=1),"each with 1 entry = same as any",""),IF($AL30="","ETC not computable",""))) -> #N/A | AS30: Easy peasy lemon squeezy | AT30: =IF($F30="","","{"&CHAR(34)&"tileId"&CHAR(34)&":"&$A30&","&CHAR(34)&"taskType"&CHAR(34)&":"&CHAR(34)&$F30&CHAR(34)&","&CHAR(34)&"taskConfig"&CHAR(34)&":{"&IF($F30="gp_value","",IF($F30="minigame_completion",CHAR(34)&"minigame"&CHAR(34)&":"&CHAR(34)&$L30&CHAR(34)&","&CHAR(34)&"message"&CHAR(34)&":"&CHAR(34)&IFERROR(INDEX(minigame_completion!$J$5:$J$47,MATCH($L30,minigame_completion!$A$5:$A$47,0)),"")&CHAR(34)&",",IF($AJ30=1,CHAR(34)&INDEX(Settings!$F$6:$F$13,MATCH($F30,Settings!$E$6:$E$13,0))&CHAR(34)&":"&Calc!$EW30&",",CHAR(34)&INDEX(Settings!$G$6:$G$13,MATCH($F30,Settings!$E$6:$E$13,0))&CHAR(34)&":["&_xlfn.TEXTJOIN(",",TRUE,Calc!$EW30:$FT30)&"],")))&CHAR(34)&"target"&CHAR(34)&":"&$H30&IF($G30="each",","&CHAR(34)&"mode"&CHAR(34)&":"&CHAR(34)&"each"&CHAR(34),"")&"}}") -> {"tileId":50,"taskType":"clue_completion","taskConfig":{"tier":"easy","target":40}}
A31: 41 | B31: =IFERROR(INDEX(Maze!$C$5:$C$85,MATCH($A31,Maze!$A$5:$A$85,0)),"") -> Arm 2 | C31: =IFERROR(INDEX(Maze!$D$5:$D$85,MATCH($A31,Maze!$A$5:$A$85,0)),"") -> 4 | D31: =IFERROR(INDEX(Maze!$E$5:$E$85,MATCH($A31,Maze!$A$5:$A$85,0)),"") -> Forced | E31: =IFERROR(INDEX(Maze!$G$5:$G$85,MATCH($A31,Maze!$A$5:$A$85,0)),"") -> No | F31: item_drop | H31: 5 | L31: Scurrius' spine | AJ31: {=SUMPRODUCT(($L31:$AI31<>"")*1)} -> 1 | AK31: =IF($F31="","",IF($G31="each",$AJ31*$H31,$H31)) -> 5 | AL31: =IF($F31="","",IFERROR((IF($G31="each",IF($I31="No",SUM(Calc!$BZ31:$CW31),IF($F31="item_drop",SUM(Calc!$DX31:$EU31),IF($I31="Yes",MAX(Calc!$BZ31:$CW31),SUM(Calc!$BZ31:$CW31)))),$H31/MAX(Calc!$BA31:$BX31)))/IF($J31="",cfg_ratemult,$J31),"")) -> 2.75 | AM31: =IF($AL31="","",$AL31/MAX(0.1,IF($K31="",IF($B31="Arm 1",cfg_arm1,IF($B31="Arm 2",cfg_arm2,IF($B31="Arm 3",cfg_arm3,cfg_concurrent))),$K31))+cfg_overhead/60) -> 2.95 | AN31: =IF($AM31="","",INT($AM31/24)&"d "&TEXT(MOD($AM31,24),"0.0")&"h") -> 0d 03h | AO31: =IF($AM31="","",$AL31*IFERROR(GAMMAINV(cfg_pct,MAX(1,IF($F31="item_drop",IF($G31="each",$AJ31*$H31,$H31),1000)),1/MAX(1,IF($F31="item_drop",IF($G31="each",$AJ31*$H31,$H31),1000))),1)/MAX(0.1,IF($K31="",IF($B31="Arm 1",cfg_arm1,IF($B31="Arm 2",cfg_arm2,IF($B31="Arm 3",cfg_arm3,cfg_concurrent))),$K31))+cfg_overhead/60) -> 4.5964743 | AP31: =(cfg_base+cfg_slope*$C31^cfg_exp)*IF($D31="KEY",cfg_mkey,IF($D31="END",cfg_mend,IF($D31="Skippable",cfg_mskip,1))) -> 0.52243122 | AQ31: =IF(OR($AM31="",$AP31=0),"",$AM31/$AP31) -> 5.6466764 | AR31: =IF($F31="","- no task set -",_xlfn.TEXTJOIN(" | ",TRUE,IF(AND($F31<>"gp_value",$AJ31=0),"no items selected",""),IF(AND($F31="gp_value",$AJ31=0),"pick a farming method so the ETC can be estimated",""),IF(AND($F31="gp_value",$AJ31>1),"gp_value takes no item list - one method is enough",""),IF(AND($F31="minigame_completion",$AJ31>1),"only 1 minigame per tile",""),IF(OR($H31="",$H31<=0),"target missing",""),IF(SUMPRODUCT(($L31:$AE31<>"")*(Calc!$C31:$Z31=0))>0,"unknown entry - not in catalogue",""),IF(AND($G31="each",$AJ31=1),"each with 1 entry = same as any",""),IF($AL31="","ETC not computable",""))) -> #N/A | AS31: My neck, my back ft Thomas the engine | AT31: =IF($F31="","","{"&CHAR(34)&"tileId"&CHAR(34)&":"&$A31&","&CHAR(34)&"taskType"&CHAR(34)&":"&CHAR(34)&$F31&CHAR(34)&","&CHAR(34)&"taskConfig"&CHAR(34)&":{"&IF($F31="gp_value","",IF($F31="minigame_completion",CHAR(34)&"minigame"&CHAR(34)&":"&CHAR(34)&$L31&CHAR(34)&","&CHAR(34)&"message"&CHAR(34)&":"&CHAR(34)&IFERROR(INDEX(minigame_completion!$J$5:$J$47,MATCH($L31,minigame_completion!$A$5:$A$47,0)),"")&CHAR(34)&",",IF($AJ31=1,CHAR(34)&INDEX(Settings!$F$6:$F$13,MATCH($F31,Settings!$E$6:$E$13,0))&CHAR(34)&":"&Calc!$EW31&",",CHAR(34)&INDEX(Settings!$G$6:$G$13,MATCH($F31,Settings!$E$6:$E$13,0))&CHAR(34)&":["&_xlfn.TEXTJOIN(",",TRUE,Calc!$EW31:$FT31)&"],")))&CHAR(34)&"target"&CHAR(34)&":"&$H31&IF($G31="each",","&CHAR(34)&"mode"&CHAR(34)&":"&CHAR(34)&"each"&CHAR(34),"")&"}}") -> {"tileId":41,"taskType":"item_drop","taskConfig":{"item":"Scurrius' spine","target":5}}
A32: 32 | B32: =IFERROR(INDEX(Maze!$C$5:$C$85,MATCH($A32,Maze!$A$5:$A$85,0)),"") -> Arm 2 | C32: =IFERROR(INDEX(Maze!$D$5:$D$85,MATCH($A32,Maze!$A$5:$A$85,0)),"") -> 5 | D32: =IFERROR(INDEX(Maze!$E$5:$E$85,MATCH($A32,Maze!$A$5:$A$85,0)),"") -> Forced | E32: =IFERROR(INDEX(Maze!$G$5:$G$85,MATCH($A32,Maze!$A$5:$A$85,0)),"") -> No | F32: npc_kill | H32: 300 | L32: Vorkath | AJ32: {=SUMPRODUCT(($L32:$AI32<>"")*1)} -> 1 | AK32: =IF($F32="","",IF($G32="each",$AJ32*$H32,$H32)) -> 300 | AL32: =IF($F32="","",IFERROR((IF($G32="each",IF($I32="No",SUM(Calc!$BZ32:$CW32),IF($F32="item_drop",SUM(Calc!$DX32:$EU32),IF($I32="Yes",MAX(Calc!$BZ32:$CW32),SUM(Calc!$BZ32:$CW32)))),$H32/MAX(Calc!$BA32:$BX32)))/IF($J32="",cfg_ratemult,$J32),"")) -> 10 | AM32: =IF($AL32="","",$AL32/MAX(0.1,IF($K32="",IF($B32="Arm 1",cfg_arm1,IF($B32="Arm 2",cfg_arm2,IF($B32="Arm 3",cfg_arm3,cfg_concurrent))),$K32))+cfg_overhead/60) -> 10.2 | AN32: =IF($AM32="","",INT($AM32/24)&"d "&TEXT(MOD($AM32,24),"0.0")&"h") -> 0d 10h | AO32: =IF($AM32="","",$AL32*IFERROR(GAMMAINV(cfg_pct,MAX(1,IF($F32="item_drop",IF($G32="each",$AJ32*$H32,$H32),1000)),1/MAX(1,IF($F32="item_drop",IF($G32="each",$AJ32*$H32,$H32),1000))),1)/MAX(0.1,IF($K32="",IF($B32="Arm 1",cfg_arm1,IF($B32="Arm 2",cfg_arm2,IF($B32="Arm 3",cfg_arm3,cfg_concurrent))),$K32))+cfg_overhead/60) -> 10.607343 | AP32: =(cfg_base+cfg_slope*$C32^cfg_exp)*IF($D32="KEY",cfg_mkey,IF($D32="END",cfg_mend,IF($D32="Skippable",cfg_mskip,1))) -> 0.56802458 | AQ32: =IF(OR($AM32="",$AP32=0),"",$AM32/$AP32) -> 17.956969 | AR32: =IF($F32="","- no task set -",_xlfn.TEXTJOIN(" | ",TRUE,IF(AND($F32<>"gp_value",$AJ32=0),"no items selected",""),IF(AND($F32="gp_value",$AJ32=0),"pick a farming method so the ETC can be estimated",""),IF(AND($F32="gp_value",$AJ32>1),"gp_value takes no item list - one method is enough",""),IF(AND($F32="minigame_completion",$AJ32>1),"only 1 minigame per tile",""),IF(OR($H32="",$H32<=0),"target missing",""),IF(SUMPRODUCT(($L32:$AE32<>"")*(Calc!$C32:$Z32=0))>0,"unknown entry - not in catalogue",""),IF(AND($G32="each",$AJ32=1),"each with 1 entry = same as any",""),IF($AL32="","ETC not computable",""))) -> #N/A | AS32: Dragon slayer 2: Electric Boogaloo | AT32: =IF($F32="","","{"&CHAR(34)&"tileId"&CHAR(34)&":"&$A32&","&CHAR(34)&"taskType"&CHAR(34)&":"&CHAR(34)&$F32&CHAR(34)&","&CHAR(34)&"taskConfig"&CHAR(34)&":{"&IF($F32="gp_value","",IF($F32="minigame_completion",CHAR(34)&"minigame"&CHAR(34)&":"&CHAR(34)&$L32&CHAR(34)&","&CHAR(34)&"message"&CHAR(34)&":"&CHAR(34)&IFERROR(INDEX(minigame_completion!$J$5:$J$47,MATCH($L32,minigame_completion!$A$5:$A$47,0)),"")&CHAR(34)&",",IF($AJ32=1,CHAR(34)&INDEX(Settings!$F$6:$F$13,MATCH($F32,Settings!$E$6:$E$13,0))&CHAR(34)&":"&Calc!$EW32&",",CHAR(34)&INDEX(Settings!$G$6:$G$13,MATCH($F32,Settings!$E$6:$E$13,0))&CHAR(34)&":["&_xlfn.TEXTJOIN(",",TRUE,Calc!$EW32:$FT32)&"],")))&CHAR(34)&"target"&CHAR(34)&":"&$H32&IF($G32="each",","&CHAR(34)&"mode"&CHAR(34)&":"&CHAR(34)&"each"&CHAR(34),"")&"}}") -> {"tileId":32,"taskType":"npc_kill","taskConfig":{"npc":"Vorkath","target":300}}
A33: 31 | B33: =IFERROR(INDEX(Maze!$C$5:$C$85,MATCH($A33,Maze!$A$5:$A$85,0)),"") -> Arm 2 | C33: =IFERROR(INDEX(Maze!$D$5:$D$85,MATCH($A33,Maze!$A$5:$A$85,0)),"") -> 6 | D33: =IFERROR(INDEX(Maze!$E$5:$E$85,MATCH($A33,Maze!$A$5:$A$85,0)),"") -> Forced | E33: =IFERROR(INDEX(Maze!$G$5:$G$85,MATCH($A33,Maze!$A$5:$A$85,0)),"") -> No | F33: item_drop | H33: 5 | L33: Fire cape | AJ33: {=SUMPRODUCT(($L33:$AI33<>"")*1)} -> 1 | AK33: =IF($F33="","",IF($G33="each",$AJ33*$H33,$H33)) -> 5 | AL33: =IF($F33="","",IFERROR((IF($G33="each",IF($I33="No",SUM(Calc!$BZ33:$CW33),IF($F33="item_drop",SUM(Calc!$DX33:$EU33),IF($I33="Yes",MAX(Calc!$BZ33:$CW33),SUM(Calc!$BZ33:$CW33)))),$H33/MAX(Calc!$BA33:$BX33)))/IF($J33="",cfg_ratemult,$J33),"")) -> 7.1428571 | AM33: =IF($AL33="","",$AL33/MAX(0.1,IF($K33="",IF($B33="Arm 1",cfg_arm1,IF($B33="Arm 2",cfg_arm2,IF($B33="Arm 3",cfg_arm3,cfg_concurrent))),$K33))+cfg_overhead/60) -> 7.3428571 | AN33: =IF($AM33="","",INT($AM33/24)&"d "&TEXT(MOD($AM33,24),"0.0")&"h") -> 0d 07h | AO33: =IF($AM33="","",$AL33*IFERROR(GAMMAINV(cfg_pct,MAX(1,IF($F33="item_drop",IF($G33="each",$AJ33*$H33,$H33),1000)),1/MAX(1,IF($F33="item_drop",IF($G33="each",$AJ33*$H33,$H33),1000))),1)/MAX(0.1,IF($K33="",IF($B33="Arm 1",cfg_arm1,IF($B33="Arm 2",cfg_arm2,IF($B33="Arm 3",cfg_arm3,cfg_concurrent))),$K33))+cfg_overhead/60) -> 11.619414 | AP33: =(cfg_base+cfg_slope*$C33^cfg_exp)*IF($D33="KEY",cfg_mkey,IF($D33="END",cfg_mend,IF($D33="Skippable",cfg_mskip,1))) -> 0.61997831 | AQ33: =IF(OR($AM33="",$AP33=0),"",$AM33/$AP33) -> 11.843732 | AR33: =IF($F33="","- no task set -",_xlfn.TEXTJOIN(" | ",TRUE,IF(AND($F33<>"gp_value",$AJ33=0),"no items selected",""),IF(AND($F33="gp_value",$AJ33=0),"pick a farming method so the ETC can be estimated",""),IF(AND($F33="gp_value",$AJ33>1),"gp_value takes no item list - one method is enough",""),IF(AND($F33="minigame_completion",$AJ33>1),"only 1 minigame per tile",""),IF(OR($H33="",$H33<=0),"target missing",""),IF(SUMPRODUCT(($L33:$AE33<>"")*(Calc!$C33:$Z33=0))>0,"unknown entry - not in catalogue",""),IF(AND($G33="each",$AJ33=1),"each with 1 entry = same as any",""),IF($AL33="","ETC not computable",""))) -> #N/A | AS33: Welcome to Domino's | AT33: =IF($F33="","","{"&CHAR(34)&"tileId"&CHAR(34)&":"&$A33&","&CHAR(34)&"taskType"&CHAR(34)&":"&CHAR(34)&$F33&CHAR(34)&","&CHAR(34)&"taskConfig"&CHAR(34)&":{"&IF($F33="gp_value","",IF($F33="minigame_completion",CHAR(34)&"minigame"&CHAR(34)&":"&CHAR(34)&$L33&CHAR(34)&","&CHAR(34)&"message"&CHAR(34)&":"&CHAR(34)&IFERROR(INDEX(minigame_completion!$J$5:$J$47,MATCH($L33,minigame_completion!$A$5:$A$47,0)),"")&CHAR(34)&",",IF($AJ33=1,CHAR(34)&INDEX(Settings!$F$6:$F$13,MATCH($F33,Settings!$E$6:$E$13,0))&CHAR(34)&":"&Calc!$EW33&",",CHAR(34)&INDEX(Settings!$G$6:$G$13,MATCH($F33,Settings!$E$6:$E$13,0))&CHAR(34)&":["&_xlfn.TEXTJOIN(",",TRUE,Calc!$EW33:$FT33)&"],")))&CHAR(34)&"target"&CHAR(34)&":"&$H33&IF($G33="each",","&CHAR(34)&"mode"&CHAR(34)&":"&CHAR(34)&"each"&CHAR(34),"")&"}}") -> {"tileId":31,"taskType":"item_drop","taskConfig":{"item":"Fire cape","target":5}}
A34: 30 | B34: =IFERROR(INDEX(Maze!$C$5:$C$85,MATCH($A34,Maze!$A$5:$A$85,0)),"") -> Arm 2 | C34: =IFERROR(INDEX(Maze!$D$5:$D$85,MATCH($A34,Maze!$A$5:$A$85,0)),"") -> 7 | D34: =IFERROR(INDEX(Maze!$E$5:$E$85,MATCH($A34,Maze!$A$5:$A$85,0)),"") -> Skippable | E34: =IFERROR(INDEX(Maze!$G$5:$G$85,MATCH($A34,Maze!$A$5:$A$85,0)),"") -> Yes | F34: item_drop | H34: 1 | L34: Voidwaker hilt | M34: Voidwaker gem | N34: Voidwaker blade | AJ34: {=SUMPRODUCT(($L34:$AI34<>"")*1)} -> 3 | AK34: =IF($F34="","",IF($G34="each",$AJ34*$H34,$H34)) -> 1 | AL34: =IF($F34="","",IFERROR((IF($G34="each",IF($I34="No",SUM(Calc!$BZ34:$CW34),IF($F34="item_drop",SUM(Calc!$DX34:$EU34),IF($I34="Yes",MAX(Calc!$BZ34:$CW34),SUM(Calc!$BZ34:$CW34)))),$H34/MAX(Calc!$BA34:$BX34)))/IF($J34="",cfg_ratemult,$J34),"")) -> 10.588235 | AM34: =IF($AL34="","",$AL34/MAX(0.1,IF($K34="",IF($B34="Arm 1",cfg_arm1,IF($B34="Arm 2",cfg_arm2,IF($B34="Arm 3",cfg_arm3,cfg_concurrent))),$K34))+cfg_overhead/60) -> 10.788235 | AN34: =IF($AM34="","",INT($AM34/24)&"d "&TEXT(MOD($AM34,24),"0.0")&"h") -> 0d 11h | AO34: =IF($AM34="","",$AL34*IFERROR(GAMMAINV(cfg_pct,MAX(1,IF($F34="item_drop",IF($G34="each",$AJ34*$H34,$H34),1000)),1/MAX(1,IF($F34="item_drop",IF($G34="each",$AJ34*$H34,$H34),1000))),1)/MAX(0.1,IF($K34="",IF($B34="Arm 1",cfg_arm1,IF($B34="Arm 2",cfg_arm2,IF($B34="Arm 3",cfg_arm3,cfg_concurrent))),$K34))+cfg_overhead/60) -> 24.580313 | AP34: =(cfg_base+cfg_slope*$C34^cfg_exp)*IF($D34="KEY",cfg_mkey,IF($D34="END",cfg_mend,IF($D34="Skippable",cfg_mskip,1))) -> 0.37284296 | AQ34: =IF(OR($AM34="",$AP34=0),"",$AM34/$AP34) -> 28.935065 | AR34: =IF($F34="","- no task set -",_xlfn.TEXTJOIN(" | ",TRUE,IF(AND($F34<>"gp_value",$AJ34=0),"no items selected",""),IF(AND($F34="gp_value",$AJ34=0),"pick a farming method so the ETC can be estimated",""),IF(AND($F34="gp_value",$AJ34>1),"gp_value takes no item list - one method is enough",""),IF(AND($F34="minigame_completion",$AJ34>1),"only 1 minigame per tile",""),IF(OR($H34="",$H34<=0),"target missing",""),IF(SUMPRODUCT(($L34:$AE34<>"")*(Calc!$C34:$Z34=0))>0,"unknown entry - not in catalogue",""),IF(AND($G34="each",$AJ34=1),"each with 1 entry = same as any",""),IF($AL34="","ETC not computable",""))) -> #N/A | AS34: Be glad it's only 1 piece | AT34: =IF($F34="","","{"&CHAR(34)&"tileId"&CHAR(34)&":"&$A34&","&CHAR(34)&"taskType"&CHAR(34)&":"&CHAR(34)&$F34&CHAR(34)&","&CHAR(34)&"taskConfig"&CHAR(34)&":{"&IF($F34="gp_value","",IF($F34="minigame_completion",CHAR(34)&"minigame"&CHAR(34)&":"&CHAR(34)&$L34&CHAR(34)&","&CHAR(34)&"message"&CHAR(34)&":"&CHAR(34)&IFERROR(INDEX(minigame_completion!$J$5:$J$47,MATCH($L34,minigame_completion!$A$5:$A$47,0)),"")&CHAR(34)&",",IF($AJ34=1,CHAR(34)&INDEX(Settings!$F$6:$F$13,MATCH($F34,Settings!$E$6:$E$13,0))&CHAR(34)&":"&Calc!$EW34&",",CHAR(34)&INDEX(Settings!$G$6:$G$13,MATCH($F34,Settings!$E$6:$E$13,0))&CHAR(34)&":["&_xlfn.TEXTJOIN(",",TRUE,Calc!$EW34:$FT34)&"],")))&CHAR(34)&"target"&CHAR(34)&":"&$H34&IF($G34="each",","&CHAR(34)&"mode"&CHAR(34)&":"&CHAR(34)&"each"&CHAR(34),"")&"}}") -> {"tileId":30,"taskType":"item_drop","taskConfig":{"items":["Voidwaker hilt","Voidwaker gem","Voidwaker blade"],"target":1}}
A35: 40 | B35: =IFERROR(INDEX(Maze!$C$5:$C$85,MATCH($A35,Maze!$A$5:$A$85,0)),"") -> Arm 2 | C35: =IFERROR(INDEX(Maze!$D$5:$D$85,MATCH($A35,Maze!$A$5:$A$85,0)),"") -> 7 | D35: =IFERROR(INDEX(Maze!$E$5:$E$85,MATCH($A35,Maze!$A$5:$A$85,0)),"") -> Forced | E35: =IFERROR(INDEX(Maze!$G$5:$G$85,MATCH($A35,Maze!$A$5:$A$85,0)),"") -> No | F35: item_drop | H35: 1 | L35: Malediction shard 1 | M35: Malediction shard 2 | N35: Malediction shard 3 | AJ35: {=SUMPRODUCT(($L35:$AI35<>"")*1)} -> 3 | AK35: =IF($F35="","",IF($G35="each",$AJ35*$H35,$H35)) -> 1 | AL35: =IF($F35="","",IFERROR((IF($G35="each",IF($I35="No",SUM(Calc!$BZ35:$CW35),IF($F35="item_drop",SUM(Calc!$DX35:$EU35),IF($I35="Yes",MAX(Calc!$BZ35:$CW35),SUM(Calc!$BZ35:$CW35)))),$H35/MAX(Calc!$BA35:$BX35)))/IF($J35="",cfg_ratemult,$J35),"")) -> 5.6888889 | AM35: =IF($AL35="","",$AL35/MAX(0.1,IF($K35="",IF($B35="Arm 1",cfg_arm1,IF($B35="Arm 2",cfg_arm2,IF($B35="Arm 3",cfg_arm3,cfg_concurrent))),$K35))+cfg_overhead/60) -> 5.8888889 | AN35: =IF($AM35="","",INT($AM35/24)&"d "&TEXT(MOD($AM35,24),"0.0")&"h") -> 0d 06h | AO35: =IF($AM35="","",$AL35*IFERROR(GAMMAINV(cfg_pct,MAX(1,IF($F35="item_drop",IF($G35="each",$AJ35*$H35,$H35),1000)),1/MAX(1,IF($F35="item_drop",IF($G35="each",$AJ35*$H35,$H35),1000))),1)/MAX(0.1,IF($K35="",IF($B35="Arm 1",cfg_arm1,IF($B35="Arm 2",cfg_arm2,IF($B35="Arm 3",cfg_arm3,cfg_concurrent))),$K35))+cfg_overhead/60) -> 13.299151 | AP35: =(cfg_base+cfg_slope*$C35^cfg_exp)*IF($D35="KEY",cfg_mkey,IF($D35="END",cfg_mend,IF($D35="Skippable",cfg_mskip,1))) -> 0.6778963 | AQ35: =IF(OR($AM35="",$AP35=0),"",$AM35/$AP35) -> 8.6870055 | AR35: =IF($F35="","- no task set -",_xlfn.TEXTJOIN(" | ",TRUE,IF(AND($F35<>"gp_value",$AJ35=0),"no items selected",""),IF(AND($F35="gp_value",$AJ35=0),"pick a farming method so the ETC can be estimated",""),IF(AND($F35="gp_value",$AJ35>1),"gp_value takes no item list - one method is enough",""),IF(AND($F35="minigame_completion",$AJ35>1),"only 1 minigame per tile",""),IF(OR($H35="",$H35<=0),"target missing",""),IF(SUMPRODUCT(($L35:$AE35<>"")*(Calc!$C35:$Z35=0))>0,"unknown entry - not in catalogue",""),IF(AND($G35="each",$AJ35=1),"each with 1 entry = same as any",""),IF($AL35="","ETC not computable",""))) -> #N/A | AS35: I can shardly believe it | AT35: =IF($F35="","","{"&CHAR(34)&"tileId"&CHAR(34)&":"&$A35&","&CHAR(34)&"taskType"&CHAR(34)&":"&CHAR(34)&$F35&CHAR(34)&","&CHAR(34)&"taskConfig"&CHAR(34)&":{"&IF($F35="gp_value","",IF($F35="minigame_completion",CHAR(34)&"minigame"&CHAR(34)&":"&CHAR(34)&$L35&CHAR(34)&","&CHAR(34)&"message"&CHAR(34)&":"&CHAR(34)&IFERROR(INDEX(minigame_completion!$J$5:$J$47,MATCH($L35,minigame_completion!$A$5:$A$47,0)),"")&CHAR(34)&",",IF($AJ35=1,CHAR(34)&INDEX(Settings!$F$6:$F$13,MATCH($F35,Settings!$E$6:$E$13,0))&CHAR(34)&":"&Calc!$EW35&",",CHAR(34)&INDEX(Settings!$G$6:$G$13,MATCH($F35,Settings!$E$6:$E$13,0))&CHAR(34)&":["&_xlfn.TEXTJOIN(",",TRUE,Calc!$EW35:$FT35)&"],")))&CHAR(34)&"target"&CHAR(34)&":"&$H35&IF($G35="each",","&CHAR(34)&"mode"&CHAR(34)&":"&CHAR(34)&"each"&CHAR(34),"")&"}}") -> {"tileId":40,"taskType":"item_drop","taskConfig":{"items":["Malediction shard 1","Malediction shard 2","Malediction shard 3"],"target":1}}
A36: 39 | B36: =IFERROR(INDEX(Maze!$C$5:$C$85,MATCH($A36,Maze!$A$5:$A$85,0)),"") -> Arm 2 | C36: =IFERROR(INDEX(Maze!$D$5:$D$85,MATCH($A36,Maze!$A$5:$A$85,0)),"") -> 8 | D36: =IFERROR(INDEX(Maze!$E$5:$E$85,MATCH($A36,Maze!$A$5:$A$85,0)),"") -> Forced | E36: =IFERROR(INDEX(Maze!$G$5:$G$85,MATCH($A36,Maze!$A$5:$A$85,0)),"") -> No | F36: clue_completion | H36: 20 | L36: hard | AJ36: {=SUMPRODUCT(($L36:$AI36<>"")*1)} -> 1 | AK36: =IF($F36="","",IF($G36="each",$AJ36*$H36,$H36)) -> 20 | AL36: =IF($F36="","",IFERROR((IF($G36="each",IF($I36="No",SUM(Calc!$BZ36:$CW36),IF($F36="item_drop",SUM(Calc!$DX36:$EU36),IF($I36="Yes",MAX(Calc!$BZ36:$CW36),SUM(Calc!$BZ36:$CW36)))),$H36/MAX(Calc!$BA36:$BX36)))/IF($J36="",cfg_ratemult,$J36),"")) -> 3.3333333 | AM36: =IF($AL36="","",$AL36/MAX(0.1,IF($K36="",IF($B36="Arm 1",cfg_arm1,IF($B36="Arm 2",cfg_arm2,IF($B36="Arm 3",cfg_arm3,cfg_concurrent))),$K36))+cfg_overhead/60) -> 3.5333333 | AN36: =IF($AM36="","",INT($AM36/24)&"d "&TEXT(MOD($AM36,24),"0.0")&"h") -> 0d 04h | AO36: =IF($AM36="","",$AL36*IFERROR(GAMMAINV(cfg_pct,MAX(1,IF($F36="item_drop",IF($G36="each",$AJ36*$H36,$H36),1000)),1/MAX(1,IF($F36="item_drop",IF($G36="each",$AJ36*$H36,$H36),1000))),1)/MAX(0.1,IF($K36="",IF($B36="Arm 1",cfg_arm1,IF($B36="Arm 2",cfg_arm2,IF($B36="Arm 3",cfg_arm3,cfg_concurrent))),$K36))+cfg_overhead/60) -> 3.6691144 | AP36: =(cfg_base+cfg_slope*$C36^cfg_exp)*IF($D36="KEY",cfg_mkey,IF($D36="END",cfg_mend,IF($D36="Skippable",cfg_mskip,1))) -> 0.74146361 | AQ36: =IF(OR($AM36="",$AP36=0),"",$AM36/$AP36) -> 4.7653496 | AR36: =IF($F36="","- no task set -",_xlfn.TEXTJOIN(" | ",TRUE,IF(AND($F36<>"gp_value",$AJ36=0),"no items selected",""),IF(AND($F36="gp_value",$AJ36=0),"pick a farming method so the ETC can be estimated",""),IF(AND($F36="gp_value",$AJ36>1),"gp_value takes no item list - one method is enough",""),IF(AND($F36="minigame_completion",$AJ36>1),"only 1 minigame per tile",""),IF(OR($H36="",$H36<=0),"target missing",""),IF(SUMPRODUCT(($L36:$AE36<>"")*(Calc!$C36:$Z36=0))>0,"unknown entry - not in catalogue",""),IF(AND($G36="each",$AJ36=1),"each with 1 entry = same as any",""),IF($AL36="","ETC not computable",""))) -> #N/A | AS36: Difficult, difficult, lemon difficult | AT36: =IF($F36="","","{"&CHAR(34)&"tileId"&CHAR(34)&":"&$A36&","&CHAR(34)&"taskType"&CHAR(34)&":"&CHAR(34)&$F36&CHAR(34)&","&CHAR(34)&"taskConfig"&CHAR(34)&":{"&IF($F36="gp_value","",IF($F36="minigame_completion",CHAR(34)&"minigame"&CHAR(34)&":"&CHAR(34)&$L36&CHAR(34)&","&CHAR(34)&"message"&CHAR(34)&":"&CHAR(34)&IFERROR(INDEX(minigame_completion!$J$5:$J$47,MATCH($L36,minigame_completion!$A$5:$A$47,0)),"")&CHAR(34)&",",IF($AJ36=1,CHAR(34)&INDEX(Settings!$F$6:$F$13,MATCH($F36,Settings!$E$6:$E$13,0))&CHAR(34)&":"&Calc!$EW36&",",CHAR(34)&INDEX(Settings!$G$6:$G$13,MATCH($F36,Settings!$E$6:$E$13,0))&CHAR(34)&":["&_xlfn.TEXTJOIN(",",TRUE,Calc!$EW36:$FT36)&"],")))&CHAR(34)&"target"&CHAR(34)&":"&$H36&IF($G36="each",","&CHAR(34)&"mode"&CHAR(34)&":"&CHAR(34)&"each"&CHAR(34),"")&"}}") -> {"tileId":39,"taskType":"clue_completion","taskConfig":{"tier":"hard","target":20}}
A37: 38 | B37: =IFERROR(INDEX(Maze!$C$5:$C$85,MATCH($A37,Maze!$A$5:$A$85,0)),"") -> Arm 2 | C37: =IFERROR(INDEX(Maze!$D$5:$D$85,MATCH($A37,Maze!$A$5:$A$85,0)),"") -> 9 | D37: =IFERROR(INDEX(Maze!$E$5:$E$85,MATCH($A37,Maze!$A$5:$A$85,0)),"") -> Forced | E37: =IFERROR(INDEX(Maze!$G$5:$G$85,MATCH($A37,Maze!$A$5:$A$85,0)),"") -> No | F37: agility_lap | H37: 300 | L37: Penguin | AJ37: {=SUMPRODUCT(($L37:$AI37<>"")*1)} -> 1 | AK37: =IF($F37="","",IF($G37="each",$AJ37*$H37,$H37)) -> 300 | AL37: =IF($F37="","",IFERROR((IF($G37="each",IF($I37="No",SUM(Calc!$BZ37:$CW37),IF($F37="item_drop",SUM(Calc!$DX37:$EU37),IF($I37="Yes",MAX(Calc!$BZ37:$CW37),SUM(Calc!$BZ37:$CW37)))),$H37/MAX(Calc!$BA37:$BX37)))/IF($J37="",cfg_ratemult,$J37),"")) -> 10 | AM37: =IF($AL37="","",$AL37/MAX(0.1,IF($K37="",IF($B37="Arm 1",cfg_arm1,IF($B37="Arm 2",cfg_arm2,IF($B37="Arm 3",cfg_arm3,cfg_concurrent))),$K37))+cfg_overhead/60) -> 10.2 | AN37: =IF($AM37="","",INT($AM37/24)&"d "&TEXT(MOD($AM37,24),"0.0")&"h") -> 0d 10h | AO37: =IF($AM37="","",$AL37*IFERROR(GAMMAINV(cfg_pct,MAX(1,IF($F37="item_drop",IF($G37="each",$AJ37*$H37,$H37),1000)),1/MAX(1,IF($F37="item_drop",IF($G37="each",$AJ37*$H37,$H37),1000))),1)/MAX(0.1,IF($K37="",IF($B37="Arm 1",cfg_arm1,IF($B37="Arm 2",cfg_arm2,IF($B37="Arm 3",cfg_arm3,cfg_concurrent))),$K37))+cfg_overhead/60) -> 10.607343 | AP37: =(cfg_base+cfg_slope*$C37^cfg_exp)*IF($D37="KEY",cfg_mkey,IF($D37="END",cfg_mend,IF($D37="Skippable",cfg_mskip,1))) -> 0.81042128 | AQ37: =IF(OR($AM37="",$AP37=0),"",$AM37/$AP37) -> 12.586047 | AR37: =IF($F37="","- no task set -",_xlfn.TEXTJOIN(" | ",TRUE,IF(AND($F37<>"gp_value",$AJ37=0),"no items selected",""),IF(AND($F37="gp_value",$AJ37=0),"pick a farming method so the ETC can be estimated",""),IF(AND($F37="gp_value",$AJ37>1),"gp_value takes no item list - one method is enough",""),IF(AND($F37="minigame_completion",$AJ37>1),"only 1 minigame per tile",""),IF(OR($H37="",$H37<=0),"target missing",""),IF(SUMPRODUCT(($L37:$AE37<>"")*(Calc!$C37:$Z37=0))>0,"unknown entry - not in catalogue",""),IF(AND($G37="each",$AJ37=1),"each with 1 entry = same as any",""),IF($AL37="","ETC not computable",""))) -> #N/A | AS37: Next destination: Madagascar | AT37: =IF($F37="","","{"&CHAR(34)&"tileId"&CHAR(34)&":"&$A37&","&CHAR(34)&"taskType"&CHAR(34)&":"&CHAR(34)&$F37&CHAR(34)&","&CHAR(34)&"taskConfig"&CHAR(34)&":{"&IF($F37="gp_value","",IF($F37="minigame_completion",CHAR(34)&"minigame"&CHAR(34)&":"&CHAR(34)&$L37&CHAR(34)&","&CHAR(34)&"message"&CHAR(34)&":"&CHAR(34)&IFERROR(INDEX(minigame_completion!$J$5:$J$47,MATCH($L37,minigame_completion!$A$5:$A$47,0)),"")&CHAR(34)&",",IF($AJ37=1,CHAR(34)&INDEX(Settings!$F$6:$F$13,MATCH($F37,Settings!$E$6:$E$13,0))&CHAR(34)&":"&Calc!$EW37&",",CHAR(34)&INDEX(Settings!$G$6:$G$13,MATCH($F37,Settings!$E$6:$E$13,0))&CHAR(34)&":["&_xlfn.TEXTJOIN(",",TRUE,Calc!$EW37:$FT37)&"],")))&CHAR(34)&"target"&CHAR(34)&":"&$H37&IF($G37="each",","&CHAR(34)&"mode"&CHAR(34)&":"&CHAR(34)&"each"&CHAR(34),"")&"}}") -> {"tileId":38,"taskType":"agility_lap","taskConfig":{"course":"Penguin","target":300}}
A38: 29 | B38: =IFERROR(INDEX(Maze!$C$5:$C$85,MATCH($A38,Maze!$A$5:$A$85,0)),"") -> Arm 2 | C38: =IFERROR(INDEX(Maze!$D$5:$D$85,MATCH($A38,Maze!$A$5:$A$85,0)),"") -> 10 | D38: =IFERROR(INDEX(Maze!$E$5:$E$85,MATCH($A38,Maze!$A$5:$A$85,0)),"") -> Forced | E38: =IFERROR(INDEX(Maze!$G$5:$G$85,MATCH($A38,Maze!$A$5:$A$85,0)),"") -> No | F38: npc_kill | H38: 250 | L38: Mad Angel | AJ38: {=SUMPRODUCT(($L38:$AI38<>"")*1)} -> 1 | AK38: =IF($F38="","",IF($G38="each",$AJ38*$H38,$H38)) -> 250 | AL38: =IF($F38="","",IFERROR((IF($G38="each",IF($I38="No",SUM(Calc!$BZ38:$CW38),IF($F38="item_drop",SUM(Calc!$DX38:$EU38),IF($I38="Yes",MAX(Calc!$BZ38:$CW38),SUM(Calc!$BZ38:$CW38)))),$H38/MAX(Calc!$BA38:$BX38)))/IF($J38="",cfg_ratemult,$J38),"")) -> 6.25 | AM38: =IF($AL38="","",$AL38/MAX(0.1,IF($K38="",IF($B38="Arm 1",cfg_arm1,IF($B38="Arm 2",cfg_arm2,IF($B38="Arm 3",cfg_arm3,cfg_concurrent))),$K38))+cfg_overhead/60) -> 6.45 | AN38: =IF($AM38="","",INT($AM38/24)&"d "&TEXT(MOD($AM38,24),"0.0")&"h") -> 0d 06h | AO38: =IF($AM38="","",$AL38*IFERROR(GAMMAINV(cfg_pct,MAX(1,IF($F38="item_drop",IF($G38="each",$AJ38*$H38,$H38),1000)),1/MAX(1,IF($F38="item_drop",IF($G38="each",$AJ38*$H38,$H38),1000))),1)/MAX(0.1,IF($K38="",IF($B38="Arm 1",cfg_arm1,IF($B38="Arm 2",cfg_arm2,IF($B38="Arm 3",cfg_arm3,cfg_concurrent))),$K38))+cfg_overhead/60) -> 6.7045894 | AP38: =(cfg_base+cfg_slope*$C38^cfg_exp)*IF($D38="KEY",cfg_mkey,IF($D38="END",cfg_mend,IF($D38="Skippable",cfg_mskip,1))) -> 0.88455094 | AQ38: =IF(OR($AM38="",$AP38=0),"",$AM38/$AP38) -> 7.2918356 | AR38: =IF($F38="","- no task set -",_xlfn.TEXTJOIN(" | ",TRUE,IF(AND($F38<>"gp_value",$AJ38=0),"no items selected",""),IF(AND($F38="gp_value",$AJ38=0),"pick a farming method so the ETC can be estimated",""),IF(AND($F38="gp_value",$AJ38>1),"gp_value takes no item list - one method is enough",""),IF(AND($F38="minigame_completion",$AJ38>1),"only 1 minigame per tile",""),IF(OR($H38="",$H38<=0),"target missing",""),IF(SUMPRODUCT(($L38:$AE38<>"")*(Calc!$C38:$Z38=0))>0,"unknown entry - not in catalogue",""),IF(AND($G38="each",$AJ38=1),"each with 1 entry = same as any",""),IF($AL38="","ETC not computable",""))) -> #N/A | AS38: It's only game, why you heff to be mad | AT38: =IF($F38="","","{"&CHAR(34)&"tileId"&CHAR(34)&":"&$A38&","&CHAR(34)&"taskType"&CHAR(34)&":"&CHAR(34)&$F38&CHAR(34)&","&CHAR(34)&"taskConfig"&CHAR(34)&":{"&IF($F38="gp_value","",IF($F38="minigame_completion",CHAR(34)&"minigame"&CHAR(34)&":"&CHAR(34)&$L38&CHAR(34)&","&CHAR(34)&"message"&CHAR(34)&":"&CHAR(34)&IFERROR(INDEX(minigame_completion!$J$5:$J$47,MATCH($L38,minigame_completion!$A$5:$A$47,0)),"")&CHAR(34)&",",IF($AJ38=1,CHAR(34)&INDEX(Settings!$F$6:$F$13,MATCH($F38,Settings!$E$6:$E$13,0))&CHAR(34)&":"&Calc!$EW38&",",CHAR(34)&INDEX(Settings!$G$6:$G$13,MATCH($F38,Settings!$E$6:$E$13,0))&CHAR(34)&":["&_xlfn.TEXTJOIN(",",TRUE,Calc!$EW38:$FT38)&"],")))&CHAR(34)&"target"&CHAR(34)&":"&$H38&IF($G38="each",","&CHAR(34)&"mode"&CHAR(34)&":"&CHAR(34)&"each"&CHAR(34),"")&"}}") -> {"tileId":29,"taskType":"npc_kill","taskConfig":{"npc":"Mad Angel","target":250}}
A39: 20 | B39: =IFERROR(INDEX(Maze!$C$5:$C$85,MATCH($A39,Maze!$A$5:$A$85,0)),"") -> Arm 2 | C39: =IFERROR(INDEX(Maze!$D$5:$D$85,MATCH($A39,Maze!$A$5:$A$85,0)),"") -> 11 | D39: =IFERROR(INDEX(Maze!$E$5:$E$85,MATCH($A39,Maze!$A$5:$A$85,0)),"") -> Forced | E39: =IFERROR(INDEX(Maze!$G$5:$G$85,MATCH($A39,Maze!$A$5:$A$85,0)),"") -> No | F39: item_drop | H39: 1 | L39: Granite gloves | M39: Granite ring | N39: Granite hammer | O39: Black tourmaline core | AJ39: {=SUMPRODUCT(($L39:$AI39<>"")*1)} -> 4 | AK39: =IF($F39="","",IF($G39="each",$AJ39*$H39,$H39)) -> 1 | AL39: =IF($F39="","",IFERROR((IF($G39="each",IF($I39="No",SUM(Calc!$BZ39:$CW39),IF($F39="item_drop",SUM(Calc!$DX39:$EU39),IF($I39="Yes",MAX(Calc!$BZ39:$CW39),SUM(Calc!$BZ39:$CW39)))),$H39/MAX(Calc!$BA39:$BX39)))/IF($J39="",cfg_ratemult,$J39),"")) -> 6.5789474 | AM39: =IF($AL39="","",$AL39/MAX(0.1,IF($K39="",IF($B39="Arm 1",cfg_arm1,IF($B39="Arm 2",cfg_arm2,IF($B39="Arm 3",cfg_arm3,cfg_concurrent))),$K39))+cfg_overhead/60) -> 6.7789474 | AN39: =IF($AM39="","",INT($AM39/24)&"d "&TEXT(MOD($AM39,24),"0.0")&"h") -> 0d 07h | AO39: =IF($AM39="","",$AL39*IFERROR(GAMMAINV(cfg_pct,MAX(1,IF($F39="item_drop",IF($G39="each",$AJ39*$H39,$H39),1000)),1/MAX(1,IF($F39="item_drop",IF($G39="each",$AJ39*$H39,$H39),1000))),1)/MAX(0.1,IF($K39="",IF($B39="Arm 1",cfg_arm1,IF($B39="Arm 2",cfg_arm2,IF($B39="Arm 3",cfg_arm3,cfg_concurrent))),$K39))+cfg_overhead/60) -> 15.348586 | AP39: =(cfg_base+cfg_slope*$C39^cfg_exp)*IF($D39="KEY",cfg_mkey,IF($D39="END",cfg_mend,IF($D39="Skippable",cfg_mskip,1))) -> 0.96366487 | AQ39: =IF(OR($AM39="",$AP39=0),"",$AM39/$AP39) -> 7.0345486 | AR39: =IF($F39="","- no task set -",_xlfn.TEXTJOIN(" | ",TRUE,IF(AND($F39<>"gp_value",$AJ39=0),"no items selected",""),IF(AND($F39="gp_value",$AJ39=0),"pick a farming method so the ETC can be estimated",""),IF(AND($F39="gp_value",$AJ39>1),"gp_value takes no item list - one method is enough",""),IF(AND($F39="minigame_completion",$AJ39>1),"only 1 minigame per tile",""),IF(OR($H39="",$H39<=0),"target missing",""),IF(SUMPRODUCT(($L39:$AE39<>"")*(Calc!$C39:$Z39=0))>0,"unknown entry - not in catalogue",""),IF(AND($G39="each",$AJ39=1),"each with 1 entry = same as any",""),IF($AL39="","ETC not computable",""))) -> #N/A | AS39: Everyone's favorite slayer task | AT39: =IF($F39="","","{"&CHAR(34)&"tileId"&CHAR(34)&":"&$A39&","&CHAR(34)&"taskType"&CHAR(34)&":"&CHAR(34)&$F39&CHAR(34)&","&CHAR(34)&"taskConfig"&CHAR(34)&":{"&IF($F39="gp_value","",IF($F39="minigame_completion",CHAR(34)&"minigame"&CHAR(34)&":"&CHAR(34)&$L39&CHAR(34)&","&CHAR(34)&"message"&CHAR(34)&":"&CHAR(34)&IFERROR(INDEX(minigame_completion!$J$5:$J$47,MATCH($L39,minigame_completion!$A$5:$A$47,0)),"")&CHAR(34)&",",IF($AJ39=1,CHAR(34)&INDEX(Settings!$F$6:$F$13,MATCH($F39,Settings!$E$6:$E$13,0))&CHAR(34)&":"&Calc!$EW39&",",CHAR(34)&INDEX(Settings!$G$6:$G$13,MATCH($F39,Settings!$E$6:$E$13,0))&CHAR(34)&":["&_xlfn.TEXTJOIN(",",TRUE,Calc!$EW39:$FT39)&"],")))&CHAR(34)&"target"&CHAR(34)&":"&$H39&IF($G39="each",","&CHAR(34)&"mode"&CHAR(34)&":"&CHAR(34)&"each"&CHAR(34),"")&"}}") -> {"tileId":20,"taskType":"item_drop","taskConfig":{"items":["Granite gloves","Granite ring","Granite hammer","Black tourmaline core"],"target":1}}
A40: 21 | B40: =IFERROR(INDEX(Maze!$C$5:$C$85,MATCH($A40,Maze!$A$5:$A$85,0)),"") -> Arm 2 | C40: =IFERROR(INDEX(Maze!$D$5:$D$85,MATCH($A40,Maze!$A$5:$A$85,0)),"") -> 12 | D40: =IFERROR(INDEX(Maze!$E$5:$E$85,MATCH($A40,Maze!$A$5:$A$85,0)),"") -> Forced | E40: =IFERROR(INDEX(Maze!$G$5:$G$85,MATCH($A40,Maze!$A$5:$A$85,0)),"") -> No | F40: npc_kill | G40: each | H40: 50 | L40: General Graardor | M40: K'ril Tsutsaroth | N40: Kree'arra | O40: Commander Zilyana | AJ40: {=SUMPRODUCT(($L40:$AI40<>"")*1)} -> 4 | AK40: =IF($F40="","",IF($G40="each",$AJ40*$H40,$H40)) -> 200 | AL40: =IF($F40="","",IFERROR((IF($G40="each",IF($I40="No",SUM(Calc!$BZ40:$CW40),IF($F40="item_drop",SUM(Calc!$DX40:$EU40),IF($I40="Yes",MAX(Calc!$BZ40:$CW40),SUM(Calc!$BZ40:$CW40)))),$H40/MAX(Calc!$BA40:$BX40)))/IF($J40="",cfg_ratemult,$J40),"")) -> 7.710114 | AM40: =IF($AL40="","",$AL40/MAX(0.1,IF($K40="",IF($B40="Arm 1",cfg_arm1,IF($B40="Arm 2",cfg_arm2,IF($B40="Arm 3",cfg_arm3,cfg_concurrent))),$K40))+cfg_overhead/60) -> 7.910114 | AN40: =IF($AM40="","",INT($AM40/24)&"d "&TEXT(MOD($AM40,24),"0.0")&"h") -> 0d 08h | AO40: =IF($AM40="","",$AL40*IFERROR(GAMMAINV(cfg_pct,MAX(1,IF($F40="item_drop",IF($G40="each",$AJ40*$H40,$H40),1000)),1/MAX(1,IF($F40="item_drop",IF($G40="each",$AJ40*$H40,$H40),1000))),1)/MAX(0.1,IF($K40="",IF($B40="Arm 1",cfg_arm1,IF($B40="Arm 2",cfg_arm2,IF($B40="Arm 3",cfg_arm3,cfg_concurrent))),$K40))+cfg_overhead/60) -> 8.2241801 | AP40: =(cfg_base+cfg_slope*$C40^cfg_exp)*IF($D40="KEY",cfg_mkey,IF($D40="END",cfg_mend,IF($D40="Skippable",cfg_mskip,1))) -> 1.0475992 | AQ40: =IF(OR($AM40="",$AP40=0),"",$AM40/$AP40) -> 7.5507062 | AR40: =IF($F40="","- no task set -",_xlfn.TEXTJOIN(" | ",TRUE,IF(AND($F40<>"gp_value",$AJ40=0),"no items selected",""),IF(AND($F40="gp_value",$AJ40=0),"pick a farming method so the ETC can be estimated",""),IF(AND($F40="gp_value",$AJ40>1),"gp_value takes no item list - one method is enough",""),IF(AND($F40="minigame_completion",$AJ40>1),"only 1 minigame per tile",""),IF(OR($H40="",$H40<=0),"target missing",""),IF(SUMPRODUCT(($L40:$AE40<>"")*(Calc!$C40:$Z40=0))>0,"unknown entry - not in catalogue",""),IF(AND($G40="each",$AJ40=1),"each with 1 entry = same as any",""),IF($AL40="","ETC not computable",""))) -> #N/A | AS40: This used to be endgame | AT40: =IF($F40="","","{"&CHAR(34)&"tileId"&CHAR(34)&":"&$A40&","&CHAR(34)&"taskType"&CHAR(34)&":"&CHAR(34)&$F40&CHAR(34)&","&CHAR(34)&"taskConfig"&CHAR(34)&":{"&IF($F40="gp_value","",IF($F40="minigame_completion",CHAR(34)&"minigame"&CHAR(34)&":"&CHAR(34)&$L40&CHAR(34)&","&CHAR(34)&"message"&CHAR(34)&":"&CHAR(34)&IFERROR(INDEX(minigame_completion!$J$5:$J$47,MATCH($L40,minigame_completion!$A$5:$A$47,0)),"")&CHAR(34)&",",IF($AJ40=1,CHAR(34)&INDEX(Settings!$F$6:$F$13,MATCH($F40,Settings!$E$6:$E$13,0))&CHAR(34)&":"&Calc!$EW40&",",CHAR(34)&INDEX(Settings!$G$6:$G$13,MATCH($F40,Settings!$E$6:$E$13,0))&CHAR(34)&":["&_xlfn.TEXTJOIN(",",TRUE,Calc!$EW40:$FT40)&"],")))&CHAR(34)&"target"&CHAR(34)&":"&$H40&IF($G40="each",","&CHAR(34)&"mode"&CHAR(34)&":"&CHAR(34)&"each"&CHAR(34),"")&"}}") -> {"tileId":21,"taskType":"npc_kill","taskConfig":{"npcs":["General Graardor","K'ril Tsutsaroth","Kree'arra","Commander Zilyana"],"target":50,"mode":"each"}}
A41: 22 | B41: =IFERROR(INDEX(Maze!$C$5:$C$85,MATCH($A41,Maze!$A$5:$A$85,0)),"") -> Arm 2 | C41: =IFERROR(INDEX(Maze!$D$5:$D$85,MATCH($A41,Maze!$A$5:$A$85,0)),"") -> 13 | D41: =IFERROR(INDEX(Maze!$E$5:$E$85,MATCH($A41,Maze!$A$5:$A$85,0)),"") -> Forced | E41: =IFERROR(INDEX(Maze!$G$5:$G$85,MATCH($A41,Maze!$A$5:$A$85,0)),"") -> No | F41: item_drop | H41: 1 | L41: Zenyte shard | AJ41: {=SUMPRODUCT(($L41:$AI41<>"")*1)} -> 1 | AK41: =IF($F41="","",IF($G41="each",$AJ41*$H41,$H41)) -> 1 | AL41: =IF($F41="","",IFERROR((IF($G41="each",IF($I41="No",SUM(Calc!$BZ41:$CW41),IF($F41="item_drop",SUM(Calc!$DX41:$EU41),IF($I41="Yes",MAX(Calc!$BZ41:$CW41),SUM(Calc!$BZ41:$CW41)))),$H41/MAX(Calc!$BA41:$BX41)))/IF($J41="",cfg_ratemult,$J41),"")) -> 3.75 | AM41: =IF($AL41="","",$AL41/MAX(0.1,IF($K41="",IF($B41="Arm 1",cfg_arm1,IF($B41="Arm 2",cfg_arm2,IF($B41="Arm 3",cfg_arm3,cfg_concurrent))),$K41))+cfg_overhead/60) -> 3.95 | AN41: =IF($AM41="","",INT($AM41/24)&"d "&TEXT(MOD($AM41,24),"0.0")&"h") -> 0d 04h | AO41: =IF($AM41="","",$AL41*IFERROR(GAMMAINV(cfg_pct,MAX(1,IF($F41="item_drop",IF($G41="each",$AJ41*$H41,$H41),1000)),1/MAX(1,IF($F41="item_drop",IF($G41="each",$AJ41*$H41,$H41),1000))),1)/MAX(0.1,IF($K41="",IF($B41="Arm 1",cfg_arm1,IF($B41="Arm 2",cfg_arm2,IF($B41="Arm 3",cfg_arm3,cfg_concurrent))),$K41))+cfg_overhead/60) -> 8.8346941 | AP41: =(cfg_base+cfg_slope*$C41^cfg_exp)*IF($D41="KEY",cfg_mkey,IF($D41="END",cfg_mend,IF($D41="Skippable",cfg_mskip,1))) -> 1.1362092 | AQ41: =IF(OR($AM41="",$AP41=0),"",$AM41/$AP41) -> 3.4764726 | AR41: =IF($F41="","- no task set -",_xlfn.TEXTJOIN(" | ",TRUE,IF(AND($F41<>"gp_value",$AJ41=0),"no items selected",""),IF(AND($F41="gp_value",$AJ41=0),"pick a farming method so the ETC can be estimated",""),IF(AND($F41="gp_value",$AJ41>1),"gp_value takes no item list - one method is enough",""),IF(AND($F41="minigame_completion",$AJ41>1),"only 1 minigame per tile",""),IF(OR($H41="",$H41<=0),"target missing",""),IF(SUMPRODUCT(($L41:$AE41<>"")*(Calc!$C41:$Z41=0))>0,"unknown entry - not in catalogue",""),IF(AND($G41="each",$AJ41=1),"each with 1 entry = same as any",""),IF($AL41="","ETC not computable",""))) -> #N/A | AS41: Reject humanity, return to monkey | AT41: =IF($F41="","","{"&CHAR(34)&"tileId"&CHAR(34)&":"&$A41&","&CHAR(34)&"taskType"&CHAR(34)&":"&CHAR(34)&$F41&CHAR(34)&","&CHAR(34)&"taskConfig"&CHAR(34)&":{"&IF($F41="gp_value","",IF($F41="minigame_completion",CHAR(34)&"minigame"&CHAR(34)&":"&CHAR(34)&$L41&CHAR(34)&","&CHAR(34)&"message"&CHAR(34)&":"&CHAR(34)&IFERROR(INDEX(minigame_completion!$J$5:$J$47,MATCH($L41,minigame_completion!$A$5:$A$47,0)),"")&CHAR(34)&",",IF($AJ41=1,CHAR(34)&INDEX(Settings!$F$6:$F$13,MATCH($F41,Settings!$E$6:$E$13,0))&CHAR(34)&":"&Calc!$EW41&",",CHAR(34)&INDEX(Settings!$G$6:$G$13,MATCH($F41,Settings!$E$6:$E$13,0))&CHAR(34)&":["&_xlfn.TEXTJOIN(",",TRUE,Calc!$EW41:$FT41)&"],")))&CHAR(34)&"target"&CHAR(34)&":"&$H41&IF($G41="each",","&CHAR(34)&"mode"&CHAR(34)&":"&CHAR(34)&"each"&CHAR(34),"")&"}}") -> {"tileId":22,"taskType":"item_drop","taskConfig":{"item":"Zenyte shard","target":1}}
A42: 23 | B42: =IFERROR(INDEX(Maze!$C$5:$C$85,MATCH($A42,Maze!$A$5:$A$85,0)),"") -> Arm 2 | C42: =IFERROR(INDEX(Maze!$D$5:$D$85,MATCH($A42,Maze!$A$5:$A$85,0)),"") -> 14 | D42: =IFERROR(INDEX(Maze!$E$5:$E$85,MATCH($A42,Maze!$A$5:$A$85,0)),"") -> Forced | E42: =IFERROR(INDEX(Maze!$G$5:$G$85,MATCH($A42,Maze!$A$5:$A$85,0)),"") -> No | F42: item_drop | H42: 1000 | L42: Crystal shard | AJ42: {=SUMPRODUCT(($L42:$AI42<>"")*1)} -> 1 | AK42: =IF($F42="","",IF($G42="each",$AJ42*$H42,$H42)) -> 1000 | AL42: =IF($F42="","",IFERROR((IF($G42="each",IF($I42="No",SUM(Calc!$BZ42:$CW42),IF($F42="item_drop",SUM(Calc!$DX42:$EU42),IF($I42="Yes",MAX(Calc!$BZ42:$CW42),SUM(Calc!$BZ42:$CW42)))),$H42/MAX(Calc!$BA42:$BX42)))/IF($J42="",cfg_ratemult,$J42),"")) -> 22.222222 | AM42: =IF($AL42="","",$AL42/MAX(0.1,IF($K42="",IF($B42="Arm 1",cfg_arm1,IF($B42="Arm 2",cfg_arm2,IF($B42="Arm 3",cfg_arm3,cfg_concurrent))),$K42))+cfg_overhead/60) -> 22.422222 | AN42: =IF($AM42="","",INT($AM42/24)&"d "&TEXT(MOD($AM42,24),"0.0")&"h") -> 0d 22h | AO42: =IF($AM42="","",$AL42*IFERROR(GAMMAINV(cfg_pct,MAX(1,IF($F42="item_drop",IF($G42="each",$AJ42*$H42,$H42),1000)),1/MAX(1,IF($F42="item_drop",IF($G42="each",$AJ42*$H42,$H42),1000))),1)/MAX(0.1,IF($K42="",IF($B42="Arm 1",cfg_arm1,IF($B42="Arm 2",cfg_arm2,IF($B42="Arm 3",cfg_arm3,cfg_concurrent))),$K42))+cfg_overhead/60) -> 23.327429 | AP42: =(cfg_base+cfg_slope*$C42^cfg_exp)*IF($D42="KEY",cfg_mkey,IF($D42="END",cfg_mend,IF($D42="Skippable",cfg_mskip,1))) -> 1.2293653 | AQ42: =IF(OR($AM42="",$AP42=0),"",$AM42/$AP42) -> 18.23886 | AR42: =IF($F42="","- no task set -",_xlfn.TEXTJOIN(" | ",TRUE,IF(AND($F42<>"gp_value",$AJ42=0),"no items selected",""),IF(AND($F42="gp_value",$AJ42=0),"pick a farming method so the ETC can be estimated",""),IF(AND($F42="gp_value",$AJ42>1),"gp_value takes no item list - one method is enough",""),IF(AND($F42="minigame_completion",$AJ42>1),"only 1 minigame per tile",""),IF(OR($H42="",$H42<=0),"target missing",""),IF(SUMPRODUCT(($L42:$AE42<>"")*(Calc!$C42:$Z42=0))>0,"unknown entry - not in catalogue",""),IF(AND($G42="each",$AJ42=1),"each with 1 entry = same as any",""),IF($AL42="","ETC not computable",""))) -> #N/A | AS42: Plenty of options | AT42: =IF($F42="","","{"&CHAR(34)&"tileId"&CHAR(34)&":"&$A42&","&CHAR(34)&"taskType"&CHAR(34)&":"&CHAR(34)&$F42&CHAR(34)&","&CHAR(34)&"taskConfig"&CHAR(34)&":{"&IF($F42="gp_value","",IF($F42="minigame_completion",CHAR(34)&"minigame"&CHAR(34)&":"&CHAR(34)&$L42&CHAR(34)&","&CHAR(34)&"message"&CHAR(34)&":"&CHAR(34)&IFERROR(INDEX(minigame_completion!$J$5:$J$47,MATCH($L42,minigame_completion!$A$5:$A$47,0)),"")&CHAR(34)&",",IF($AJ42=1,CHAR(34)&INDEX(Settings!$F$6:$F$13,MATCH($F42,Settings!$E$6:$E$13,0))&CHAR(34)&":"&Calc!$EW42&",",CHAR(34)&INDEX(Settings!$G$6:$G$13,MATCH($F42,Settings!$E$6:$E$13,0))&CHAR(34)&":["&_xlfn.TEXTJOIN(",",TRUE,Calc!$EW42:$FT42)&"],")))&CHAR(34)&"target"&CHAR(34)&":"&$H42&IF($G42="each",","&CHAR(34)&"mode"&CHAR(34)&":"&CHAR(34)&"each"&CHAR(34),"")&"}}") -> {"tileId":23,"taskType":"item_drop","taskConfig":{"item":"Crystal shard","target":1000}}
A43: 24 | B43: =IFERROR(INDEX(Maze!$C$5:$C$85,MATCH($A43,Maze!$A$5:$A$85,0)),"") -> Arm 2 | C43: =IFERROR(INDEX(Maze!$D$5:$D$85,MATCH($A43,Maze!$A$5:$A$85,0)),"") -> 15 | D43: =IFERROR(INDEX(Maze!$E$5:$E$85,MATCH($A43,Maze!$A$5:$A$85,0)),"") -> Forced | E43: =IFERROR(INDEX(Maze!$G$5:$G$85,MATCH($A43,Maze!$A$5:$A$85,0)),"") -> No | F43: item_drop | H43: 1 | L43: Chromium ingot | AJ43: {=SUMPRODUCT(($L43:$AI43<>"")*1)} -> 1 | AK43: =IF($F43="","",IF($G43="each",$AJ43*$H43,$H43)) -> 1 | AL43: =IF($F43="","",IFERROR((IF($G43="each",IF($I43="No",SUM(Calc!$BZ43:$CW43),IF($F43="item_drop",SUM(Calc!$DX43:$EU43),IF($I43="Yes",MAX(Calc!$BZ43:$CW43),SUM(Calc!$BZ43:$CW43)))),$H43/MAX(Calc!$BA43:$BX43)))/IF($J43="",cfg_ratemult,$J43),"")) -> 7.0588235 | AM43: =IF($AL43="","",$AL43/MAX(0.1,IF($K43="",IF($B43="Arm 1",cfg_arm1,IF($B43="Arm 2",cfg_arm2,IF($B43="Arm 3",cfg_arm3,cfg_concurrent))),$K43))+cfg_overhead/60) -> 7.2588235 | AN43: =IF($AM43="","",INT($AM43/24)&"d "&TEXT(MOD($AM43,24),"0.0")&"h") -> 0d 07h | AO43: =IF($AM43="","",$AL43*IFERROR(GAMMAINV(cfg_pct,MAX(1,IF($F43="item_drop",IF($G43="each",$AJ43*$H43,$H43),1000)),1/MAX(1,IF($F43="item_drop",IF($G43="each",$AJ43*$H43,$H43),1000))),1)/MAX(0.1,IF($K43="",IF($B43="Arm 1",cfg_arm1,IF($B43="Arm 2",cfg_arm2,IF($B43="Arm 3",cfg_arm3,cfg_concurrent))),$K43))+cfg_overhead/60) -> 16.453542 | AP43: =(cfg_base+cfg_slope*$C43^cfg_exp)*IF($D43="KEY",cfg_mkey,IF($D43="END",cfg_mend,IF($D43="Skippable",cfg_mskip,1))) -> 1.3269512 | AQ43: =IF(OR($AM43="",$AP43=0),"",$AM43/$AP43) -> 5.4703018 | AR43: =IF($F43="","- no task set -",_xlfn.TEXTJOIN(" | ",TRUE,IF(AND($F43<>"gp_value",$AJ43=0),"no items selected",""),IF(AND($F43="gp_value",$AJ43=0),"pick a farming method so the ETC can be estimated",""),IF(AND($F43="gp_value",$AJ43>1),"gp_value takes no item list - one method is enough",""),IF(AND($F43="minigame_completion",$AJ43>1),"only 1 minigame per tile",""),IF(OR($H43="",$H43<=0),"target missing",""),IF(SUMPRODUCT(($L43:$AE43<>"")*(Calc!$C43:$Z43=0))>0,"unknown entry - not in catalogue",""),IF(AND($G43="each",$AJ43=1),"each with 1 entry = same as any",""),IF($AL43="","ETC not computable",""))) -> #N/A | AS43: You could fish for it | AT43: =IF($F43="","","{"&CHAR(34)&"tileId"&CHAR(34)&":"&$A43&","&CHAR(34)&"taskType"&CHAR(34)&":"&CHAR(34)&$F43&CHAR(34)&","&CHAR(34)&"taskConfig"&CHAR(34)&":{"&IF($F43="gp_value","",IF($F43="minigame_completion",CHAR(34)&"minigame"&CHAR(34)&":"&CHAR(34)&$L43&CHAR(34)&","&CHAR(34)&"message"&CHAR(34)&":"&CHAR(34)&IFERROR(INDEX(minigame_completion!$J$5:$J$47,MATCH($L43,minigame_completion!$A$5:$A$47,0)),"")&CHAR(34)&",",IF($AJ43=1,CHAR(34)&INDEX(Settings!$F$6:$F$13,MATCH($F43,Settings!$E$6:$E$13,0))&CHAR(34)&":"&Calc!$EW43&",",CHAR(34)&INDEX(Settings!$G$6:$G$13,MATCH($F43,Settings!$E$6:$E$13,0))&CHAR(34)&":["&_xlfn.TEXTJOIN(",",TRUE,Calc!$EW43:$FT43)&"],")))&CHAR(34)&"target"&CHAR(34)&":"&$H43&IF($G43="each",","&CHAR(34)&"mode"&CHAR(34)&":"&CHAR(34)&"each"&CHAR(34),"")&"}}") -> {"tileId":24,"taskType":"item_drop","taskConfig":{"item":"Chromium ingot","target":1}}
A44: 25 | B44: =IFERROR(INDEX(Maze!$C$5:$C$85,MATCH($A44,Maze!$A$5:$A$85,0)),"") -> Arm 2 | C44: =IFERROR(INDEX(Maze!$D$5:$D$85,MATCH($A44,Maze!$A$5:$A$85,0)),"") -> 16 | D44: =IFERROR(INDEX(Maze!$E$5:$E$85,MATCH($A44,Maze!$A$5:$A$85,0)),"") -> Forced | E44: =IFERROR(INDEX(Maze!$G$5:$G$85,MATCH($A44,Maze!$A$5:$A$85,0)),"") -> No | F44: minigame_completion | H44: 20 | L44: Hallowed Sepulchre (Floor 5) | AJ44: {=SUMPRODUCT(($L44:$AI44<>"")*1)} -> 1 | AK44: =IF($F44="","",IF($G44="each",$AJ44*$H44,$H44)) -> 20 | AL44: =IF($F44="","",IFERROR((IF($G44="each",IF($I44="No",SUM(Calc!$BZ44:$CW44),IF($F44="item_drop",SUM(Calc!$DX44:$EU44),IF($I44="Yes",MAX(Calc!$BZ44:$CW44),SUM(Calc!$BZ44:$CW44)))),$H44/MAX(Calc!$BA44:$BX44)))/IF($J44="",cfg_ratemult,$J44),"")) -> 4 | AM44: =IF($AL44="","",$AL44/MAX(0.1,IF($K44="",IF($B44="Arm 1",cfg_arm1,IF($B44="Arm 2",cfg_arm2,IF($B44="Arm 3",cfg_arm3,cfg_concurrent))),$K44))+cfg_overhead/60) -> 4.2 | AN44: =IF($AM44="","",INT($AM44/24)&"d "&TEXT(MOD($AM44,24),"0.0")&"h") -> 0d 04h | AO44: =IF($AM44="","",$AL44*IFERROR(GAMMAINV(cfg_pct,MAX(1,IF($F44="item_drop",IF($G44="each",$AJ44*$H44,$H44),1000)),1/MAX(1,IF($F44="item_drop",IF($G44="each",$AJ44*$H44,$H44),1000))),1)/MAX(0.1,IF($K44="",IF($B44="Arm 1",cfg_arm1,IF($B44="Arm 2",cfg_arm2,IF($B44="Arm 3",cfg_arm3,cfg_concurrent))),$K44))+cfg_overhead/60) -> 4.3629372 | AP44: =(cfg_base+cfg_slope*$C44^cfg_exp)*IF($D44="KEY",cfg_mkey,IF($D44="END",cfg_mend,IF($D44="Skippable",cfg_mskip,1))) -> 1.4288609 | AQ44: =IF(OR($AM44="",$AP44=0),"",$AM44/$AP44) -> 2.9394043 | AR44: =IF($F44="","- no task set -",_xlfn.TEXTJOIN(" | ",TRUE,IF(AND($F44<>"gp_value",$AJ44=0),"no items selected",""),IF(AND($F44="gp_value",$AJ44=0),"pick a farming method so the ETC can be estimated",""),IF(AND($F44="gp_value",$AJ44>1),"gp_value takes no item list - one method is enough",""),IF(AND($F44="minigame_completion",$AJ44>1),"only 1 minigame per tile",""),IF(OR($H44="",$H44<=0),"target missing",""),IF(SUMPRODUCT(($L44:$AE44<>"")*(Calc!$C44:$Z44=0))>0,"unknown entry - not in catalogue",""),IF(AND($G44="each",$AJ44=1),"each with 1 entry = same as any",""),IF($AL44="","ETC not computable",""))) -> #N/A | AS44: Are we there yet? | AT44: =IF($F44="","","{"&CHAR(34)&"tileId"&CHAR(34)&":"&$A44&","&CHAR(34)&"taskType"&CHAR(34)&":"&CHAR(34)&$F44&CHAR(34)&","&CHAR(34)&"taskConfig"&CHAR(34)&":{"&IF($F44="gp_value","",IF($F44="minigame_completion",CHAR(34)&"minigame"&CHAR(34)&":"&CHAR(34)&$L44&CHAR(34)&","&CHAR(34)&"message"&CHAR(34)&":"&CHAR(34)&IFERROR(INDEX(minigame_completion!$J$5:$J$47,MATCH($L44,minigame_completion!$A$5:$A$47,0)),"")&CHAR(34)&",",IF($AJ44=1,CHAR(34)&INDEX(Settings!$F$6:$F$13,MATCH($F44,Settings!$E$6:$E$13,0))&CHAR(34)&":"&Calc!$EW44&",",CHAR(34)&INDEX(Settings!$G$6:$G$13,MATCH($F44,Settings!$E$6:$E$13,0))&CHAR(34)&":["&_xlfn.TEXTJOIN(",",TRUE,Calc!$EW44:$FT44)&"],")))&CHAR(34)&"target"&CHAR(34)&":"&$H44&IF($G44="each",","&CHAR(34)&"mode"&CHAR(34)&":"&CHAR(34)&"each"&CHAR(34),"")&"}}") -> {"tileId":25,"taskType":"minigame_completion","taskConfig":{"minigame":"Hallowed Sepulchre (Floor 5)","message":"completed Floor 5 of the Hallowed Sepulchre","target":20}}
A45: 26 | B45: =IFERROR(INDEX(Maze!$C$5:$C$85,MATCH($A45,Maze!$A$5:$A$85,0)),"") -> Arm 2 | C45: =IFERROR(INDEX(Maze!$D$5:$D$85,MATCH($A45,Maze!$A$5:$A$85,0)),"") -> 17 | D45: =IFERROR(INDEX(Maze!$E$5:$E$85,MATCH($A45,Maze!$A$5:$A$85,0)),"") -> Forced | E45: =IFERROR(INDEX(Maze!$G$5:$G$85,MATCH($A45,Maze!$A$5:$A$85,0)),"") -> No | F45: npc_kill | G45: each | H45: 50 | L45: Venenatis | M45: Vet'ion | N45: Callisto | AJ45: {=SUMPRODUCT(($L45:$AI45<>"")*1)} -> 3 | AK45: =IF($F45="","",IF($G45="each",$AJ45*$H45,$H45)) -> 150 | AL45: =IF($F45="","",IFERROR((IF($G45="each",IF($I45="No",SUM(Calc!$BZ45:$CW45),IF($F45="item_drop",SUM(Calc!$DX45:$EU45),IF($I45="Yes",MAX(Calc!$BZ45:$CW45),SUM(Calc!$BZ45:$CW45)))),$H45/MAX(Calc!$BA45:$BX45)))/IF($J45="",cfg_ratemult,$J45),"")) -> 5.3936652 | AM45: =IF($AL45="","",$AL45/MAX(0.1,IF($K45="",IF($B45="Arm 1",cfg_arm1,IF($B45="Arm 2",cfg_arm2,IF($B45="Arm 3",cfg_arm3,cfg_concurrent))),$K45))+cfg_overhead/60) -> 5.5936652 | AN45: =IF($AM45="","",INT($AM45/24)&"d "&TEXT(MOD($AM45,24),"0.0")&"h") -> 0d 06h | AO45: =IF($AM45="","",$AL45*IFERROR(GAMMAINV(cfg_pct,MAX(1,IF($F45="item_drop",IF($G45="each",$AJ45*$H45,$H45),1000)),1/MAX(1,IF($F45="item_drop",IF($G45="each",$AJ45*$H45,$H45),1000))),1)/MAX(0.1,IF($K45="",IF($B45="Arm 1",cfg_arm1,IF($B45="Arm 2",cfg_arm2,IF($B45="Arm 3",cfg_arm3,cfg_concurrent))),$K45))+cfg_overhead/60) -> 5.8133724 | AP45: =(cfg_base+cfg_slope*$C45^cfg_exp)*IF($D45="KEY",cfg_mkey,IF($D45="END",cfg_mend,IF($D45="Skippable",cfg_mskip,1))) -> 1.5349979 | AQ45: =IF(OR($AM45="",$AP45=0),"",$AM45/$AP45) -> 3.6440865 | AR45: =IF($F45="","- no task set -",_xlfn.TEXTJOIN(" | ",TRUE,IF(AND($F45<>"gp_value",$AJ45=0),"no items selected",""),IF(AND($F45="gp_value",$AJ45=0),"pick a farming method so the ETC can be estimated",""),IF(AND($F45="gp_value",$AJ45>1),"gp_value takes no item list - one method is enough",""),IF(AND($F45="minigame_completion",$AJ45>1),"only 1 minigame per tile",""),IF(OR($H45="",$H45<=0),"target missing",""),IF(SUMPRODUCT(($L45:$AE45<>"")*(Calc!$C45:$Z45=0))>0,"unknown entry - not in catalogue",""),IF(AND($G45="each",$AJ45=1),"each with 1 entry = same as any",""),IF($AL45="","ETC not computable",""))) -> #N/A | AS45: Dangerous tourism | AT45: =IF($F45="","","{"&CHAR(34)&"tileId"&CHAR(34)&":"&$A45&","&CHAR(34)&"taskType"&CHAR(34)&":"&CHAR(34)&$F45&CHAR(34)&","&CHAR(34)&"taskConfig"&CHAR(34)&":{"&IF($F45="gp_value","",IF($F45="minigame_completion",CHAR(34)&"minigame"&CHAR(34)&":"&CHAR(34)&$L45&CHAR(34)&","&CHAR(34)&"message"&CHAR(34)&":"&CHAR(34)&IFERROR(INDEX(minigame_completion!$J$5:$J$47,MATCH($L45,minigame_completion!$A$5:$A$47,0)),"")&CHAR(34)&",",IF($AJ45=1,CHAR(34)&INDEX(Settings!$F$6:$F$13,MATCH($F45,Settings!$E$6:$E$13,0))&CHAR(34)&":"&Calc!$EW45&",",CHAR(34)&INDEX(Settings!$G$6:$G$13,MATCH($F45,Settings!$E$6:$E$13,0))&CHAR(34)&":["&_xlfn.TEXTJOIN(",",TRUE,Calc!$EW45:$FT45)&"],")))&CHAR(34)&"target"&CHAR(34)&":"&$H45&IF($G45="each",","&CHAR(34)&"mode"&CHAR(34)&":"&CHAR(34)&"each"&CHAR(34),"")&"}}") -> {"tileId":26,"taskType":"npc_kill","taskConfig":{"npcs":["Venenatis","Vet'ion","Callisto"],"target":50,"mode":"each"}}
A46: 17 | B46: =IFERROR(INDEX(Maze!$C$5:$C$85,MATCH($A46,Maze!$A$5:$A$85,0)),"") -> Arm 2 | C46: =IFERROR(INDEX(Maze!$D$5:$D$85,MATCH($A46,Maze!$A$5:$A$85,0)),"") -> 18 | D46: =IFERROR(INDEX(Maze!$E$5:$E$85,MATCH($A46,Maze!$A$5:$A$85,0)),"") -> Skippable | E46: =IFERROR(INDEX(Maze!$G$5:$G$85,MATCH($A46,Maze!$A$5:$A$85,0)),"") -> Yes | F46: item_drop | H46: 1 | L46: Gull | AJ46: {=SUMPRODUCT(($L46:$AI46<>"")*1)} -> 1 | AK46: =IF($F46="","",IF($G46="each",$AJ46*$H46,$H46)) -> 1 | AL46: =IF($F46="","",IFERROR((IF($G46="each",IF($I46="No",SUM(Calc!$BZ46:$CW46),IF($F46="item_drop",SUM(Calc!$DX46:$EU46),IF($I46="Yes",MAX(Calc!$BZ46:$CW46),SUM(Calc!$BZ46:$CW46)))),$H46/MAX(Calc!$BA46:$BX46)))/IF($J46="",cfg_ratemult,$J46),"")) -> 100 | AM46: =IF($AL46="","",$AL46/MAX(0.1,IF($K46="",IF($B46="Arm 1",cfg_arm1,IF($B46="Arm 2",cfg_arm2,IF($B46="Arm 3",cfg_arm3,cfg_concurrent))),$K46))+cfg_overhead/60) -> 100.2 | AN46: =IF($AM46="","",INT($AM46/24)&"d "&TEXT(MOD($AM46,24),"0.0")&"h") -> 4d 04h | AO46: =IF($AM46="","",$AL46*IFERROR(GAMMAINV(cfg_pct,MAX(1,IF($F46="item_drop",IF($G46="each",$AJ46*$H46,$H46),1000)),1/MAX(1,IF($F46="item_drop",IF($G46="each",$AJ46*$H46,$H46),1000))),1)/MAX(0.1,IF($K46="",IF($B46="Arm 1",cfg_arm1,IF($B46="Arm 2",cfg_arm2,IF($B46="Arm 3",cfg_arm3,cfg_concurrent))),$K46))+cfg_overhead/60) -> 230.45851 | AP46: =(cfg_base+cfg_slope*$C46^cfg_exp)*IF($D46="KEY",cfg_mkey,IF($D46="END",cfg_mend,IF($D46="Skippable",cfg_mskip,1))) -> 0.90490032 | AQ46: =IF(OR($AM46="",$AP46=0),"",$AM46/$AP46) -> 110.73043 | AR46: =IF($F46="","- no task set -",_xlfn.TEXTJOIN(" | ",TRUE,IF(AND($F46<>"gp_value",$AJ46=0),"no items selected",""),IF(AND($F46="gp_value",$AJ46=0),"pick a farming method so the ETC can be estimated",""),IF(AND($F46="gp_value",$AJ46>1),"gp_value takes no item list - one method is enough",""),IF(AND($F46="minigame_completion",$AJ46>1),"only 1 minigame per tile",""),IF(OR($H46="",$H46<=0),"target missing",""),IF(SUMPRODUCT(($L46:$AE46<>"")*(Calc!$C46:$Z46=0))>0,"unknown entry - not in catalogue",""),IF(AND($G46="each",$AJ46=1),"each with 1 entry = same as any",""),IF($AL46="","ETC not computable",""))) -> #N/A | AS46: Kolan asked for this | AT46: =IF($F46="","","{"&CHAR(34)&"tileId"&CHAR(34)&":"&$A46&","&CHAR(34)&"taskType"&CHAR(34)&":"&CHAR(34)&$F46&CHAR(34)&","&CHAR(34)&"taskConfig"&CHAR(34)&":{"&IF($F46="gp_value","",IF($F46="minigame_completion",CHAR(34)&"minigame"&CHAR(34)&":"&CHAR(34)&$L46&CHAR(34)&","&CHAR(34)&"message"&CHAR(34)&":"&CHAR(34)&IFERROR(INDEX(minigame_completion!$J$5:$J$47,MATCH($L46,minigame_completion!$A$5:$A$47,0)),"")&CHAR(34)&",",IF($AJ46=1,CHAR(34)&INDEX(Settings!$F$6:$F$13,MATCH($F46,Settings!$E$6:$E$13,0))&CHAR(34)&":"&Calc!$EW46&",",CHAR(34)&INDEX(Settings!$G$6:$G$13,MATCH($F46,Settings!$E$6:$E$13,0))&CHAR(34)&":["&_xlfn.TEXTJOIN(",",TRUE,Calc!$EW46:$FT46)&"],")))&CHAR(34)&"target"&CHAR(34)&":"&$H46&IF($G46="each",","&CHAR(34)&"mode"&CHAR(34)&":"&CHAR(34)&"each"&CHAR(34),"")&"}}") -> {"tileId":17,"taskType":"item_drop","taskConfig":{"item":"Gull","target":1}}
A47: 35 | B47: =IFERROR(INDEX(Maze!$C$5:$C$85,MATCH($A47,Maze!$A$5:$A$85,0)),"") -> Arm 2 | C47: =IFERROR(INDEX(Maze!$D$5:$D$85,MATCH($A47,Maze!$A$5:$A$85,0)),"") -> 18 | D47: =IFERROR(INDEX(Maze!$E$5:$E$85,MATCH($A47,Maze!$A$5:$A$85,0)),"") -> Forced | E47: =IFERROR(INDEX(Maze!$G$5:$G$85,MATCH($A47,Maze!$A$5:$A$85,0)),"") -> No | F47: npc_kill | H47: 150 | L47: Thermonuclear smoke devil | AJ47: {=SUMPRODUCT(($L47:$AI47<>"")*1)} -> 1 | AK47: =IF($F47="","",IF($G47="each",$AJ47*$H47,$H47)) -> 150 | AL47: =IF($F47="","",IFERROR((IF($G47="each",IF($I47="No",SUM(Calc!$BZ47:$CW47),IF($F47="item_drop",SUM(Calc!$DX47:$EU47),IF($I47="Yes",MAX(Calc!$BZ47:$CW47),SUM(Calc!$BZ47:$CW47)))),$H47/MAX(Calc!$BA47:$BX47)))/IF($J47="",cfg_ratemult,$J47),"")) -> 3.3333333 | AM47: =IF($AL47="","",$AL47/MAX(0.1,IF($K47="",IF($B47="Arm 1",cfg_arm1,IF($B47="Arm 2",cfg_arm2,IF($B47="Arm 3",cfg_arm3,cfg_concurrent))),$K47))+cfg_overhead/60) -> 3.5333333 | AN47: =IF($AM47="","",INT($AM47/24)&"d "&TEXT(MOD($AM47,24),"0.0")&"h") -> 0d 04h | AO47: =IF($AM47="","",$AL47*IFERROR(GAMMAINV(cfg_pct,MAX(1,IF($F47="item_drop",IF($G47="each",$AJ47*$H47,$H47),1000)),1/MAX(1,IF($F47="item_drop",IF($G47="each",$AJ47*$H47,$H47),1000))),1)/MAX(0.1,IF($K47="",IF($B47="Arm 1",cfg_arm1,IF($B47="Arm 2",cfg_arm2,IF($B47="Arm 3",cfg_arm3,cfg_concurrent))),$K47))+cfg_overhead/60) -> 3.6691144 | AP47: =(cfg_base+cfg_slope*$C47^cfg_exp)*IF($D47="KEY",cfg_mkey,IF($D47="END",cfg_mend,IF($D47="Skippable",cfg_mskip,1))) -> 1.6452733 | AQ47: =IF(OR($AM47="",$AP47=0),"",$AM47/$AP47) -> 2.1475662 | AR47: =IF($F47="","- no task set -",_xlfn.TEXTJOIN(" | ",TRUE,IF(AND($F47<>"gp_value",$AJ47=0),"no items selected",""),IF(AND($F47="gp_value",$AJ47=0),"pick a farming method so the ETC can be estimated",""),IF(AND($F47="gp_value",$AJ47>1),"gp_value takes no item list - one method is enough",""),IF(AND($F47="minigame_completion",$AJ47>1),"only 1 minigame per tile",""),IF(OR($H47="",$H47<=0),"target missing",""),IF(SUMPRODUCT(($L47:$AE47<>"")*(Calc!$C47:$Z47=0))>0,"unknown entry - not in catalogue",""),IF(AND($G47="each",$AJ47=1),"each with 1 entry = same as any",""),IF($AL47="","ETC not computable",""))) -> #N/A | AS47: Smoking kills | AT47: =IF($F47="","","{"&CHAR(34)&"tileId"&CHAR(34)&":"&$A47&","&CHAR(34)&"taskType"&CHAR(34)&":"&CHAR(34)&$F47&CHAR(34)&","&CHAR(34)&"taskConfig"&CHAR(34)&":{"&IF($F47="gp_value","",IF($F47="minigame_completion",CHAR(34)&"minigame"&CHAR(34)&":"&CHAR(34)&$L47&CHAR(34)&","&CHAR(34)&"message"&CHAR(34)&":"&CHAR(34)&IFERROR(INDEX(minigame_completion!$J$5:$J$47,MATCH($L47,minigame_completion!$A$5:$A$47,0)),"")&CHAR(34)&",",IF($AJ47=1,CHAR(34)&INDEX(Settings!$F$6:$F$13,MATCH($F47,Settings!$E$6:$E$13,0))&CHAR(34)&":"&Calc!$EW47&",",CHAR(34)&INDEX(Settings!$G$6:$G$13,MATCH($F47,Settings!$E$6:$E$13,0))&CHAR(34)&":["&_xlfn.TEXTJOIN(",",TRUE,Calc!$EW47:$FT47)&"],")))&CHAR(34)&"target"&CHAR(34)&":"&$H47&IF($G47="each",","&CHAR(34)&"mode"&CHAR(34)&":"&CHAR(34)&"each"&CHAR(34),"")&"}}") -> {"tileId":35,"taskType":"npc_kill","taskConfig":{"npc":"Thermonuclear smoke devil","target":150}}
A48: 36 | B48: =IFERROR(INDEX(Maze!$C$5:$C$85,MATCH($A48,Maze!$A$5:$A$85,0)),"") -> Arm 2 | C48: =IFERROR(INDEX(Maze!$D$5:$D$85,MATCH($A48,Maze!$A$5:$A$85,0)),"") -> 19 | D48: =IFERROR(INDEX(Maze!$E$5:$E$85,MATCH($A48,Maze!$A$5:$A$85,0)),"") -> Forced | E48: =IFERROR(INDEX(Maze!$G$5:$G$85,MATCH($A48,Maze!$A$5:$A$85,0)),"") -> No | F48: item_drop | H48: 1 | L48: Saradomin sword | M48: Saradomin's light | N48: Saradomin hilt | O48: Armadyl crossbow | AJ48: {=SUMPRODUCT(($L48:$AI48<>"")*1)} -> 4 | AK48: =IF($F48="","",IF($G48="each",$AJ48*$H48,$H48)) -> 1 | AL48: =IF($F48="","",IFERROR((IF($G48="each",IF($I48="No",SUM(Calc!$BZ48:$CW48),IF($F48="item_drop",SUM(Calc!$DX48:$EU48),IF($I48="Yes",MAX(Calc!$BZ48:$CW48),SUM(Calc!$BZ48:$CW48)))),$H48/MAX(Calc!$BA48:$BX48)))/IF($J48="",cfg_ratemult,$J48),"")) -> 2.3518519 | AM48: =IF($AL48="","",$AL48/MAX(0.1,IF($K48="",IF($B48="Arm 1",cfg_arm1,IF($B48="Arm 2",cfg_arm2,IF($B48="Arm 3",cfg_arm3,cfg_concurrent))),$K48))+cfg_overhead/60) -> 2.5518519 | AN48: =IF($AM48="","",INT($AM48/24)&"d "&TEXT(MOD($AM48,24),"0.0")&"h") -> 0d 03h | AO48: =IF($AM48="","",$AL48*IFERROR(GAMMAINV(cfg_pct,MAX(1,IF($F48="item_drop",IF($G48="each",$AJ48*$H48,$H48),1000)),1/MAX(1,IF($F48="item_drop",IF($G48="each",$AJ48*$H48,$H48),1000))),1)/MAX(0.1,IF($K48="",IF($B48="Arm 1",cfg_arm1,IF($B48="Arm 2",cfg_arm2,IF($B48="Arm 3",cfg_arm3,cfg_concurrent))),$K48))+cfg_overhead/60) -> 5.615339 | AP48: =(cfg_base+cfg_slope*$C48^cfg_exp)*IF($D48="KEY",cfg_mkey,IF($D48="END",cfg_mend,IF($D48="Skippable",cfg_mskip,1))) -> 1.7596051 | AQ48: =IF(OR($AM48="",$AP48=0),"",$AM48/$AP48) -> 1.4502413 | AR48: =IF($F48="","- no task set -",_xlfn.TEXTJOIN(" | ",TRUE,IF(AND($F48<>"gp_value",$AJ48=0),"no items selected",""),IF(AND($F48="gp_value",$AJ48=0),"pick a farming method so the ETC can be estimated",""),IF(AND($F48="gp_value",$AJ48>1),"gp_value takes no item list - one method is enough",""),IF(AND($F48="minigame_completion",$AJ48>1),"only 1 minigame per tile",""),IF(OR($H48="",$H48<=0),"target missing",""),IF(SUMPRODUCT(($L48:$AE48<>"")*(Calc!$C48:$Z48=0))>0,"unknown entry - not in catalogue",""),IF(AND($G48="each",$AJ48=1),"each with 1 entry = same as any",""),IF($AL48="","ETC not computable",""))) -> #N/A | AS48: Smash or pass | AT48: =IF($F48="","","{"&CHAR(34)&"tileId"&CHAR(34)&":"&$A48&","&CHAR(34)&"taskType"&CHAR(34)&":"&CHAR(34)&$F48&CHAR(34)&","&CHAR(34)&"taskConfig"&CHAR(34)&":{"&IF($F48="gp_value","",IF($F48="minigame_completion",CHAR(34)&"minigame"&CHAR(34)&":"&CHAR(34)&$L48&CHAR(34)&","&CHAR(34)&"message"&CHAR(34)&":"&CHAR(34)&IFERROR(INDEX(minigame_completion!$J$5:$J$47,MATCH($L48,minigame_completion!$A$5:$A$47,0)),"")&CHAR(34)&",",IF($AJ48=1,CHAR(34)&INDEX(Settings!$F$6:$F$13,MATCH($F48,Settings!$E$6:$E$13,0))&CHAR(34)&":"&Calc!$EW48&",",CHAR(34)&INDEX(Settings!$G$6:$G$13,MATCH($F48,Settings!$E$6:$E$13,0))&CHAR(34)&":["&_xlfn.TEXTJOIN(",",TRUE,Calc!$EW48:$FT48)&"],")))&CHAR(34)&"target"&CHAR(34)&":"&$H48&IF($G48="each",","&CHAR(34)&"mode"&CHAR(34)&":"&CHAR(34)&"each"&CHAR(34),"")&"}}") -> {"tileId":36,"taskType":"item_drop","taskConfig":{"items":["Saradomin sword","Saradomin's light","Saradomin hilt","Armadyl crossbow"],"target":1}}
A49: 27 | B49: =IFERROR(INDEX(Maze!$C$5:$C$85,MATCH($A49,Maze!$A$5:$A$85,0)),"") -> Arm 2 | C49: =IFERROR(INDEX(Maze!$D$5:$D$85,MATCH($A49,Maze!$A$5:$A$85,0)),"") -> 20 | D49: =IFERROR(INDEX(Maze!$E$5:$E$85,MATCH($A49,Maze!$A$5:$A$85,0)),"") -> Forced | E49: =IFERROR(INDEX(Maze!$G$5:$G$85,MATCH($A49,Maze!$A$5:$A$85,0)),"") -> No | F49: clue_completion | H49: 5 | L49: master | AJ49: {=SUMPRODUCT(($L49:$AI49<>"")*1)} -> 1 | AK49: =IF($F49="","",IF($G49="each",$AJ49*$H49,$H49)) -> 5 | AL49: =IF($F49="","",IFERROR((IF($G49="each",IF($I49="No",SUM(Calc!$BZ49:$CW49),IF($F49="item_drop",SUM(Calc!$DX49:$EU49),IF($I49="Yes",MAX(Calc!$BZ49:$CW49),SUM(Calc!$BZ49:$CW49)))),$H49/MAX(Calc!$BA49:$BX49)))/IF($J49="",cfg_ratemult,$J49),"")) -> 2 | AM49: =IF($AL49="","",$AL49/MAX(0.1,IF($K49="",IF($B49="Arm 1",cfg_arm1,IF($B49="Arm 2",cfg_arm2,IF($B49="Arm 3",cfg_arm3,cfg_concurrent))),$K49))+cfg_overhead/60) -> 2.2 | AN49: =IF($AM49="","",INT($AM49/24)&"d "&TEXT(MOD($AM49,24),"0.0")&"h") -> 0d 02h | AO49: =IF($AM49="","",$AL49*IFERROR(GAMMAINV(cfg_pct,MAX(1,IF($F49="item_drop",IF($G49="each",$AJ49*$H49,$H49),1000)),1/MAX(1,IF($F49="item_drop",IF($G49="each",$AJ49*$H49,$H49),1000))),1)/MAX(0.1,IF($K49="",IF($B49="Arm 1",cfg_arm1,IF($B49="Arm 2",cfg_arm2,IF($B49="Arm 3",cfg_arm3,cfg_concurrent))),$K49))+cfg_overhead/60) -> 2.2814686 | AP49: =(cfg_base+cfg_slope*$C49^cfg_exp)*IF($D49="KEY",cfg_mkey,IF($D49="END",cfg_mend,IF($D49="Skippable",cfg_mskip,1))) -> 1.8779171 | AQ49: =IF(OR($AM49="",$AP49=0),"",$AM49/$AP49) -> 1.1715107 | AR49: =IF($F49="","- no task set -",_xlfn.TEXTJOIN(" | ",TRUE,IF(AND($F49<>"gp_value",$AJ49=0),"no items selected",""),IF(AND($F49="gp_value",$AJ49=0),"pick a farming method so the ETC can be estimated",""),IF(AND($F49="gp_value",$AJ49>1),"gp_value takes no item list - one method is enough",""),IF(AND($F49="minigame_completion",$AJ49>1),"only 1 minigame per tile",""),IF(OR($H49="",$H49<=0),"target missing",""),IF(SUMPRODUCT(($L49:$AE49<>"")*(Calc!$C49:$Z49=0))>0,"unknown entry - not in catalogue",""),IF(AND($G49="each",$AJ49=1),"each with 1 entry = same as any",""),IF($AL49="","ETC not computable",""))) -> #N/A | AS49: The student becomes the master | AT49: =IF($F49="","","{"&CHAR(34)&"tileId"&CHAR(34)&":"&$A49&","&CHAR(34)&"taskType"&CHAR(34)&":"&CHAR(34)&$F49&CHAR(34)&","&CHAR(34)&"taskConfig"&CHAR(34)&":{"&IF($F49="gp_value","",IF($F49="minigame_completion",CHAR(34)&"minigame"&CHAR(34)&":"&CHAR(34)&$L49&CHAR(34)&","&CHAR(34)&"message"&CHAR(34)&":"&CHAR(34)&IFERROR(INDEX(minigame_completion!$J$5:$J$47,MATCH($L49,minigame_completion!$A$5:$A$47,0)),"")&CHAR(34)&",",IF($AJ49=1,CHAR(34)&INDEX(Settings!$F$6:$F$13,MATCH($F49,Settings!$E$6:$E$13,0))&CHAR(34)&":"&Calc!$EW49&",",CHAR(34)&INDEX(Settings!$G$6:$G$13,MATCH($F49,Settings!$E$6:$E$13,0))&CHAR(34)&":["&_xlfn.TEXTJOIN(",",TRUE,Calc!$EW49:$FT49)&"],")))&CHAR(34)&"target"&CHAR(34)&":"&$H49&IF($G49="each",","&CHAR(34)&"mode"&CHAR(34)&":"&CHAR(34)&"each"&CHAR(34),"")&"}}") -> {"tileId":27,"taskType":"clue_completion","taskConfig":{"tier":"master","target":5}}
A50: 18 | B50: =IFERROR(INDEX(Maze!$C$5:$C$85,MATCH($A50,Maze!$A$5:$A$85,0)),"") -> Arm 2 | C50: =IFERROR(INDEX(Maze!$D$5:$D$85,MATCH($A50,Maze!$A$5:$A$85,0)),"") -> 21 | D50: =IFERROR(INDEX(Maze!$E$5:$E$85,MATCH($A50,Maze!$A$5:$A$85,0)),"") -> Forced | E50: =IFERROR(INDEX(Maze!$G$5:$G$85,MATCH($A50,Maze!$A$5:$A$85,0)),"") -> No | F50: item_drop | H50: 1 | L50: Bandos chestplate | M50: Bandos tassets | N50: Bandos boots | O50: Bandos hilt | AJ50: {=SUMPRODUCT(($L50:$AI50<>"")*1)} -> 4 | AK50: =IF($F50="","",IF($G50="each",$AJ50*$H50,$H50)) -> 1 | AL50: =IF($F50="","",IFERROR((IF($G50="each",IF($I50="No",SUM(Calc!$BZ50:$CW50),IF($F50="item_drop",SUM(Calc!$DX50:$EU50),IF($I50="Yes",MAX(Calc!$BZ50:$CW50),SUM(Calc!$BZ50:$CW50)))),$H50/MAX(Calc!$BA50:$BX50)))/IF($J50="",cfg_ratemult,$J50),"")) -> 3.762963 | AM50: =IF($AL50="","",$AL50/MAX(0.1,IF($K50="",IF($B50="Arm 1",cfg_arm1,IF($B50="Arm 2",cfg_arm2,IF($B50="Arm 3",cfg_arm3,cfg_concurrent))),$K50))+cfg_overhead/60) -> 3.962963 | AN50: =IF($AM50="","",INT($AM50/24)&"d "&TEXT(MOD($AM50,24),"0.0")&"h") -> 0d 04h | AO50: =IF($AM50="","",$AL50*IFERROR(GAMMAINV(cfg_pct,MAX(1,IF($F50="item_drop",IF($G50="each",$AJ50*$H50,$H50),1000)),1/MAX(1,IF($F50="item_drop",IF($G50="each",$AJ50*$H50,$H50),1000))),1)/MAX(0.1,IF($K50="",IF($B50="Arm 1",cfg_arm1,IF($B50="Arm 2",cfg_arm2,IF($B50="Arm 3",cfg_arm3,cfg_concurrent))),$K50))+cfg_overhead/60) -> 8.8645424 | AP50: =(cfg_base+cfg_slope*$C50^cfg_exp)*IF($D50="KEY",cfg_mkey,IF($D50="END",cfg_mend,IF($D50="Skippable",cfg_mskip,1))) -> 2.0001386 | AQ50: =IF(OR($AM50="",$AP50=0),"",$AM50/$AP50) -> 1.9813442 | AR50: =IF($F50="","- no task set -",_xlfn.TEXTJOIN(" | ",TRUE,IF(AND($F50<>"gp_value",$AJ50=0),"no items selected",""),IF(AND($F50="gp_value",$AJ50=0),"pick a farming method so the ETC can be estimated",""),IF(AND($F50="gp_value",$AJ50>1),"gp_value takes no item list - one method is enough",""),IF(AND($F50="minigame_completion",$AJ50>1),"only 1 minigame per tile",""),IF(OR($H50="",$H50<=0),"target missing",""),IF(SUMPRODUCT(($L50:$AE50<>"")*(Calc!$C50:$Z50=0))>0,"unknown entry - not in catalogue",""),IF(AND($G50="each",$AJ50=1),"each with 1 entry = same as any",""),IF($AL50="","ETC not computable",""))) -> #N/A | AS50: General Garagedoor | AT50: =IF($F50="","","{"&CHAR(34)&"tileId"&CHAR(34)&":"&$A50&","&CHAR(34)&"taskType"&CHAR(34)&":"&CHAR(34)&$F50&CHAR(34)&","&CHAR(34)&"taskConfig"&CHAR(34)&":{"&IF($F50="gp_value","",IF($F50="minigame_completion",CHAR(34)&"minigame"&CHAR(34)&":"&CHAR(34)&$L50&CHAR(34)&","&CHAR(34)&"message"&CHAR(34)&":"&CHAR(34)&IFERROR(INDEX(minigame_completion!$J$5:$J$47,MATCH($L50,minigame_completion!$A$5:$A$47,0)),"")&CHAR(34)&",",IF($AJ50=1,CHAR(34)&INDEX(Settings!$F$6:$F$13,MATCH($F50,Settings!$E$6:$E$13,0))&CHAR(34)&":"&Calc!$EW50&",",CHAR(34)&INDEX(Settings!$G$6:$G$13,MATCH($F50,Settings!$E$6:$E$13,0))&CHAR(34)&":["&_xlfn.TEXTJOIN(",",TRUE,Calc!$EW50:$FT50)&"],")))&CHAR(34)&"target"&CHAR(34)&":"&$H50&IF($G50="each",","&CHAR(34)&"mode"&CHAR(34)&":"&CHAR(34)&"each"&CHAR(34),"")&"}}") -> {"tileId":18,"taskType":"item_drop","taskConfig":{"items":["Bandos chestplate","Bandos tassets","Bandos boots","Bandos hilt"],"target":1}}
A51: 9 | B51: =IFERROR(INDEX(Maze!$C$5:$C$85,MATCH($A51,Maze!$A$5:$A$85,0)),"") -> Arm 2 | C51: =IFERROR(INDEX(Maze!$D$5:$D$85,MATCH($A51,Maze!$A$5:$A$85,0)),"") -> 22 | D51: =IFERROR(INDEX(Maze!$E$5:$E$85,MATCH($A51,Maze!$A$5:$A$85,0)),"") -> Forced | E51: =IFERROR(INDEX(Maze!$G$5:$G$85,MATCH($A51,Maze!$A$5:$A$85,0)),"") -> No | F51: item_drop | H51: 1 | L51: Crystal weapon seed | AJ51: {=SUMPRODUCT(($L51:$AI51<>"")*1)} -> 1 | AK51: =IF($F51="","",IF($G51="each",$AJ51*$H51,$H51)) -> 1 | AL51: =IF($F51="","",IFERROR((IF($G51="each",IF($I51="No",SUM(Calc!$BZ51:$CW51),IF($F51="item_drop",SUM(Calc!$DX51:$EU51),IF($I51="Yes",MAX(Calc!$BZ51:$CW51),SUM(Calc!$BZ51:$CW51)))),$H51/MAX(Calc!$BA51:$BX51)))/IF($J51="",cfg_ratemult,$J51),"")) -> 24 | AM51: =IF($AL51="","",$AL51/MAX(0.1,IF($K51="",IF($B51="Arm 1",cfg_arm1,IF($B51="Arm 2",cfg_arm2,IF($B51="Arm 3",cfg_arm3,cfg_concurrent))),$K51))+cfg_overhead/60) -> 24.2 | AN51: =IF($AM51="","",INT($AM51/24)&"d "&TEXT(MOD($AM51,24),"0.0")&"h") -> 1d 00h | AO51: =IF($AM51="","",$AL51*IFERROR(GAMMAINV(cfg_pct,MAX(1,IF($F51="item_drop",IF($G51="each",$AJ51*$H51,$H51),1000)),1/MAX(1,IF($F51="item_drop",IF($G51="each",$AJ51*$H51,$H51),1000))),1)/MAX(0.1,IF($K51="",IF($B51="Arm 1",cfg_arm1,IF($B51="Arm 2",cfg_arm2,IF($B51="Arm 3",cfg_arm3,cfg_concurrent))),$K51))+cfg_overhead/60) -> 55.462042 | AP51: =(cfg_base+cfg_slope*$C51^cfg_exp)*IF($D51="KEY",cfg_mkey,IF($D51="END",cfg_mend,IF($D51="Skippable",cfg_mskip,1))) -> 2.1262032 | AQ51: =IF(OR($AM51="",$AP51=0),"",$AM51/$AP51) -> 11.381791 | AR51: =IF($F51="","- no task set -",_xlfn.TEXTJOIN(" | ",TRUE,IF(AND($F51<>"gp_value",$AJ51=0),"no items selected",""),IF(AND($F51="gp_value",$AJ51=0),"pick a farming method so the ETC can be estimated",""),IF(AND($F51="gp_value",$AJ51>1),"gp_value takes no item list - one method is enough",""),IF(AND($F51="minigame_completion",$AJ51>1),"only 1 minigame per tile",""),IF(OR($H51="",$H51<=0),"target missing",""),IF(SUMPRODUCT(($L51:$AE51<>"")*(Calc!$C51:$Z51=0))>0,"unknown entry - not in catalogue",""),IF(AND($G51="each",$AJ51=1),"each with 1 entry = same as any",""),IF($AL51="","ETC not computable",""))) -> #N/A | AS51: It finally has a use | AT51: =IF($F51="","","{"&CHAR(34)&"tileId"&CHAR(34)&":"&$A51&","&CHAR(34)&"taskType"&CHAR(34)&":"&CHAR(34)&$F51&CHAR(34)&","&CHAR(34)&"taskConfig"&CHAR(34)&":{"&IF($F51="gp_value","",IF($F51="minigame_completion",CHAR(34)&"minigame"&CHAR(34)&":"&CHAR(34)&$L51&CHAR(34)&","&CHAR(34)&"message"&CHAR(34)&":"&CHAR(34)&IFERROR(INDEX(minigame_completion!$J$5:$J$47,MATCH($L51,minigame_completion!$A$5:$A$47,0)),"")&CHAR(34)&",",IF($AJ51=1,CHAR(34)&INDEX(Settings!$F$6:$F$13,MATCH($F51,Settings!$E$6:$E$13,0))&CHAR(34)&":"&Calc!$EW51&",",CHAR(34)&INDEX(Settings!$G$6:$G$13,MATCH($F51,Settings!$E$6:$E$13,0))&CHAR(34)&":["&_xlfn.TEXTJOIN(",",TRUE,Calc!$EW51:$FT51)&"],")))&CHAR(34)&"target"&CHAR(34)&":"&$H51&IF($G51="each",","&CHAR(34)&"mode"&CHAR(34)&":"&CHAR(34)&"each"&CHAR(34),"")&"}}") -> {"tileId":9,"taskType":"item_drop","taskConfig":{"item":"Crystal weapon seed","target":1}}
A52: 8 | B52: =IFERROR(INDEX(Maze!$C$5:$C$85,MATCH($A52,Maze!$A$5:$A$85,0)),"") -> Arm 2 | C52: =IFERROR(INDEX(Maze!$D$5:$D$85,MATCH($A52,Maze!$A$5:$A$85,0)),"") -> 23 | D52: =IFERROR(INDEX(Maze!$E$5:$E$85,MATCH($A52,Maze!$A$5:$A$85,0)),"") -> Forced | E52: =IFERROR(INDEX(Maze!$G$5:$G$85,MATCH($A52,Maze!$A$5:$A$85,0)),"") -> No | F52: item_drop | H52: 1 | L52: Blood quartz | M52: Ice quartz | N52: Shadow quartz | O52: Smoke quartz | AJ52: {=SUMPRODUCT(($L52:$AI52<>"")*1)} -> 4 | AK52: =IF($F52="","",IF($G52="each",$AJ52*$H52,$H52)) -> 1 | AL52: =IF($F52="","",IFERROR((IF($G52="each",IF($I52="No",SUM(Calc!$BZ52:$CW52),IF($F52="item_drop",SUM(Calc!$DX52:$EU52),IF($I52="Yes",MAX(Calc!$BZ52:$CW52),SUM(Calc!$BZ52:$CW52)))),$H52/MAX(Calc!$BA52:$BX52)))/IF($J52="",cfg_ratemult,$J52),"")) -> 6 | AM52: =IF($AL52="","",$AL52/MAX(0.1,IF($K52="",IF($B52="Arm 1",cfg_arm1,IF($B52="Arm 2",cfg_arm2,IF($B52="Arm 3",cfg_arm3,cfg_concurrent))),$K52))+cfg_overhead/60) -> 6.2 | AN52: =IF($AM52="","",INT($AM52/24)&"d "&TEXT(MOD($AM52,24),"0.0")&"h") -> 0d 06h | AO52: =IF($AM52="","",$AL52*IFERROR(GAMMAINV(cfg_pct,MAX(1,IF($F52="item_drop",IF($G52="each",$AJ52*$H52,$H52),1000)),1/MAX(1,IF($F52="item_drop",IF($G52="each",$AJ52*$H52,$H52),1000))),1)/MAX(0.1,IF($K52="",IF($B52="Arm 1",cfg_arm1,IF($B52="Arm 2",cfg_arm2,IF($B52="Arm 3",cfg_arm3,cfg_concurrent))),$K52))+cfg_overhead/60) -> 14.015511 | AP52: =(cfg_base+cfg_slope*$C52^cfg_exp)*IF($D52="KEY",cfg_mkey,IF($D52="END",cfg_mend,IF($D52="Skippable",cfg_mskip,1))) -> 2.256049 | AQ52: =IF(OR($AM52="",$AP52=0),"",$AM52/$AP52) -> 2.7481673 | AR52: =IF($F52="","- no task set -",_xlfn.TEXTJOIN(" | ",TRUE,IF(AND($F52<>"gp_value",$AJ52=0),"no items selected",""),IF(AND($F52="gp_value",$AJ52=0),"pick a farming method so the ETC can be estimated",""),IF(AND($F52="gp_value",$AJ52>1),"gp_value takes no item list - one method is enough",""),IF(AND($F52="minigame_completion",$AJ52>1),"only 1 minigame per tile",""),IF(OR($H52="",$H52<=0),"target missing",""),IF(SUMPRODUCT(($L52:$AE52<>"")*(Calc!$C52:$Z52=0))>0,"unknown entry - not in catalogue",""),IF(AND($G52="each",$AJ52=1),"each with 1 entry = same as any",""),IF($AL52="","ETC not computable",""))) -> #N/A | AS52: Budget infinity stones | AT52: =IF($F52="","","{"&CHAR(34)&"tileId"&CHAR(34)&":"&$A52&","&CHAR(34)&"taskType"&CHAR(34)&":"&CHAR(34)&$F52&CHAR(34)&","&CHAR(34)&"taskConfig"&CHAR(34)&":{"&IF($F52="gp_value","",IF($F52="minigame_completion",CHAR(34)&"minigame"&CHAR(34)&":"&CHAR(34)&$L52&CHAR(34)&","&CHAR(34)&"message"&CHAR(34)&":"&CHAR(34)&IFERROR(INDEX(minigame_completion!$J$5:$J$47,MATCH($L52,minigame_completion!$A$5:$A$47,0)),"")&CHAR(34)&",",IF($AJ52=1,CHAR(34)&INDEX(Settings!$F$6:$F$13,MATCH($F52,Settings!$E$6:$E$13,0))&CHAR(34)&":"&Calc!$EW52&",",CHAR(34)&INDEX(Settings!$G$6:$G$13,MATCH($F52,Settings!$E$6:$E$13,0))&CHAR(34)&":["&_xlfn.TEXTJOIN(",",TRUE,Calc!$EW52:$FT52)&"],")))&CHAR(34)&"target"&CHAR(34)&":"&$H52&IF($G52="each",","&CHAR(34)&"mode"&CHAR(34)&":"&CHAR(34)&"each"&CHAR(34),"")&"}}") -> {"tileId":8,"taskType":"item_drop","taskConfig":{"items":["Blood quartz","Ice quartz","Shadow quartz","Smoke quartz"],"target":1}}
A53: 7 | B53: =IFERROR(INDEX(Maze!$C$5:$C$85,MATCH($A53,Maze!$A$5:$A$85,0)),"") -> Arm 2 | C53: =IFERROR(INDEX(Maze!$D$5:$D$85,MATCH($A53,Maze!$A$5:$A$85,0)),"") -> 24 | D53: =IFERROR(INDEX(Maze!$E$5:$E$85,MATCH($A53,Maze!$A$5:$A$85,0)),"") -> Forced | E53: =IFERROR(INDEX(Maze!$G$5:$G$85,MATCH($A53,Maze!$A$5:$A$85,0)),"") -> No | F53: item_drop | H53: 10 | L53: Dizana's quiver | AJ53: {=SUMPRODUCT(($L53:$AI53<>"")*1)} -> 1 | AK53: =IF($F53="","",IF($G53="each",$AJ53*$H53,$H53)) -> 10 | AL53: =IF($F53="","",IFERROR((IF($G53="each",IF($I53="No",SUM(Calc!$BZ53:$CW53),IF($F53="item_drop",SUM(Calc!$DX53:$EU53),IF($I53="Yes",MAX(Calc!$BZ53:$CW53),SUM(Calc!$BZ53:$CW53)))),$H53/MAX(Calc!$BA53:$BX53)))/IF($J53="",cfg_ratemult,$J53),"")) -> 6.6666667 | AM53: =IF($AL53="","",$AL53/MAX(0.1,IF($K53="",IF($B53="Arm 1",cfg_arm1,IF($B53="Arm 2",cfg_arm2,IF($B53="Arm 3",cfg_arm3,cfg_concurrent))),$K53))+cfg_overhead/60) -> 6.8666667 | AN53: =IF($AM53="","",INT($AM53/24)&"d "&TEXT(MOD($AM53,24),"0.0")&"h") -> 0d 07h | AO53: =IF($AM53="","",$AL53*IFERROR(GAMMAINV(cfg_pct,MAX(1,IF($F53="item_drop",IF($G53="each",$AJ53*$H53,$H53),1000)),1/MAX(1,IF($F53="item_drop",IF($G53="each",$AJ53*$H53,$H53),1000))),1)/MAX(0.1,IF($K53="",IF($B53="Arm 1",cfg_arm1,IF($B53="Arm 2",cfg_arm2,IF($B53="Arm 3",cfg_arm3,cfg_concurrent))),$K53))+cfg_overhead/60) -> 9.6706602 | AP53: =(cfg_base+cfg_slope*$C53^cfg_exp)*IF($D53="KEY",cfg_mkey,IF($D53="END",cfg_mend,IF($D53="Skippable",cfg_mskip,1))) -> 2.3896175 | AQ53: =IF(OR($AM53="",$AP53=0),"",$AM53/$AP53) -> 2.8735422 | AR53: =IF($F53="","- no task set -",_xlfn.TEXTJOIN(" | ",TRUE,IF(AND($F53<>"gp_value",$AJ53=0),"no items selected",""),IF(AND($F53="gp_value",$AJ53=0),"pick a farming method so the ETC can be estimated",""),IF(AND($F53="gp_value",$AJ53>1),"gp_value takes no item list - one method is enough",""),IF(AND($F53="minigame_completion",$AJ53>1),"only 1 minigame per tile",""),IF(OR($H53="",$H53<=0),"target missing",""),IF(SUMPRODUCT(($L53:$AE53<>"")*(Calc!$C53:$Z53=0))>0,"unknown entry - not in catalogue",""),IF(AND($G53="each",$AJ53=1),"each with 1 entry = same as any",""),IF($AL53="","ETC not computable",""))) -> #N/A | AS53: Quiver me timbers | AT53: =IF($F53="","","{"&CHAR(34)&"tileId"&CHAR(34)&":"&$A53&","&CHAR(34)&"taskType"&CHAR(34)&":"&CHAR(34)&$F53&CHAR(34)&","&CHAR(34)&"taskConfig"&CHAR(34)&":{"&IF($F53="gp_value","",IF($F53="minigame_completion",CHAR(34)&"minigame"&CHAR(34)&":"&CHAR(34)&$L53&CHAR(34)&","&CHAR(34)&"message"&CHAR(34)&":"&CHAR(34)&IFERROR(INDEX(minigame_completion!$J$5:$J$47,MATCH($L53,minigame_completion!$A$5:$A$47,0)),"")&CHAR(34)&",",IF($AJ53=1,CHAR(34)&INDEX(Settings!$F$6:$F$13,MATCH($F53,Settings!$E$6:$E$13,0))&CHAR(34)&":"&Calc!$EW53&",",CHAR(34)&INDEX(Settings!$G$6:$G$13,MATCH($F53,Settings!$E$6:$E$13,0))&CHAR(34)&":["&_xlfn.TEXTJOIN(",",TRUE,Calc!$EW53:$FT53)&"],")))&CHAR(34)&"target"&CHAR(34)&":"&$H53&IF($G53="each",","&CHAR(34)&"mode"&CHAR(34)&":"&CHAR(34)&"each"&CHAR(34),"")&"}}") -> {"tileId":7,"taskType":"item_drop","taskConfig":{"item":"Dizana's quiver","target":10}}
A54: 16 | B54: =IFERROR(INDEX(Maze!$C$5:$C$85,MATCH($A54,Maze!$A$5:$A$85,0)),"") -> Arm 2 | C54: =IFERROR(INDEX(Maze!$D$5:$D$85,MATCH($A54,Maze!$A$5:$A$85,0)),"") -> 25 | D54: =IFERROR(INDEX(Maze!$E$5:$E$85,MATCH($A54,Maze!$A$5:$A$85,0)),"") -> KEY | E54: =IFERROR(INDEX(Maze!$G$5:$G$85,MATCH($A54,Maze!$A$5:$A$85,0)),"") -> Yes | F54: item_drop | H54: 1 | L54: Scythe of vitur | M54: Sanguinesti staff | N54: Ghrazi rapier | O54: Justiciar faceguard | P54: Justiciar chestguard | Q54: Justiciar legguards | AJ54: {=SUMPRODUCT(($L54:$AI54<>"")*1)} -> 6 | AK54: =IF($F54="","",IF($G54="each",$AJ54*$H54,$H54)) -> 1 | AL54: =IF($F54="","",IFERROR((IF($G54="each",IF($I54="No",SUM(Calc!$BZ54:$CW54),IF($F54="item_drop",SUM(Calc!$DX54:$EU54),IF($I54="Yes",MAX(Calc!$BZ54:$CW54),SUM(Calc!$BZ54:$CW54)))),$H54/MAX(Calc!$BA54:$BX54)))/IF($J54="",cfg_ratemult,$J54),"")) -> 55.873517 | AM54: =IF($AL54="","",$AL54/MAX(0.1,IF($K54="",IF($B54="Arm 1",cfg_arm1,IF($B54="Arm 2",cfg_arm2,IF($B54="Arm 3",cfg_arm3,cfg_concurrent))),$K54))+cfg_overhead/60) -> 56.073517 | AN54: =IF($AM54="","",INT($AM54/24)&"d "&TEXT(MOD($AM54,24),"0.0")&"h") -> 2d 08h | AO54: =IF($AM54="","",$AL54*IFERROR(GAMMAINV(cfg_pct,MAX(1,IF($F54="item_drop",IF($G54="each",$AJ54*$H54,$H54),1000)),1/MAX(1,IF($F54="item_drop",IF($G54="each",$AJ54*$H54,$H54),1000))),1)/MAX(0.1,IF($K54="",IF($B54="Arm 1",cfg_arm1,IF($B54="Arm 2",cfg_arm2,IF($B54="Arm 3",cfg_arm3,cfg_concurrent))),$K54))+cfg_overhead/60) -> 128.85353 | AP54: =(cfg_base+cfg_slope*$C54^cfg_exp)*IF($D54="KEY",cfg_mkey,IF($D54="END",cfg_mend,IF($D54="Skippable",cfg_mskip,1))) -> 4.2956511 | AQ54: =IF(OR($AM54="",$AP54=0),"",$AM54/$AP54) -> 13.053555 | AR54: =IF($F54="","- no task set -",_xlfn.TEXTJOIN(" | ",TRUE,IF(AND($F54<>"gp_value",$AJ54=0),"no items selected",""),IF(AND($F54="gp_value",$AJ54=0),"pick a farming method so the ETC can be estimated",""),IF(AND($F54="gp_value",$AJ54>1),"gp_value takes no item list - one method is enough",""),IF(AND($F54="minigame_completion",$AJ54>1),"only 1 minigame per tile",""),IF(OR($H54="",$H54<=0),"target missing",""),IF(SUMPRODUCT(($L54:$AE54<>"")*(Calc!$C54:$Z54=0))>0,"unknown entry - not in catalogue",""),IF(AND($G54="each",$AJ54=1),"each with 1 entry = same as any",""),IF($AL54="","ETC not computable",""))) -> #N/A | AS54: 10/10, would die again | AT54: =IF($F54="","","{"&CHAR(34)&"tileId"&CHAR(34)&":"&$A54&","&CHAR(34)&"taskType"&CHAR(34)&":"&CHAR(34)&$F54&CHAR(34)&","&CHAR(34)&"taskConfig"&CHAR(34)&":{"&IF($F54="gp_value","",IF($F54="minigame_completion",CHAR(34)&"minigame"&CHAR(34)&":"&CHAR(34)&$L54&CHAR(34)&","&CHAR(34)&"message"&CHAR(34)&":"&CHAR(34)&IFERROR(INDEX(minigame_completion!$J$5:$J$47,MATCH($L54,minigame_completion!$A$5:$A$47,0)),"")&CHAR(34)&",",IF($AJ54=1,CHAR(34)&INDEX(Settings!$F$6:$F$13,MATCH($F54,Settings!$E$6:$E$13,0))&CHAR(34)&":"&Calc!$EW54&",",CHAR(34)&INDEX(Settings!$G$6:$G$13,MATCH($F54,Settings!$E$6:$E$13,0))&CHAR(34)&":["&_xlfn.TEXTJOIN(",",TRUE,Calc!$EW54:$FT54)&"],")))&CHAR(34)&"target"&CHAR(34)&":"&$H54&IF($G54="each",","&CHAR(34)&"mode"&CHAR(34)&":"&CHAR(34)&"each"&CHAR(34),"")&"}}") -> {"tileId":16,"taskType":"item_drop","taskConfig":{"items":["Scythe of vitur","Sanguinesti staff","Ghrazi rapier","Justiciar faceguard","Justiciar chestguard","Justiciar legguards"],"target":1}}
A55: 76 | B55: =IFERROR(INDEX(Maze!$C$5:$C$85,MATCH($A55,Maze!$A$5:$A$85,0)),"") -> Arm 3 | C55: =IFERROR(INDEX(Maze!$D$5:$D$85,MATCH($A55,Maze!$A$5:$A$85,0)),"") -> 1 | D55: =IFERROR(INDEX(Maze!$E$5:$E$85,MATCH($A55,Maze!$A$5:$A$85,0)),"") -> Forced | E55: =IFERROR(INDEX(Maze!$G$5:$G$85,MATCH($A55,Maze!$A$5:$A$85,0)),"") -> No | F55: minigame_completion | H55: 100 | L55: Wintertodt | AJ55: {=SUMPRODUCT(($L55:$AI55<>"")*1)} -> 1 | AK55: =IF($F55="","",IF($G55="each",$AJ55*$H55,$H55)) -> 100 | AL55: =IF($F55="","",IFERROR((IF($G55="each",IF($I55="No",SUM(Calc!$BZ55:$CW55),IF($F55="item_drop",SUM(Calc!$DX55:$EU55),IF($I55="Yes",MAX(Calc!$BZ55:$CW55),SUM(Calc!$BZ55:$CW55)))),$H55/MAX(Calc!$BA55:$BX55)))/IF($J55="",cfg_ratemult,$J55),"")) -> 8.3333333 | AM55: =IF($AL55="","",$AL55/MAX(0.1,IF($K55="",IF($B55="Arm 1",cfg_arm1,IF($B55="Arm 2",cfg_arm2,IF($B55="Arm 3",cfg_arm3,cfg_concurrent))),$K55))+cfg_overhead/60) -> 8.5333333 | AN55: =IF($AM55="","",INT($AM55/24)&"d "&TEXT(MOD($AM55,24),"0.0")&"h") -> 0d 09h | AO55: =IF($AM55="","",$AL55*IFERROR(GAMMAINV(cfg_pct,MAX(1,IF($F55="item_drop",IF($G55="each",$AJ55*$H55,$H55),1000)),1/MAX(1,IF($F55="item_drop",IF($G55="each",$AJ55*$H55,$H55),1000))),1)/MAX(0.1,IF($K55="",IF($B55="Arm 1",cfg_arm1,IF($B55="Arm 2",cfg_arm2,IF($B55="Arm 3",cfg_arm3,cfg_concurrent))),$K55))+cfg_overhead/60) -> 8.8727859 | AP55: =(cfg_base+cfg_slope*$C55^cfg_exp)*IF($D55="KEY",cfg_mkey,IF($D55="END",cfg_mend,IF($D55="Skippable",cfg_mskip,1))) -> 0.4304 | AQ55: =IF(OR($AM55="",$AP55=0),"",$AM55/$AP55) -> 19.826518 | AR55: =IF($F55="","- no task set -",_xlfn.TEXTJOIN(" | ",TRUE,IF(AND($F55<>"gp_value",$AJ55=0),"no items selected",""),IF(AND($F55="gp_value",$AJ55=0),"pick a farming method so the ETC can be estimated",""),IF(AND($F55="gp_value",$AJ55>1),"gp_value takes no item list - one method is enough",""),IF(AND($F55="minigame_completion",$AJ55>1),"only 1 minigame per tile",""),IF(OR($H55="",$H55<=0),"target missing",""),IF(SUMPRODUCT(($L55:$AE55<>"")*(Calc!$C55:$Z55=0))>0,"unknown entry - not in catalogue",""),IF(AND($G55="each",$AJ55=1),"each with 1 entry = same as any",""),IF($AL55="","ETC not computable",""))) -> #N/A | AS55: Chop chop! | AT55: =IF($F55="","","{"&CHAR(34)&"tileId"&CHAR(34)&":"&$A55&","&CHAR(34)&"taskType"&CHAR(34)&":"&CHAR(34)&$F55&CHAR(34)&","&CHAR(34)&"taskConfig"&CHAR(34)&":{"&IF($F55="gp_value","",IF($F55="minigame_completion",CHAR(34)&"minigame"&CHAR(34)&":"&CHAR(34)&$L55&CHAR(34)&","&CHAR(34)&"message"&CHAR(34)&":"&CHAR(34)&IFERROR(INDEX(minigame_completion!$J$5:$J$47,MATCH($L55,minigame_completion!$A$5:$A$47,0)),"")&CHAR(34)&",",IF($AJ55=1,CHAR(34)&INDEX(Settings!$F$6:$F$13,MATCH($F55,Settings!$E$6:$E$13,0))&CHAR(34)&":"&Calc!$EW55&",",CHAR(34)&INDEX(Settings!$G$6:$G$13,MATCH($F55,Settings!$E$6:$E$13,0))&CHAR(34)&":["&_xlfn.TEXTJOIN(",",TRUE,Calc!$EW55:$FT55)&"],")))&CHAR(34)&"target"&CHAR(34)&":"&$H55&IF($G55="each",","&CHAR(34)&"mode"&CHAR(34)&":"&CHAR(34)&"each"&CHAR(34),"")&"}}") -> {"tileId":76,"taskType":"minigame_completion","taskConfig":{"minigame":"Wintertodt","message":"subdued Wintertodt count is","target":100}}
A56: 67 | B56: =IFERROR(INDEX(Maze!$C$5:$C$85,MATCH($A56,Maze!$A$5:$A$85,0)),"") -> Arm 3 | C56: =IFERROR(INDEX(Maze!$D$5:$D$85,MATCH($A56,Maze!$A$5:$A$85,0)),"") -> 2 | D56: =IFERROR(INDEX(Maze!$E$5:$E$85,MATCH($A56,Maze!$A$5:$A$85,0)),"") -> Forced | E56: =IFERROR(INDEX(Maze!$G$5:$G$85,MATCH($A56,Maze!$A$5:$A$85,0)),"") -> No | F56: item_drop | H56: 1 | L56: Fedora | AJ56: {=SUMPRODUCT(($L56:$AI56<>"")*1)} -> 1 | AK56: =IF($F56="","",IF($G56="each",$AJ56*$H56,$H56)) -> 1 | AL56: =IF($F56="","",IFERROR((IF($G56="each",IF($I56="No",SUM(Calc!$BZ56:$CW56),IF($F56="item_drop",SUM(Calc!$DX56:$EU56),IF($I56="Yes",MAX(Calc!$BZ56:$CW56),SUM(Calc!$BZ56:$CW56)))),$H56/MAX(Calc!$BA56:$BX56)))/IF($J56="",cfg_ratemult,$J56),"")) -> 2.8444444 | AM56: =IF($AL56="","",$AL56/MAX(0.1,IF($K56="",IF($B56="Arm 1",cfg_arm1,IF($B56="Arm 2",cfg_arm2,IF($B56="Arm 3",cfg_arm3,cfg_concurrent))),$K56))+cfg_overhead/60) -> 3.0444444 | AN56: =IF($AM56="","",INT($AM56/24)&"d "&TEXT(MOD($AM56,24),"0.0")&"h") -> 0d 03h | AO56: =IF($AM56="","",$AL56*IFERROR(GAMMAINV(cfg_pct,MAX(1,IF($F56="item_drop",IF($G56="each",$AJ56*$H56,$H56),1000)),1/MAX(1,IF($F56="item_drop",IF($G56="each",$AJ56*$H56,$H56),1000))),1)/MAX(0.1,IF($K56="",IF($B56="Arm 1",cfg_arm1,IF($B56="Arm 2",cfg_arm2,IF($B56="Arm 3",cfg_arm3,cfg_concurrent))),$K56))+cfg_overhead/60) -> 6.7495754 | AP56: =(cfg_base+cfg_slope*$C56^cfg_exp)*IF($D56="KEY",cfg_mkey,IF($D56="END",cfg_mend,IF($D56="Skippable",cfg_mskip,1))) -> 0.4526387 | AQ56: =IF(OR($AM56="",$AP56=0),"",$AM56/$AP56) -> 6.7259924 | AR56: =IF($F56="","- no task set -",_xlfn.TEXTJOIN(" | ",TRUE,IF(AND($F56<>"gp_value",$AJ56=0),"no items selected",""),IF(AND($F56="gp_value",$AJ56=0),"pick a farming method so the ETC can be estimated",""),IF(AND($F56="gp_value",$AJ56>1),"gp_value takes no item list - one method is enough",""),IF(AND($F56="minigame_completion",$AJ56>1),"only 1 minigame per tile",""),IF(OR($H56="",$H56<=0),"target missing",""),IF(SUMPRODUCT(($L56:$AE56<>"")*(Calc!$C56:$Z56=0))>0,"unknown entry - not in catalogue",""),IF(AND($G56="each",$AJ56=1),"each with 1 entry = same as any",""),IF($AL56="","ETC not computable",""))) -> #N/A | AS56: Fedorable | AT56: =IF($F56="","","{"&CHAR(34)&"tileId"&CHAR(34)&":"&$A56&","&CHAR(34)&"taskType"&CHAR(34)&":"&CHAR(34)&$F56&CHAR(34)&","&CHAR(34)&"taskConfig"&CHAR(34)&":{"&IF($F56="gp_value","",IF($F56="minigame_completion",CHAR(34)&"minigame"&CHAR(34)&":"&CHAR(34)&$L56&CHAR(34)&","&CHAR(34)&"message"&CHAR(34)&":"&CHAR(34)&IFERROR(INDEX(minigame_completion!$J$5:$J$47,MATCH($L56,minigame_completion!$A$5:$A$47,0)),"")&CHAR(34)&",",IF($AJ56=1,CHAR(34)&INDEX(Settings!$F$6:$F$13,MATCH($F56,Settings!$E$6:$E$13,0))&CHAR(34)&":"&Calc!$EW56&",",CHAR(34)&INDEX(Settings!$G$6:$G$13,MATCH($F56,Settings!$E$6:$E$13,0))&CHAR(34)&":["&_xlfn.TEXTJOIN(",",TRUE,Calc!$EW56:$FT56)&"],")))&CHAR(34)&"target"&CHAR(34)&":"&$H56&IF($G56="each",","&CHAR(34)&"mode"&CHAR(34)&":"&CHAR(34)&"each"&CHAR(34),"")&"}}") -> {"tileId":67,"taskType":"item_drop","taskConfig":{"item":"Fedora","target":1}}
A57: 66 | B57: =IFERROR(INDEX(Maze!$C$5:$C$85,MATCH($A57,Maze!$A$5:$A$85,0)),"") -> Arm 3 | C57: =IFERROR(INDEX(Maze!$D$5:$D$85,MATCH($A57,Maze!$A$5:$A$85,0)),"") -> 3 | D57: =IFERROR(INDEX(Maze!$E$5:$E$85,MATCH($A57,Maze!$A$5:$A$85,0)),"") -> Forced | E57: =IFERROR(INDEX(Maze!$G$5:$G$85,MATCH($A57,Maze!$A$5:$A$85,0)),"") -> No | F57: npc_kill | H57: 50 | L57: Bryophyta | AJ57: {=SUMPRODUCT(($L57:$AI57<>"")*1)} -> 1 | AK57: =IF($F57="","",IF($G57="each",$AJ57*$H57,$H57)) -> 50 | AL57: =IF($F57="","",IFERROR((IF($G57="each",IF($I57="No",SUM(Calc!$BZ57:$CW57),IF($F57="item_drop",SUM(Calc!$DX57:$EU57),IF($I57="Yes",MAX(Calc!$BZ57:$CW57),SUM(Calc!$BZ57:$CW57)))),$H57/MAX(Calc!$BA57:$BX57)))/IF($J57="",cfg_ratemult,$J57),"")) -> 1.6666667 | AM57: =IF($AL57="","",$AL57/MAX(0.1,IF($K57="",IF($B57="Arm 1",cfg_arm1,IF($B57="Arm 2",cfg_arm2,IF($B57="Arm 3",cfg_arm3,cfg_concurrent))),$K57))+cfg_overhead/60) -> 1.8666667 | AN57: =IF($AM57="","",INT($AM57/24)&"d "&TEXT(MOD($AM57,24),"0.0")&"h") -> 0d 02h | AO57: =IF($AM57="","",$AL57*IFERROR(GAMMAINV(cfg_pct,MAX(1,IF($F57="item_drop",IF($G57="each",$AJ57*$H57,$H57),1000)),1/MAX(1,IF($F57="item_drop",IF($G57="each",$AJ57*$H57,$H57),1000))),1)/MAX(0.1,IF($K57="",IF($B57="Arm 1",cfg_arm1,IF($B57="Arm 2",cfg_arm2,IF($B57="Arm 3",cfg_arm3,cfg_concurrent))),$K57))+cfg_overhead/60) -> 1.9345572 | AP57: =(cfg_base+cfg_slope*$C57^cfg_exp)*IF($D57="KEY",cfg_mkey,IF($D57="END",cfg_mend,IF($D57="Skippable",cfg_mskip,1))) -> 0.48372112 | AQ57: =IF(OR($AM57="",$AP57=0),"",$AM57/$AP57) -> 3.8589728 | AR57: =IF($F57="","- no task set -",_xlfn.TEXTJOIN(" | ",TRUE,IF(AND($F57<>"gp_value",$AJ57=0),"no items selected",""),IF(AND($F57="gp_value",$AJ57=0),"pick a farming method so the ETC can be estimated",""),IF(AND($F57="gp_value",$AJ57>1),"gp_value takes no item list - one method is enough",""),IF(AND($F57="minigame_completion",$AJ57>1),"only 1 minigame per tile",""),IF(OR($H57="",$H57<=0),"target missing",""),IF(SUMPRODUCT(($L57:$AE57<>"")*(Calc!$C57:$Z57=0))>0,"unknown entry - not in catalogue",""),IF(AND($G57="each",$AJ57=1),"each with 1 entry = same as any",""),IF($AL57="","ETC not computable",""))) -> #N/A | AS57: The key to success is…. | AT57: =IF($F57="","","{"&CHAR(34)&"tileId"&CHAR(34)&":"&$A57&","&CHAR(34)&"taskType"&CHAR(34)&":"&CHAR(34)&$F57&CHAR(34)&","&CHAR(34)&"taskConfig"&CHAR(34)&":{"&IF($F57="gp_value","",IF($F57="minigame_completion",CHAR(34)&"minigame"&CHAR(34)&":"&CHAR(34)&$L57&CHAR(34)&","&CHAR(34)&"message"&CHAR(34)&":"&CHAR(34)&IFERROR(INDEX(minigame_completion!$J$5:$J$47,MATCH($L57,minigame_completion!$A$5:$A$47,0)),"")&CHAR(34)&",",IF($AJ57=1,CHAR(34)&INDEX(Settings!$F$6:$F$13,MATCH($F57,Settings!$E$6:$E$13,0))&CHAR(34)&":"&Calc!$EW57&",",CHAR(34)&INDEX(Settings!$G$6:$G$13,MATCH($F57,Settings!$E$6:$E$13,0))&CHAR(34)&":["&_xlfn.TEXTJOIN(",",TRUE,Calc!$EW57:$FT57)&"],")))&CHAR(34)&"target"&CHAR(34)&":"&$H57&IF($G57="each",","&CHAR(34)&"mode"&CHAR(34)&":"&CHAR(34)&"each"&CHAR(34),"")&"}}") -> {"tileId":66,"taskType":"npc_kill","taskConfig":{"npc":"Bryophyta","target":50}}
A58: 65 | B58: =IFERROR(INDEX(Maze!$C$5:$C$85,MATCH($A58,Maze!$A$5:$A$85,0)),"") -> Arm 3 | C58: =IFERROR(INDEX(Maze!$D$5:$D$85,MATCH($A58,Maze!$A$5:$A$85,0)),"") -> 4 | D58: =IFERROR(INDEX(Maze!$E$5:$E$85,MATCH($A58,Maze!$A$5:$A$85,0)),"") -> Forced | E58: =IFERROR(INDEX(Maze!$G$5:$G$85,MATCH($A58,Maze!$A$5:$A$85,0)),"") -> No | F58: clue_completion | H58: 30 | L58: medium | AJ58: {=SUMPRODUCT(($L58:$AI58<>"")*1)} -> 1 | AK58: =IF($F58="","",IF($G58="each",$AJ58*$H58,$H58)) -> 30 | AL58: =IF($F58="","",IFERROR((IF($G58="each",IF($I58="No",SUM(Calc!$BZ58:$CW58),IF($F58="item_drop",SUM(Calc!$DX58:$EU58),IF($I58="Yes",MAX(Calc!$BZ58:$CW58),SUM(Calc!$BZ58:$CW58)))),$H58/MAX(Calc!$BA58:$BX58)))/IF($J58="",cfg_ratemult,$J58),"")) -> 3.3333333 | AM58: =IF($AL58="","",$AL58/MAX(0.1,IF($K58="",IF($B58="Arm 1",cfg_arm1,IF($B58="Arm 2",cfg_arm2,IF($B58="Arm 3",cfg_arm3,cfg_concurrent))),$K58))+cfg_overhead/60) -> 3.5333333 | AN58: =IF($AM58="","",INT($AM58/24)&"d "&TEXT(MOD($AM58,24),"0.0")&"h") -> 0d 04h | AO58: =IF($AM58="","",$AL58*IFERROR(GAMMAINV(cfg_pct,MAX(1,IF($F58="item_drop",IF($G58="each",$AJ58*$H58,$H58),1000)),1/MAX(1,IF($F58="item_drop",IF($G58="each",$AJ58*$H58,$H58),1000))),1)/MAX(0.1,IF($K58="",IF($B58="Arm 1",cfg_arm1,IF($B58="Arm 2",cfg_arm2,IF($B58="Arm 3",cfg_arm3,cfg_concurrent))),$K58))+cfg_overhead/60) -> 3.6691144 | AP58: =(cfg_base+cfg_slope*$C58^cfg_exp)*IF($D58="KEY",cfg_mkey,IF($D58="END",cfg_mend,IF($D58="Skippable",cfg_mskip,1))) -> 0.52243122 | AQ58: =IF(OR($AM58="",$AP58=0),"",$AM58/$AP58) -> 6.7632508 | AR58: =IF($F58="","- no task set -",_xlfn.TEXTJOIN(" | ",TRUE,IF(AND($F58<>"gp_value",$AJ58=0),"no items selected",""),IF(AND($F58="gp_value",$AJ58=0),"pick a farming method so the ETC can be estimated",""),IF(AND($F58="gp_value",$AJ58>1),"gp_value takes no item list - one method is enough",""),IF(AND($F58="minigame_completion",$AJ58>1),"only 1 minigame per tile",""),IF(OR($H58="",$H58<=0),"target missing",""),IF(SUMPRODUCT(($L58:$AE58<>"")*(Calc!$C58:$Z58=0))>0,"unknown entry - not in catalogue",""),IF(AND($G58="each",$AJ58=1),"each with 1 entry = same as any",""),IF($AL58="","ETC not computable",""))) -> #N/A | AS58: I like my steak medium rare | AT58: =IF($F58="","","{"&CHAR(34)&"tileId"&CHAR(34)&":"&$A58&","&CHAR(34)&"taskType"&CHAR(34)&":"&CHAR(34)&$F58&CHAR(34)&","&CHAR(34)&"taskConfig"&CHAR(34)&":{"&IF($F58="gp_value","",IF($F58="minigame_completion",CHAR(34)&"minigame"&CHAR(34)&":"&CHAR(34)&$L58&CHAR(34)&","&CHAR(34)&"message"&CHAR(34)&":"&CHAR(34)&IFERROR(INDEX(minigame_completion!$J$5:$J$47,MATCH($L58,minigame_completion!$A$5:$A$47,0)),"")&CHAR(34)&",",IF($AJ58=1,CHAR(34)&INDEX(Settings!$F$6:$F$13,MATCH($F58,Settings!$E$6:$E$13,0))&CHAR(34)&":"&Calc!$EW58&",",CHAR(34)&INDEX(Settings!$G$6:$G$13,MATCH($F58,Settings!$E$6:$E$13,0))&CHAR(34)&":["&_xlfn.TEXTJOIN(",",TRUE,Calc!$EW58:$FT58)&"],")))&CHAR(34)&"target"&CHAR(34)&":"&$H58&IF($G58="each",","&CHAR(34)&"mode"&CHAR(34)&":"&CHAR(34)&"each"&CHAR(34),"")&"}}") -> {"tileId":65,"taskType":"clue_completion","taskConfig":{"tier":"medium","target":30}}
A59: 64 | B59: =IFERROR(INDEX(Maze!$C$5:$C$85,MATCH($A59,Maze!$A$5:$A$85,0)),"") -> Arm 3 | C59: =IFERROR(INDEX(Maze!$D$5:$D$85,MATCH($A59,Maze!$A$5:$A$85,0)),"") -> 5 | D59: =IFERROR(INDEX(Maze!$E$5:$E$85,MATCH($A59,Maze!$A$5:$A$85,0)),"") -> Forced | E59: =IFERROR(INDEX(Maze!$G$5:$G$85,MATCH($A59,Maze!$A$5:$A$85,0)),"") -> No | F59: item_drop | G59: each | H59: 1 | L59: Serpentine visage | M59: Magic fang | N59: Tanzanite fang | O59: Uncut onyx | AJ59: {=SUMPRODUCT(($L59:$AI59<>"")*1)} -> 4 | AK59: =IF($F59="","",IF($G59="each",$AJ59*$H59,$H59)) -> 4 | AL59: =IF($F59="","",IFERROR((IF($G59="each",IF($I59="No",SUM(Calc!$BZ59:$CW59),IF($F59="item_drop",SUM(Calc!$DX59:$EU59),IF($I59="Yes",MAX(Calc!$BZ59:$CW59),SUM(Calc!$BZ59:$CW59)))),$H59/MAX(Calc!$BA59:$BX59)))/IF($J59="",cfg_ratemult,$J59),"")) -> 44.444444 | AM59: =IF($AL59="","",$AL59/MAX(0.1,IF($K59="",IF($B59="Arm 1",cfg_arm1,IF($B59="Arm 2",cfg_arm2,IF($B59="Arm 3",cfg_arm3,cfg_concurrent))),$K59))+cfg_overhead/60) -> 44.644444 | AN59: =IF($AM59="","",INT($AM59/24)&"d "&TEXT(MOD($AM59,24),"0.0")&"h") -> 1d 21h | AO59: =IF($AM59="","",$AL59*IFERROR(GAMMAINV(cfg_pct,MAX(1,IF($F59="item_drop",IF($G59="each",$AJ59*$H59,$H59),1000)),1/MAX(1,IF($F59="item_drop",IF($G59="each",$AJ59*$H59,$H59),1000))),1)/MAX(0.1,IF($K59="",IF($B59="Arm 1",cfg_arm1,IF($B59="Arm 2",cfg_arm2,IF($B59="Arm 3",cfg_arm3,cfg_concurrent))),$K59))+cfg_overhead/60) -> 74.430923 | AP59: =(cfg_base+cfg_slope*$C59^cfg_exp)*IF($D59="KEY",cfg_mkey,IF($D59="END",cfg_mend,IF($D59="Skippable",cfg_mskip,1))) -> 0.56802458 | AQ59: =IF(OR($AM59="",$AP59=0),"",$AM59/$AP59) -> 78.595972 | AR59: =IF($F59="","- no task set -",_xlfn.TEXTJOIN(" | ",TRUE,IF(AND($F59<>"gp_value",$AJ59=0),"no items selected",""),IF(AND($F59="gp_value",$AJ59=0),"pick a farming method so the ETC can be estimated",""),IF(AND($F59="gp_value",$AJ59>1),"gp_value takes no item list - one method is enough",""),IF(AND($F59="minigame_completion",$AJ59>1),"only 1 minigame per tile",""),IF(OR($H59="",$H59<=0),"target missing",""),IF(SUMPRODUCT(($L59:$AE59<>"")*(Calc!$C59:$Z59=0))>0,"unknown entry - not in catalogue",""),IF(AND($G59="each",$AJ59=1),"each with 1 entry = same as any",""),IF($AL59="","ETC not computable",""))) -> #N/A | AS59: Live like an ironman | AT59: =IF($F59="","","{"&CHAR(34)&"tileId"&CHAR(34)&":"&$A59&","&CHAR(34)&"taskType"&CHAR(34)&":"&CHAR(34)&$F59&CHAR(34)&","&CHAR(34)&"taskConfig"&CHAR(34)&":{"&IF($F59="gp_value","",IF($F59="minigame_completion",CHAR(34)&"minigame"&CHAR(34)&":"&CHAR(34)&$L59&CHAR(34)&","&CHAR(34)&"message"&CHAR(34)&":"&CHAR(34)&IFERROR(INDEX(minigame_completion!$J$5:$J$47,MATCH($L59,minigame_completion!$A$5:$A$47,0)),"")&CHAR(34)&",",IF($AJ59=1,CHAR(34)&INDEX(Settings!$F$6:$F$13,MATCH($F59,Settings!$E$6:$E$13,0))&CHAR(34)&":"&Calc!$EW59&",",CHAR(34)&INDEX(Settings!$G$6:$G$13,MATCH($F59,Settings!$E$6:$E$13,0))&CHAR(34)&":["&_xlfn.TEXTJOIN(",",TRUE,Calc!$EW59:$FT59)&"],")))&CHAR(34)&"target"&CHAR(34)&":"&$H59&IF($G59="each",","&CHAR(34)&"mode"&CHAR(34)&":"&CHAR(34)&"each"&CHAR(34),"")&"}}") -> {"tileId":64,"taskType":"item_drop","taskConfig":{"items":["Serpentine visage","Magic fang","Tanzanite fang","Uncut onyx"],"target":1,"mode":"each"}}
A60: 55 | B60: =IFERROR(INDEX(Maze!$C$5:$C$85,MATCH($A60,Maze!$A$5:$A$85,0)),"") -> Arm 3 | C60: =IFERROR(INDEX(Maze!$D$5:$D$85,MATCH($A60,Maze!$A$5:$A$85,0)),"") -> 6 | D60: =IFERROR(INDEX(Maze!$E$5:$E$85,MATCH($A60,Maze!$A$5:$A$85,0)),"") -> Forced | E60: =IFERROR(INDEX(Maze!$G$5:$G$85,MATCH($A60,Maze!$A$5:$A$85,0)),"") -> No | F60: xp_gain | G60: each | H60: 100000 | L60: Attack | M60: Strength | N60: Defence | O60: Ranged | P60: Prayer | Q60: Magic | R60: Runecraft | S60: Construction | T60: Hitpoints | U60: Agility | V60: Herblore | W60: Thieving | X60: Crafting | Y60: Fletching | Z60: Slayer | AA60: Hunter | AB60: Mining | AC60: Smithing | AD60: Fishing | AE60: Cooking | AF60: Firemaking | AG60: Woodcutting | AH60: Farming | AI60: Sailing | AJ60: {=SUMPRODUCT(($L60:$AI60<>"")*1)} -> 24 | AK60: =IF($F60="","",IF($G60="each",$AJ60*$H60,$H60)) -> 2400000 | AL60: =IF($F60="","",IFERROR((IF($G60="each",IF($I60="No",SUM(Calc!$BZ60:$CW60),IF($F60="item_drop",SUM(Calc!$DX60:$EU60),IF($I60="Yes",MAX(Calc!$BZ60:$CW60),SUM(Calc!$BZ60:$CW60)))),$H60/MAX(Calc!$BA60:$BX60)))/IF($J60="",cfg_ratemult,$J60),"")) -> 24.208664 | AM60: =IF($AL60="","",$AL60/MAX(0.1,IF($K60="",IF($B60="Arm 1",cfg_arm1,IF($B60="Arm 2",cfg_arm2,IF($B60="Arm 3",cfg_arm3,cfg_concurrent))),$K60))+cfg_overhead/60) -> 24.408664 | AN60: =IF($AM60="","",INT($AM60/24)&"d "&TEXT(MOD($AM60,24),"0.0")&"h") -> 1d 00h | AO60: =IF($AM60="","",$AL60*IFERROR(GAMMAINV(cfg_pct,MAX(1,IF($F60="item_drop",IF($G60="each",$AJ60*$H60,$H60),1000)),1/MAX(1,IF($F60="item_drop",IF($G60="each",$AJ60*$H60,$H60),1000))),1)/MAX(0.1,IF($K60="",IF($B60="Arm 1",cfg_arm1,IF($B60="Arm 2",cfg_arm2,IF($B60="Arm 3",cfg_arm3,cfg_concurrent))),$K60))+cfg_overhead/60) -> 25.394788 | AP60: =(cfg_base+cfg_slope*$C60^cfg_exp)*IF($D60="KEY",cfg_mkey,IF($D60="END",cfg_mend,IF($D60="Skippable",cfg_mskip,1))) -> 0.61997831 | AQ60: =IF(OR($AM60="",$AP60=0),"",$AM60/$AP60) -> 39.370191 | AR60: =IF($F60="","- no task set -",_xlfn.TEXTJOIN(" | ",TRUE,IF(AND($F60<>"gp_value",$AJ60=0),"no items selected",""),IF(AND($F60="gp_value",$AJ60=0),"pick a farming method so the ETC can be estimated",""),IF(AND($F60="gp_value",$AJ60>1),"gp_value takes no item list - one method is enough",""),IF(AND($F60="minigame_completion",$AJ60>1),"only 1 minigame per tile",""),IF(OR($H60="",$H60<=0),"target missing",""),IF(SUMPRODUCT(($L60:$AE60<>"")*(Calc!$C60:$Z60=0))>0,"unknown entry - not in catalogue",""),IF(AND($G60="each",$AJ60=1),"each with 1 entry = same as any",""),IF($AL60="","ETC not computable",""))) -> #N/A | AS60: Jack of all trades | AT60: =IF($F60="","","{"&CHAR(34)&"tileId"&CHAR(34)&":"&$A60&","&CHAR(34)&"taskType"&CHAR(34)&":"&CHAR(34)&$F60&CHAR(34)&","&CHAR(34)&"taskConfig"&CHAR(34)&":{"&IF($F60="gp_value","",IF($F60="minigame_completion",CHAR(34)&"minigame"&CHAR(34)&":"&CHAR(34)&$L60&CHAR(34)&","&CHAR(34)&"message"&CHAR(34)&":"&CHAR(34)&IFERROR(INDEX(minigame_completion!$J$5:$J$47,MATCH($L60,minigame_completion!$A$5:$A$47,0)),"")&CHAR(34)&",",IF($AJ60=1,CHAR(34)&INDEX(Settings!$F$6:$F$13,MATCH($F60,Settings!$E$6:$E$13,0))&CHAR(34)&":"&Calc!$EW60&",",CHAR(34)&INDEX(Settings!$G$6:$G$13,MATCH($F60,Settings!$E$6:$E$13,0))&CHAR(34)&":["&_xlfn.TEXTJOIN(",",TRUE,Calc!$EW60:$FT60)&"],")))&CHAR(34)&"target"&CHAR(34)&":"&$H60&IF($G60="each",","&CHAR(34)&"mode"&CHAR(34)&":"&CHAR(34)&"each"&CHAR(34),"")&"}}") -> {"tileId":55,"taskType":"xp_gain","taskConfig":{"skills":["Attack","Strength","Defence","Ranged","Prayer","Magic","Runecraft","Construction","Hitpoints","Agility","Herblore","Thieving","Crafting","Fletching","Slayer","Hunter","Mining","Smithing","Fishing","Cooking","Firemaking","Woodcutting","Farming","Sailing"],"target":100000,"mode":"each"}}
A61: 56 | B61: =IFERROR(INDEX(Maze!$C$5:$C$85,MATCH($A61,Maze!$A$5:$A$85,0)),"") -> Arm 3 | C61: =IFERROR(INDEX(Maze!$D$5:$D$85,MATCH($A61,Maze!$A$5:$A$85,0)),"") -> 7 | D61: =IFERROR(INDEX(Maze!$E$5:$E$85,MATCH($A61,Maze!$A$5:$A$85,0)),"") -> Forced | E61: =IFERROR(INDEX(Maze!$G$5:$G$85,MATCH($A61,Maze!$A$5:$A$85,0)),"") -> No | F61: item_drop | H61: 1 | L61: Dragon chainbody | AJ61: {=SUMPRODUCT(($L61:$AI61<>"")*1)} -> 1 | AK61: =IF($F61="","",IF($G61="each",$AJ61*$H61,$H61)) -> 1 | AL61: =IF($F61="","",IFERROR((IF($G61="each",IF($I61="No",SUM(Calc!$BZ61:$CW61),IF($F61="item_drop",SUM(Calc!$DX61:$EU61),IF($I61="Yes",MAX(Calc!$BZ61:$CW61),SUM(Calc!$BZ61:$CW61)))),$H61/MAX(Calc!$BA61:$BX61)))/IF($J61="",cfg_ratemult,$J61),"")) -> 3.2 | AM61: =IF($AL61="","",$AL61/MAX(0.1,IF($K61="",IF($B61="Arm 1",cfg_arm1,IF($B61="Arm 2",cfg_arm2,IF($B61="Arm 3",cfg_arm3,cfg_concurrent))),$K61))+cfg_overhead/60) -> 3.4 | AN61: =IF($AM61="","",INT($AM61/24)&"d "&TEXT(MOD($AM61,24),"0.0")&"h") -> 0d 03h | AO61: =IF($AM61="","",$AL61*IFERROR(GAMMAINV(cfg_pct,MAX(1,IF($F61="item_drop",IF($G61="each",$AJ61*$H61,$H61),1000)),1/MAX(1,IF($F61="item_drop",IF($G61="each",$AJ61*$H61,$H61),1000))),1)/MAX(0.1,IF($K61="",IF($B61="Arm 1",cfg_arm1,IF($B61="Arm 2",cfg_arm2,IF($B61="Arm 3",cfg_arm3,cfg_concurrent))),$K61))+cfg_overhead/60) -> 7.5682723 | AP61: =(cfg_base+cfg_slope*$C61^cfg_exp)*IF($D61="KEY",cfg_mkey,IF($D61="END",cfg_mend,IF($D61="Skippable",cfg_mskip,1))) -> 0.6778963 | AQ61: =IF(OR($AM61="",$AP61=0),"",$AM61/$AP61) -> 5.0155164 | AR61: =IF($F61="","- no task set -",_xlfn.TEXTJOIN(" | ",TRUE,IF(AND($F61<>"gp_value",$AJ61=0),"no items selected",""),IF(AND($F61="gp_value",$AJ61=0),"pick a farming method so the ETC can be estimated",""),IF(AND($F61="gp_value",$AJ61>1),"gp_value takes no item list - one method is enough",""),IF(AND($F61="minigame_completion",$AJ61>1),"only 1 minigame per tile",""),IF(OR($H61="",$H61<=0),"target missing",""),IF(SUMPRODUCT(($L61:$AE61<>"")*(Calc!$C61:$Z61=0))>0,"unknown entry - not in catalogue",""),IF(AND($G61="each",$AJ61=1),"each with 1 entry = same as any",""),IF($AL61="","ETC not computable",""))) -> #N/A | AS61: Peak fashion | AT61: =IF($F61="","","{"&CHAR(34)&"tileId"&CHAR(34)&":"&$A61&","&CHAR(34)&"taskType"&CHAR(34)&":"&CHAR(34)&$F61&CHAR(34)&","&CHAR(34)&"taskConfig"&CHAR(34)&":{"&IF($F61="gp_value","",IF($F61="minigame_completion",CHAR(34)&"minigame"&CHAR(34)&":"&CHAR(34)&$L61&CHAR(34)&","&CHAR(34)&"message"&CHAR(34)&":"&CHAR(34)&IFERROR(INDEX(minigame_completion!$J$5:$J$47,MATCH($L61,minigame_completion!$A$5:$A$47,0)),"")&CHAR(34)&",",IF($AJ61=1,CHAR(34)&INDEX(Settings!$F$6:$F$13,MATCH($F61,Settings!$E$6:$E$13,0))&CHAR(34)&":"&Calc!$EW61&",",CHAR(34)&INDEX(Settings!$G$6:$G$13,MATCH($F61,Settings!$E$6:$E$13,0))&CHAR(34)&":["&_xlfn.TEXTJOIN(",",TRUE,Calc!$EW61:$FT61)&"],")))&CHAR(34)&"target"&CHAR(34)&":"&$H61&IF($G61="each",","&CHAR(34)&"mode"&CHAR(34)&":"&CHAR(34)&"each"&CHAR(34),"")&"}}") -> {"tileId":56,"taskType":"item_drop","taskConfig":{"item":"Dragon chainbody","target":1}}
A62: 47 | B62: =IFERROR(INDEX(Maze!$C$5:$C$85,MATCH($A62,Maze!$A$5:$A$85,0)),"") -> Arm 3 | C62: =IFERROR(INDEX(Maze!$D$5:$D$85,MATCH($A62,Maze!$A$5:$A$85,0)),"") -> 8 | D62: =IFERROR(INDEX(Maze!$E$5:$E$85,MATCH($A62,Maze!$A$5:$A$85,0)),"") -> Forced | E62: =IFERROR(INDEX(Maze!$G$5:$G$85,MATCH($A62,Maze!$A$5:$A$85,0)),"") -> No | F62: item_drop | H62: 1 | L62: Beef | AJ62: {=SUMPRODUCT(($L62:$AI62<>"")*1)} -> 1 | AK62: =IF($F62="","",IF($G62="each",$AJ62*$H62,$H62)) -> 1 | AL62: =IF($F62="","",IFERROR((IF($G62="each",IF($I62="No",SUM(Calc!$BZ62:$CW62),IF($F62="item_drop",SUM(Calc!$DX62:$EU62),IF($I62="Yes",MAX(Calc!$BZ62:$CW62),SUM(Calc!$BZ62:$CW62)))),$H62/MAX(Calc!$BA62:$BX62)))/IF($J62="",cfg_ratemult,$J62),"")) -> 8.3333333 | AM62: =IF($AL62="","",$AL62/MAX(0.1,IF($K62="",IF($B62="Arm 1",cfg_arm1,IF($B62="Arm 2",cfg_arm2,IF($B62="Arm 3",cfg_arm3,cfg_concurrent))),$K62))+cfg_overhead/60) -> 8.5333333 | AN62: =IF($AM62="","",INT($AM62/24)&"d "&TEXT(MOD($AM62,24),"0.0")&"h") -> 0d 09h | AO62: =IF($AM62="","",$AL62*IFERROR(GAMMAINV(cfg_pct,MAX(1,IF($F62="item_drop",IF($G62="each",$AJ62*$H62,$H62),1000)),1/MAX(1,IF($F62="item_drop",IF($G62="each",$AJ62*$H62,$H62),1000))),1)/MAX(0.1,IF($K62="",IF($B62="Arm 1",cfg_arm1,IF($B62="Arm 2",cfg_arm2,IF($B62="Arm 3",cfg_arm3,cfg_concurrent))),$K62))+cfg_overhead/60) -> 19.388209 | AP62: =(cfg_base+cfg_slope*$C62^cfg_exp)*IF($D62="KEY",cfg_mkey,IF($D62="END",cfg_mend,IF($D62="Skippable",cfg_mskip,1))) -> 0.74146361 | AQ62: =IF(OR($AM62="",$AP62=0),"",$AM62/$AP62) -> 11.508769 | AR62: =IF($F62="","- no task set -",_xlfn.TEXTJOIN(" | ",TRUE,IF(AND($F62<>"gp_value",$AJ62=0),"no items selected",""),IF(AND($F62="gp_value",$AJ62=0),"pick a farming method so the ETC can be estimated",""),IF(AND($F62="gp_value",$AJ62>1),"gp_value takes no item list - one method is enough",""),IF(AND($F62="minigame_completion",$AJ62>1),"only 1 minigame per tile",""),IF(OR($H62="",$H62<=0),"target missing",""),IF(SUMPRODUCT(($L62:$AE62<>"")*(Calc!$C62:$Z62=0))>0,"unknown entry - not in catalogue",""),IF(AND($G62="each",$AJ62=1),"each with 1 entry = same as any",""),IF($AL62="","ETC not computable",""))) -> #N/A | AS62: Beef Wellington | AT62: =IF($F62="","","{"&CHAR(34)&"tileId"&CHAR(34)&":"&$A62&","&CHAR(34)&"taskType"&CHAR(34)&":"&CHAR(34)&$F62&CHAR(34)&","&CHAR(34)&"taskConfig"&CHAR(34)&":{"&IF($F62="gp_value","",IF($F62="minigame_completion",CHAR(34)&"minigame"&CHAR(34)&":"&CHAR(34)&$L62&CHAR(34)&","&CHAR(34)&"message"&CHAR(34)&":"&CHAR(34)&IFERROR(INDEX(minigame_completion!$J$5:$J$47,MATCH($L62,minigame_completion!$A$5:$A$47,0)),"")&CHAR(34)&",",IF($AJ62=1,CHAR(34)&INDEX(Settings!$F$6:$F$13,MATCH($F62,Settings!$E$6:$E$13,0))&CHAR(34)&":"&Calc!$EW62&",",CHAR(34)&INDEX(Settings!$G$6:$G$13,MATCH($F62,Settings!$E$6:$E$13,0))&CHAR(34)&":["&_xlfn.TEXTJOIN(",",TRUE,Calc!$EW62:$FT62)&"],")))&CHAR(34)&"target"&CHAR(34)&":"&$H62&IF($G62="each",","&CHAR(34)&"mode"&CHAR(34)&":"&CHAR(34)&"each"&CHAR(34),"")&"}}") -> {"tileId":47,"taskType":"item_drop","taskConfig":{"item":"Beef","target":1}}
A63: 46 | B63: =IFERROR(INDEX(Maze!$C$5:$C$85,MATCH($A63,Maze!$A$5:$A$85,0)),"") -> Arm 3 | C63: =IFERROR(INDEX(Maze!$D$5:$D$85,MATCH($A63,Maze!$A$5:$A$85,0)),"") -> 9 | D63: =IFERROR(INDEX(Maze!$E$5:$E$85,MATCH($A63,Maze!$A$5:$A$85,0)),"") -> Forced | E63: =IFERROR(INDEX(Maze!$G$5:$G$85,MATCH($A63,Maze!$A$5:$A$85,0)),"") -> No | F63: item_drop | G63: each | H63: 1 | L63: Ice element staff crown | M63: Fire element staff crown | AJ63: {=SUMPRODUCT(($L63:$AI63<>"")*1)} -> 2 | AK63: =IF($F63="","",IF($G63="each",$AJ63*$H63,$H63)) -> 2 | AL63: =IF($F63="","",IFERROR((IF($G63="each",IF($I63="No",SUM(Calc!$BZ63:$CW63),IF($F63="item_drop",SUM(Calc!$DX63:$EU63),IF($I63="Yes",MAX(Calc!$BZ63:$CW63),SUM(Calc!$BZ63:$CW63)))),$H63/MAX(Calc!$BA63:$BX63)))/IF($J63="",cfg_ratemult,$J63),"")) -> 7.5 | AM63: =IF($AL63="","",$AL63/MAX(0.1,IF($K63="",IF($B63="Arm 1",cfg_arm1,IF($B63="Arm 2",cfg_arm2,IF($B63="Arm 3",cfg_arm3,cfg_concurrent))),$K63))+cfg_overhead/60) -> 7.7 | AN63: =IF($AM63="","",INT($AM63/24)&"d "&TEXT(MOD($AM63,24),"0.0")&"h") -> 0d 08h | AO63: =IF($AM63="","",$AL63*IFERROR(GAMMAINV(cfg_pct,MAX(1,IF($F63="item_drop",IF($G63="each",$AJ63*$H63,$H63),1000)),1/MAX(1,IF($F63="item_drop",IF($G63="each",$AJ63*$H63,$H63),1000))),1)/MAX(0.1,IF($K63="",IF($B63="Arm 1",cfg_arm1,IF($B63="Arm 2",cfg_arm2,IF($B63="Arm 3",cfg_arm3,cfg_concurrent))),$K63))+cfg_overhead/60) -> 14.786451 | AP63: =(cfg_base+cfg_slope*$C63^cfg_exp)*IF($D63="KEY",cfg_mkey,IF($D63="END",cfg_mend,IF($D63="Skippable",cfg_mskip,1))) -> 0.81042128 | AQ63: =IF(OR($AM63="",$AP63=0),"",$AM63/$AP63) -> 9.5012313 | AR63: =IF($F63="","- no task set -",_xlfn.TEXTJOIN(" | ",TRUE,IF(AND($F63<>"gp_value",$AJ63=0),"no items selected",""),IF(AND($F63="gp_value",$AJ63=0),"pick a farming method so the ETC can be estimated",""),IF(AND($F63="gp_value",$AJ63>1),"gp_value takes no item list - one method is enough",""),IF(AND($F63="minigame_completion",$AJ63>1),"only 1 minigame per tile",""),IF(OR($H63="",$H63<=0),"target missing",""),IF(SUMPRODUCT(($L63:$AE63<>"")*(Calc!$C63:$Z63=0))>0,"unknown entry - not in catalogue",""),IF(AND($G63="each",$AJ63=1),"each with 1 entry = same as any",""),IF($AL63="","ETC not computable",""))) -> #N/A | AS63: A Song of Ice and Fire | AT63: =IF($F63="","","{"&CHAR(34)&"tileId"&CHAR(34)&":"&$A63&","&CHAR(34)&"taskType"&CHAR(34)&":"&CHAR(34)&$F63&CHAR(34)&","&CHAR(34)&"taskConfig"&CHAR(34)&":{"&IF($F63="gp_value","",IF($F63="minigame_completion",CHAR(34)&"minigame"&CHAR(34)&":"&CHAR(34)&$L63&CHAR(34)&","&CHAR(34)&"message"&CHAR(34)&":"&CHAR(34)&IFERROR(INDEX(minigame_completion!$J$5:$J$47,MATCH($L63,minigame_completion!$A$5:$A$47,0)),"")&CHAR(34)&",",IF($AJ63=1,CHAR(34)&INDEX(Settings!$F$6:$F$13,MATCH($F63,Settings!$E$6:$E$13,0))&CHAR(34)&":"&Calc!$EW63&",",CHAR(34)&INDEX(Settings!$G$6:$G$13,MATCH($F63,Settings!$E$6:$E$13,0))&CHAR(34)&":["&_xlfn.TEXTJOIN(",",TRUE,Calc!$EW63:$FT63)&"],")))&CHAR(34)&"target"&CHAR(34)&":"&$H63&IF($G63="each",","&CHAR(34)&"mode"&CHAR(34)&":"&CHAR(34)&"each"&CHAR(34),"")&"}}") -> {"tileId":46,"taskType":"item_drop","taskConfig":{"items":["Ice element staff crown","Fire element staff crown"],"target":1,"mode":"each"}}
